Workbook

Sheet Start Here
A1: CCCL SPONSORSHIP PIPELINE
A2: Find sponsors, pitch them, follow up, collect, and deliver what was promised. Built for Cody Purtell by Kyle. Opens in Google Sheets or Excel.
B4: THE STAGES
B5: Prospect | C5: Researched, not contacted yet.
B6: Contacted | C6: Pitch sent or a conversation started. Set a next follow-up date.
B7: Interested | C7: They replied and want to hear more.
B8: Proposal sent | C8: They have the package and price.
B9: Signed | C9: They said yes and agreed an amount. Not money yet.
B10: Paid | C10: The money is in the account. Only this counts as revenue.
B11: Not now | C11: Said no or not this year. Leave a note and try again next season.
B13: EVERY WEEK (15 MINUTES)
A14: 1 | B14: Monday | C14: Open Summary. Anyone marked DUE gets a follow-up today. Claude can draft them.
A15: 2 | B15: New sponsor signed | C15: Set Stage to Signed, fill in the package and amount, and add them to the Fulfilment tab.
A16: 3 | B16: Money arrives | C16: Set Stage to Paid and fill in Amount paid.
A17: 4 | B17: Before the show | C17: Check Fulfilment: banners hung, posts done, tickets sent.
A18: 5 | B18: After the show | C18: Send every sponsor a photo and a thank-you. Mark it on Fulfilment. That's how they come back next year.
B20: TABS
B21: Summary | C21: Money agreed vs paid, follow-ups due, packages sold.
B22: Pipeline | C22: Every business, one row each. Yellow columns are yours. Grey columns came from research.
B23: Packages | C23: Cody's sponsor packages (Title $7,500 down to Community $300-500, plus VIP tables).
B24: Fulfilment | C24: What each sponsor was promised and whether it's done.
B26: ABOUT THE LIST
B27: Where it came from | C27: The 2026 Title Sponsor, 70 local businesses and 24 national and Ontario brands (rows marked 'Brand:' in the Area column), researched by Claude from public websites in October 2026. Phone numbers and emails are each business's public contact details. Check them before reaching out.
B28: Existing supporters | C28: 2026 sponsors (Cody, Oct 20, 2026): Dillabough Millwrighting & Welding (Title, $7,500), Dixie Lee, Pinestone Resort, IT STIX Signs & Graphics and ICO; most were Bronze. Businesses marked 'Yes (logo on gym wall)' support the gym but weren't May 2 sponsors. Start with both groups: thank them first, then pitch 2027. Cody has promised some sponsors spots at future Apsley, Bancroft and Haliburton shows: check with him before pitching for those towns. Add the other 2026 sponsors when Cody lists them.
B29: Brands | C29: Start with Hayabusa (Kingston fight gear), BioSteel / Canadian Protein and MuscleTech / Six Star. Ask for product first (fighter bags, a sampling table, prize packs), then cash once there are 2027 crowd numbers. Anything a fighter receives must be worth under $300 in total (amateur rule); no raffle without a lottery licence. Alcohol and energy drinks stay away from youth bouts and kids' content; Proper No. Twelve only for a 19+ show or area, and only after checking with the AGCO and the venue.
B30: Show column | C30: No 2027 show is booked yet, so every row says 'Not booked yet'. Change it once Cody confirms a town and date. Never name a town or date in a pitch until then.
B31: Colour key | C31: Yellow cells with blue text are yours to fill in. Black text is calculated. Don't type over it.

Sheet Summary
A1: SPONSORSHIP SUMMARY
A2: Updates by itself from the Pipeline tab. Nothing to type here except the goals in yellow.
A4: GOALS
A5: Sponsorship goal for the next show ($) | B5: 18000 | F5: The first show raised $18,000 from 15 sponsors (Cody). With 4+ shows in 2027, set a goal for each show. The Event Profit Predictor shows how much each venue needs to break even on a low night.
A6: Number of sponsors wanted | B6: 15 | F6: Same as 2026.
A8: WHERE THE MONEY IS
A9: Stage | B9: Businesses | C9: Dollars agreed | D9: Dollars paid
A10: Prospect | B10: =COUNTIFS(Pipeline!$H$5:$H$304,"Prospect",Pipeline!$B$5:$B$304,"<>") -> 95 | C10: =SUMIFS(Pipeline!$J$5:$J$304,Pipeline!$H$5:$H$304,"Prospect") -> 0 | D10: =SUMIFS(Pipeline!$K$5:$K$304,Pipeline!$H$5:$H$304,"Prospect") -> 0
A11: Contacted | B11: =COUNTIFS(Pipeline!$H$5:$H$304,"Contacted",Pipeline!$B$5:$B$304,"<>") -> 0 | C11: =SUMIFS(Pipeline!$J$5:$J$304,Pipeline!$H$5:$H$304,"Contacted") -> 0 | D11: =SUMIFS(Pipeline!$K$5:$K$304,Pipeline!$H$5:$H$304,"Contacted") -> 0
A12: Interested | B12: =COUNTIFS(Pipeline!$H$5:$H$304,"Interested",Pipeline!$B$5:$B$304,"<>") -> 0 | C12: =SUMIFS(Pipeline!$J$5:$J$304,Pipeline!$H$5:$H$304,"Interested") -> 0 | D12: =SUMIFS(Pipeline!$K$5:$K$304,Pipeline!$H$5:$H$304,"Interested") -> 0
A13: Proposal sent | B13: =COUNTIFS(Pipeline!$H$5:$H$304,"Proposal sent",Pipeline!$B$5:$B$304,"<>") -> 0 | C13: =SUMIFS(Pipeline!$J$5:$J$304,Pipeline!$H$5:$H$304,"Proposal sent") -> 0 | D13: =SUMIFS(Pipeline!$K$5:$K$304,Pipeline!$H$5:$H$304,"Proposal sent") -> 0
A14: Signed | B14: =COUNTIFS(Pipeline!$H$5:$H$304,"Signed",Pipeline!$B$5:$B$304,"<>") -> 0 | C14: =SUMIFS(Pipeline!$J$5:$J$304,Pipeline!$H$5:$H$304,"Signed") -> 0 | D14: =SUMIFS(Pipeline!$K$5:$K$304,Pipeline!$H$5:$H$304,"Signed") -> 0
A15: Paid | B15: =COUNTIFS(Pipeline!$H$5:$H$304,"Paid",Pipeline!$B$5:$B$304,"<>") -> 0 | C15: =SUMIFS(Pipeline!$J$5:$J$304,Pipeline!$H$5:$H$304,"Paid") -> 0 | D15: =SUMIFS(Pipeline!$K$5:$K$304,Pipeline!$H$5:$H$304,"Paid") -> 0
A16: Not now | B16: =COUNTIFS(Pipeline!$H$5:$H$304,"Not now",Pipeline!$B$5:$B$304,"<>") -> 0 | C16: =SUMIFS(Pipeline!$J$5:$J$304,Pipeline!$H$5:$H$304,"Not now") -> 0 | D16: =SUMIFS(Pipeline!$K$5:$K$304,Pipeline!$H$5:$H$304,"Not now") -> 0
A17: Total | B17: =SUM(B10:B16) -> 95 | C17: =SUM(C10:C16) -> 0 | D17: =SUM(D10:D16) -> 0
A19: SCOREBOARD
A20: Signed or paid ($ agreed) | B20: =SUMIFS(Pipeline!$J$5:$J$304,Pipeline!$H$5:$H$304,"Signed")+SUMIFS(Pipeline!$J$5:$J$304,Pipeline!$H$5:$H$304,"Paid") -> 0
A21: Money actually received | B21: =SUM(Pipeline!$K$5:$K$304) -> 0
A22: Still to collect from signed sponsors | B22: =MAX(0,B20-B21) -> 0
A23: % of goal received | B23: =IF($B$5=0,0,B21/$B$5) -> 0
A24: Sponsors signed or paid | B24: =COUNTIFS(Pipeline!$H$5:$H$304,"Signed",Pipeline!$B$5:$B$304,"<>")+COUNTIFS(Pipeline!$H$5:$H$304,"Paid",Pipeline!$B$5:$B$304,"<>") -> 0
A25: Follow-ups due today or overdue | B25: =COUNTIF(Pipeline!$T$5:$T$304,"DUE") -> 0
A26: Businesses not contacted yet | B26: =COUNTIFS(Pipeline!$H$5:$H$304,"Prospect",Pipeline!$B$5:$B$304,"<>") -> 95
A28: PACKAGES SOLD
A29: Package | B29: Price ($) | C29: Sold (signed or paid) | D29: Slots | E29: Left
A30: Title Sponsor | B30: =Packages!B5 -> 7500 | C30: =COUNTIFS(Pipeline!$I$5:$I$304,"Title Sponsor",Pipeline!$H$5:$H$304,"Signed")+COUNTIFS(Pipeline!$I$5:$I$304,"Title Sponsor",Pipeline!$H$5:$H$304,"Paid") -> 0 | D30: =Packages!D5 -> 1 | E30: =MAX(0,D30-C30) -> 1
A31: Gold Sponsor | B31: =Packages!B6 -> 4000 | C31: =COUNTIFS(Pipeline!$I$5:$I$304,"Gold Sponsor",Pipeline!$H$5:$H$304,"Signed")+COUNTIFS(Pipeline!$I$5:$I$304,"Gold Sponsor",Pipeline!$H$5:$H$304,"Paid") -> 0 | D31: =Packages!D6 -> 2 | E31: =MAX(0,D31-C31) -> 2
A32: Silver Sponsor | B32: =Packages!B7 -> 2000 | C32: =COUNTIFS(Pipeline!$I$5:$I$304,"Silver Sponsor",Pipeline!$H$5:$H$304,"Signed")+COUNTIFS(Pipeline!$I$5:$I$304,"Silver Sponsor",Pipeline!$H$5:$H$304,"Paid") -> 0 | D32: =Packages!D7 -> 4 | E32: =MAX(0,D32-C32) -> 4
A33: Bronze Sponsor | B33: =Packages!B8 -> 1000 | C33: =COUNTIFS(Pipeline!$I$5:$I$304,"Bronze Sponsor",Pipeline!$H$5:$H$304,"Signed")+COUNTIFS(Pipeline!$I$5:$I$304,"Bronze Sponsor",Pipeline!$H$5:$H$304,"Paid") -> 0 | D33: =Packages!D8 -> 10 | E33: =MAX(0,D33-C33) -> 10
A34: Community Sponsor | B34: =Packages!B9 -> 300 | C34: =COUNTIFS(Pipeline!$I$5:$I$304,"Community Sponsor",Pipeline!$H$5:$H$304,"Signed")+COUNTIFS(Pipeline!$I$5:$I$304,"Community Sponsor",Pipeline!$H$5:$H$304,"Paid") -> 0 | D34: =Packages!D9 -> 20 | E34: =MAX(0,D34-C34) -> 20
A35: In-kind Partner | B35: =Packages!B10 -> 0 | C35: =COUNTIFS(Pipeline!$I$5:$I$304,"In-kind Partner",Pipeline!$H$5:$H$304,"Signed")+COUNTIFS(Pipeline!$I$5:$I$304,"In-kind Partner",Pipeline!$H$5:$H$304,"Paid") -> 0 | D35: =Packages!D10 -> 6 | E35: =MAX(0,D35-C35) -> 6
A36: VIP Corporate Table | B36: =Packages!B11 -> 1500 | C36: =COUNTIFS(Pipeline!$I$5:$I$304,"VIP Corporate Table",Pipeline!$H$5:$H$304,"Signed")+COUNTIFS(Pipeline!$I$5:$I$304,"VIP Corporate Table",Pipeline!$H$5:$H$304,"Paid") -> 0 | D36: =Packages!D11 -> 6 | E36: =MAX(0,D36-C36) -> 6

Sheet Pipeline
A1: CCCL SPONSORSHIP PIPELINE
A2: One row per business. Move the Stage as things happen. Only 'Paid' counts as money in the bank. Yellow columns are yours to fill in; grey ones come from research.
A4: # | B4: Business | C4: Town | D4: Area | E4: Category | F4: Existing supporter? | G4: Suggested package | H4: Stage | I4: Package agreed | J4: Amount agreed ($) | K4: Amount paid ($) | L4: Show | M4: Owner | N4: Contact person | O4: Phone | P4: Email | Q4: Website | R4: Last contact | S4: Next follow-up | T4: Follow-up due? | U4: Why they fit | V4: Notes | W4: Source
A5: 1 | B5: Dillabough Millwrighting & Welding | C5: Bancroft | D5: North Hastings | E5: Millwright & welding shop | F5: Yes (2026 Title Sponsor) | G5: Title Sponsor | H5: Prospect | L5: Not booked yet | M5: Cody | T5: =IF(OR(B5="",H5="Paid",H5="Not now",S5=""),"",IF(S5<=TODAY(),"DUE","")) | U5: 2026 Title Sponsor ($7,500). Thank them first, then offer Title again for 2027 before anyone else. | W5: https://www.canpages.ca/page/ON/bancroft/dillabough-millwrighting-welding/7238519
A6: 2 | B6: Pinestone Resort & Conference Centre | C6: Haliburton | D6: Haliburton County | E6: Resort / golf / conference centre | F6: Yes (2026 sponsor) | G6: Bronze Sponsor | H6: Prospect | L6: Not booked yet | M6: Cody | O6: 705-457-1800 | P6: reservations@pinestone-resort.com | Q6: https://pinestone-resort.com/ | T6: =IF(OR(B6="",H6="Paid",H6="Not now",S6=""),"",IF(S6<=TODAY(),"DUE","")) | U6: Haliburton resort with 18-hole golf, Stone 21 dining and event space a few minutes from A.J. LaRue Arena; natural fit for fighter/out-of-town guest rooms or a weigh-in/after-party venue. | W6: https://kawarthanow.com/venue/1511/pinestone-resort-conference-centre
A7: 3 | B7: Dixie Lee Fried Chicken (Bancroft) | C7: Bancroft | D7: North Hastings | E7: Restaurant (fast food) | F7: Yes (2026 sponsor) | G7: Bronze Sponsor | H7: Prospect | L7: Not booked yet | M7: Cody | O7: 613-703-7178 | Q7: https://www.dixieleefriedchicken.com/ | T7: =IF(OR(B7="",H7="Paid",H7="Not now",S7=""),"",IF(S7<=TODAY(),"DUE","")) | U7: Bancroft fried-chicken franchise at 121 Hastings St N; easy fit for fight-night food tie-ins or a fighter-meal promo. | W7: https://www.circulaire-en-ligne.ca/annuaire/ON/dixie-lee-fried-chicken/bancroft-121-hastings-st-n
A8: 4 | B8: IT STIX Signs & Graphics Inc. | C8: Bancroft | D8: North Hastings | E8: Sign shop / graphics / web design | F8: Yes (2026 sponsor) | G8: Bronze Sponsor | H8: Prospect | L8: Not booked yet | M8: Cody | O8: 613-334-5344 | P8: itstix@itstix.ca | Q8: https://itstix.ca/ | T8: =IF(OR(B8="",H8="Paid",H8="Not now",S8=""),"",IF(S8<=TODAY(),"DUE","")) | U8: Bancroft sign, banner and web-design shop; ideal in-kind partner for event banners and sponsor signage in exchange for logo placement. | W8: https://itstix.ca/contact/
A9: 5 | B9: Quality Cedar Products | C9: Bancroft | D9: North Hastings | E9: Building supply / lumber (western red cedar) | F9: Yes (logo on gym wall) | G9: Bronze Sponsor | H9: Prospect | L9: Not booked yet | M9: Cody | O9: 289-633-3335 | P9: sales@qualitycedarproducts.ca | Q9: https://www.qualitycedarproducts.ca/ | T9: =IF(OR(B9="",H9="Paid",H9="Not now",S9=""),"",IF(S9<=TODAY(),"DUE","")) | U9: Family-owned Bancroft cedar lumber supplier (decking, siding, sauna) selling to contractors across Ontario; already on the gym wall and sells to the trades crowd. | W9: https://www.qualitycedarproducts.ca/about
A10: 6 | B10: USG Fight Gear (probable match for 'USG' logo) | C10: Brampton | D10: other | E10: Combat sports gear maker | F10: Yes (logo on gym wall) | G10: Community Sponsor | H10: Prospect | L10: Not booked yet | M10: Cody | O10: 647-573-5433 | Q10: https://usgfightgear.com/ | T10: =IF(OR(B10="",H10="Paid",H10="Not now",S10=""),"",IF(S10<=TODAY(),"DUE","")) | U10: Ontario-made boxing/MMA gloves, shin guards and walkout gear, partnered with the Canadian Boxing Federation; most likely the stylized USG logo on the wall. Good for in-kind gear, prizes or fighter kits. | W10: https://usgfightgear.com/
A11: 7 | B11: Bryan Fraser Mechanical Services (not found; closest match Bryan Fraser Contracting Inc.) | C11: Golden Lake (unconfirmed match) | D11: other | E11: Contractor / trades | F11: Yes (logo on gym wall) | G11: Bronze Sponsor | H11: Prospect | L11: Not booked yet | M11: Cody | O11: 613-639-5569 | P11: bryanfraserinc@gmail.com | Q11: https://bryanfrasercontracting.com/ | T11: =IF(OR(B11="",H11="Paid",H11="Not now",S11=""),"",IF(S11<=TODAY(),"DUE","")) | U11: No 'Bryan Fraser Mechanical' found online. Bryan Fraser Contracting Inc. in Golden Lake (custom homes, renos, ICF, decks) exists but may be a different business; confirm with Cody. | V11: Unconfirmed: check the business name and details before contacting. | W11: https://bryanfrasercontracting.com/
A12: 8 | B12: ICO - International Combat Organisation | C12: UK-based (ICO Canada listed as 'TBA') | D12: other | E12: Combat sports sanctioning organization | F12: Yes (2026 sponsor) | G12: Community Sponsor | H12: Prospect | L12: Not booked yet | M12: Cody | O12: +44 7875 138526 | Q12: https://icokickboxing.org/ | T12: =IF(OR(B12="",H12="Paid",H12="Not now",S12=""),"",IF(S12<=TODAY(),"DUE","")) | U12: Amateur kickboxing/MMA/Muay Thai sanctioning body active in 45+ countries; its Canada branch is listed as 'TBA', so the wall logo is likely an affiliation. Treat as a credibility/affiliation partner, not a cash sponsor. | V12: Cody confirmed 'ICO' sponsored May 2, 2026. Which ICO is a guess from the logo: confirm the full name with Cody before contacting. | W12: https://icokickboxing.org/international-members/
A13: 9 | B13: Unidentified '...'s Daughter' boutique (possibly 'Barber's Daughter') | C13: Unverified | D13: other | E13: Clothing boutique | F13: Yes (logo on gym wall) | G13: Community Sponsor | H13: Prospect | L13: Not booked yet | M13: Cody | T13: =IF(OR(B13="",H13="Paid",H13="Not now",S13=""),"",IF(S13<=TODAY(),"DUE","")) | U13: No boutique ending in 'Daughter' found in the Bancroft chamber shopping list, Yellow Pages Haliburton-area clothing stores or My Haliburton Highlands; Facebook pages called 'The Barbers Daughter' exist but none confirmed local. Check the logo or ask Cody. | V13: Unconfirmed: check the business name and details before contacting. | W13: https://bancroftontario.com/single-category/shopping-lifestyle/
A14: 10 | B14: Lockhart Bros. (Contracting) | C14: Unverified (likely Bancroft area) | D14: other | E14: Contractor / trades | F14: Yes (logo on gym wall) | G14: Bronze Sponsor | H14: Prospect | L14: Not booked yet | M14: Cody | Q14: https://www.facebook.com/lockhartbros/ | T14: =IF(OR(B14="",H14="Paid",H14="Not now",S14=""),"",IF(S14<=TODAY(),"DUE","")) | U14: Logo is on the BBG gym wall; a Facebook page 'Lockhart Bros.' exists, but no directory or website confirming town or services was found. Ask Cody for the contact. | V14: Unconfirmed: check the business name and details before contacting. | W14: https://www.facebook.com/lockhartbros/
A15: 11 | B15: R & R Property Services | C15: Unverified (likely Bancroft area) | D15: other | E15: Property services / contractor | F15: Yes (logo on gym wall) | G15: Bronze Sponsor | H15: Prospect | L15: Not booked yet | M15: Cody | Q15: https://www.facebook.com/RR.PR0PERTYSERVICES/ | T15: =IF(OR(B15="",H15="Paid",H15="Not now",S15=""),"",IF(S15<=TODAY(),"DUE","")) | U15: Logo is on the BBG gym wall; a Facebook page named 'R & R Property Services' exists, but its town and services could not be confirmed online. Ask Cody for the contact. | V15: Unconfirmed: check the business name and details before contacting. | W15: https://www.facebook.com/RR.PR0PERTYSERVICES/
A16: 12 | B16: Thomas Contracting | C16: Algonquin Highlands | D16: Haliburton County | E16: Excavation / construction | G16: Community Sponsor | H16: Prospect | L16: Not booked yet | M16: Cody | O16: 705-489-2711 | P16: excavate@thomascontracting.ca | T16: =IF(OR(B16="",H16="Paid",H16="Not now",S16=""),"",IF(S16<=TODAY(),"DUE","")) | U16: Excavation and construction contractor on Hwy 35; local trades business reaching homeowners and cottagers. | W16: https://marketplace.thehighlander.ca/?p=405
A17: 13 | B17: Total Site Services | C17: Dysart et al (Haliburton) | D17: Haliburton County | E17: Excavation / septic / wells | G17: Bronze Sponsor | H17: Prospect | L17: Not booked yet | M17: Cody | O17: 705-457-9558 | P17: info@totalsiteservices.ca | T17: =IF(OR(B17="",H17="Paid",H17="Not now",S17=""),"",IF(S17<=TODAY(),"DUE","")) | U17: Site clearing, excavation, septic and wells on Gelert Rd; heavy-equipment crews match the fight-night audience. | W17: https://marketplace.thehighlander.ca/?p=405
A18: 14 | B18: Sir Sam's Inn & Spa | C18: Eagle Lake (Haliburton) | D18: Haliburton County | E18: Resort / lodge | G18: Bronze Sponsor | H18: Prospect | L18: Not booked yet | M18: Cody | O18: 800-361-2188 | P18: info@sirsamsinn.com | Q18: https://www.sirsamsinn.com | T18: =IF(OR(B18="",H18="Paid",H18="Not now",S18=""),"",IF(S18<=TODAY(),"DUE","")) | U18: Upscale Haliburton resort that hosts weddings and group events; good for fighter/VIP rooms in exchange for a sponsor package. | W18: https://www.sirsamsinn.com
A19: 15 | B19: CARSTAR Haliburton | C19: Haliburton | D19: Haliburton County | E19: Auto repair / body shop | G19: Community Sponsor | H19: Prospect | L19: Not booked yet | M19: Cody | T19: =IF(OR(B19="",H19="Paid",H19="Not now",S19=""),"",IF(S19<=TODAY(),"DUE","")) | U19: 6,500 sq ft collision shop at 154 Industrial Park Dr (sister to CARSTAR Lindsay); local shop wanting name recognition with drivers. | W19: https://www.bodyshopbusiness.com/?p=179383
A20: 16 | B20: Canoe FM 100.9 (CKHA) | C20: Haliburton | D20: Haliburton County | E20: Media partner | G20: Bronze Sponsor | H20: Prospect | L20: Not booked yet | M20: Cody | O20: 705-457-1009 | P20: info@canoefm.com | Q20: https://canoefm.com | T20: =IF(OR(B20="",H20="Paid",H20="Not now",S20=""),"",IF(S20<=TODAY(),"DUE","")) | U20: MEDIA PARTNER: Haliburton community radio, and a proven local sponsor (sponsors the Haliburton Land Trust); propose on-air promo trade. | W20: https://www.canoefm.com
A21: 17 | B21: Country Pickin's | C21: Haliburton | D21: Haliburton County | E21: Clothing / footwear retailer | G21: Community Sponsor | H21: Prospect | L21: Not booked yet | M21: Cody | O21: 705-457-2726 | P21: info@countrypickinshaliburton.ca | T21: =IF(OR(B21="",H21="Paid",H21="Not now",S21=""),"",IF(S21<=TODAY(),"DUE","")) | U21: Haliburton footwear and fashion shop on Highland St; a local retailer reaching event-going shoppers. | W21: https://marketplace.thehighlander.ca/?p=405
A22: 18 | B22: Curry Chevrolet Buick GMC Ltd | C22: Haliburton | D22: Haliburton County | E22: Auto dealer | G22: Silver Sponsor | H22: Prospect | L22: Not booked yet | M22: Cody | O22: 705-457-2100 | Q22: https://currymotors.ca | T22: =IF(OR(B22="",H22="Paid",H22="Not now",S22=""),"",IF(S22<=TODAY(),"DUE","")) | U22: Haliburton's GM truck dealer on County Rd 21; pickups and trucks sell to the same 25-45 crowd that buys fight tickets. | W22: https://www.yellowpages.ca/search/si/1/Car+Dealers/Haliburton+ON
A23: 19 | B23: Emmerson Lumber | C23: Haliburton | D23: Haliburton County | E23: Building supply / lumber | G23: Bronze Sponsor | H23: Prospect | L23: Not booked yet | M23: Cody | O23: 705-457-1550 | P23: information@emmersonlumber.com | Q23: https://emmersonlumber.com | T23: =IF(OR(B23="",H23="Paid",H23="Not now",S23=""),"",IF(S23<=TODAY(),"DUE","")) | U23: Haliburton lumber and design centre that advertises heavily in The Highlander; contractors and trades customers are core fight-night ticket buyers. | W23: https://marketplace.thehighlander.ca/?p=405
A24: 20 | B24: Haliburton RPM (RPM Marinas) | C24: Haliburton | D24: Haliburton County | E24: Powersports / marine dealer | G24: Bronze Sponsor | H24: Prospect | L24: Not booked yet | M24: Cody | O24: 705-457-1473 | P24: info@haliburtonrpm.com | T24: =IF(OR(B24="",H24="Paid",H24="Not now",S24=""),"",IF(S24<=TODAY(),"DUE","")) | U24: Yamaha and Kawasaki boat and powersports showroom on County Rd 21 serving about 3,000 customers; good audience overlap for sleds and ATVs. | W24: https://marketplace.thehighlander.ca/?p=405
A25: 21 | B25: Haliburton Timber Mart | C25: Haliburton | D25: Haliburton County | E25: Building supply / hardware | G25: Bronze Sponsor | H25: Prospect | L25: Not booked yet | M25: Cody | O25: 705-457-2510 | Q25: https://timbermart.ca/en/ | T25: =IF(OR(B25="",H25="Paid",H25="Not now",S25=""),"",IF(S25<=TODAY(),"DUE","")) | U25: Proven local sponsor: listed as a 'Shooting Stars' business sponsor of the Haliburton Highlands Land Trust; serves local trades. | W25: https://www.haliburtonlandtrust.ca/landtruststar/
A26: 22 | B26: Hawk River Construction | C26: Haliburton | D26: Haliburton County | E26: Excavation / site prep / septic | G26: Bronze Sponsor | H26: Prospect | L26: Not booked yet | M26: Cody | O26: 705-457-1386 | P26: info@hawkriver.ca | T26: =IF(OR(B26="",H26="Paid",H26="Not now",S26=""),"",IF(S26<=TODAY(),"DUE","")) | U26: Haliburton site prep, roads, septic and excavation contractor; trades employers like seeing their name in front of local crowds. | W26: https://marketplace.thehighlander.ca/?p=405
A27: 23 | B27: The Highlander (newspaper) | C27: Haliburton | D27: Haliburton County | E27: Media partner | G27: Bronze Sponsor | H27: Prospect | L27: Not booked yet | M27: Cody | O27: 705-457-2900 | P27: Sales@TheHighlander.ca | Q27: https://thehighlander.ca | T27: =IF(OR(B27="",H27="Paid",H27="Not now",S27=""),"",IF(S27<=TODAY(),"DUE","")) | U27: MEDIA PARTNER: Haliburton County weekly that already covered CCCL ('Fight night coming to Haliburton County'); propose ad and coverage trade for logo placement. | W27: https://thehighlander.ca/advertise/
A28: 24 | B28: Haliburton Highlands Brewing | C28: Haliburton (Abbey Gardens) | D28: Haliburton County | E28: Brewery (ALCOHOL) | G28: Community Sponsor | H28: Prospect | L28: Not booked yet | M28: Cody | Q28: https://haliburtonhighlandsbrewing.ca | T28: =IF(OR(B28="",H28="Paid",H28="Not now",S28=""),"",IF(S28<=TODAY(),"DUE","")) | U28: Local craft brewery that champions Highlands events, artists and musicians. Alcohol sponsor: check venue and AGCO rules. | V28: ALCOHOL: Cody decides. Keep their logo off youth bouts and kids' content. | W28: https://haliburtonhighlandsbrewing.ca/aboutus
A29: 25 | B29: Haliburton Forest & Wild Life Reserve | C29: Haliburton (Dysart et al) | D29: Haliburton County | E29: Large regional employer / outdoor tourism | G29: Bronze Sponsor | H29: Prospect | L29: Not booked yet | M29: Cody | O29: 800-631-2198 | P29: reservations@haliburtonforest.com | T29: =IF(OR(B29="",H29="Paid",H29="Not now",S29=""),"",IF(S29<=TODAY(),"DUE","")) | U29: Major outdoor recreation, logging and tourism employer north of Haliburton; reaches outdoorsy locals and visitors. | W29: https://marketplace.thehighlander.ca/?p=405
A30: 26 | B30: Fowler Construction | C30: Haliburton (head office Bracebridge) | D30: Haliburton County | E30: Large regional employer / aggregate & paving | G30: Silver Sponsor | H30: Prospect | L30: Not booked yet | M30: Cody | O30: 705-457-9900 | Q30: https://fowler.ca | T30: =IF(OR(B30="",H30="Paid",H30="Not now",S30=""),"",IF(S30<=TODAY(),"DUE","")) | U30: Big road-building, aggregate and paving company with a Haliburton yard on Gelert Rd; large employer of exactly the crowd that fills arena seats. | W30: https://www.yellowpages.ca/search/si/1/Contractors/Haliburton+ON
A31: 27 | B31: Foodland Haliburton and Foodland Minden | C31: Haliburton / Minden | D31: Haliburton County | E31: Grocery | G31: Community Sponsor | H31: Prospect | L31: Not booked yet | M31: Cody | O31: 705-286-1121 | T31: =IF(OR(B31="",H31="Paid",H31="Not now",S31=""),"",IF(S31<=TODAY(),"DUE","")) | U31: Proven local supporter: the two area Foodland stores sold Haliburton County Huskies merchandise (400 hats, 300 shirts), per Minden Times. Haliburton 705-457-2242. | W31: https://mindentimes.ca/news/huskies-return-bolstered-by-community-support/
A32: 28 | B32: Hudson Henderson Insurance | C32: Haliburton / Minden / Bancroft / Lindsay | D32: Haliburton County | E32: Insurance broker | G32: Bronze Sponsor | H32: Prospect | L32: Not booked yet | M32: Cody | O32: 888-522-4999 | P32: info@hudsonhenderson.com | Q32: https://www.hudsonhenderson.com/ | T32: =IF(OR(B32="",H32="Paid",H32="Not now",S32=""),"",IF(S32<=TODAY(),"DUE","")) | U32: Cottage-country broker with offices in Haliburton, Minden, Bancroft and Lindsay, so one sponsorship covers every 2027 host town. | W32: https://www.hudsonhenderson.com/
A33: 29 | B33: Nomi Resort | C33: Harcourt | D33: Haliburton County | E33: Resort / restaurant / lounge | G33: Bronze Sponsor | H33: Prospect | L33: Not booked yet | M33: Cody | O33: 1-888-765-9951 | P33: stay@nomiresort.com | Q33: https://nomiresort.com | T33: =IF(OR(B33="",H33="Paid",H33="Not now",S33=""),"",IF(S33<=TODAY(),"DUE","")) | U33: Luxury resort with 8fifty restaurant and lounge in Harcourt, Cody's hometown; strong hometown story for a VIP table or presenting package. | W33: https://nomiresort.com
A34: 30 | B34: Boshkung Brewing | C34: Minden | D34: Haliburton County | E34: Brewery / restaurant (ALCOHOL) | G34: Bronze Sponsor | H34: Prospect | L34: Not booked yet | M34: Cody | O34: 705-286-2711 | Q34: https://boshkungbrewing.com | T34: =IF(OR(B34="",H34="Paid",H34="Not now",S34=""),"",IF(S34<=TODAY(),"DUE","")) | U34: Minden brewery and taproom now expanding into a full restaurant; a natural after-party or beer-garden partner. Alcohol sponsor: check venue and AGCO rules. | V34: ALCOHOL: Cody decides. Keep their logo off youth bouts and kids' content. | W34: https://www.boshkungbrewing.com
A35: 31 | B35: Floyd Hall Limited (insurance) | C35: Minden | D35: Haliburton County | E35: Insurance broker | G35: Community Sponsor | H35: Prospect | L35: Not booked yet | M35: Cody | O35: 705-286-1270 | T35: =IF(OR(B35="",H35="Paid",H35="Not now",S35=""),"",IF(S35<=TODAY(),"DUE","")) | U35: Proven local sponsor: listed as a 'Star Gazers' business sponsor of the Haliburton Highlands Land Trust. | W35: https://www.haliburtonlandtrust.ca/landtruststar/
A36: 32 | B36: RE/MAX Professionals North | C36: Minden | D36: Haliburton County | E36: Real estate brokerage | G36: Bronze Sponsor | H36: Prospect | L36: Not booked yet | M36: Cody | T36: =IF(OR(B36="",H36="Paid",H36="Not now",S36=""),"",IF(S36<=TODAY(),"DUE","")) | U36: Proven local sponsor: its Terry Carr team sponsors the Haliburton Land Trust, and at its Minden office opening the owners said they want to be involved in local events. | W36: https://thehighlander.ca/2020/08/25/re-max-professionals-celebrate-grand-opening/
A37: 33 | B37: Ridgewood Ford Sales Ltd | C37: Minden | D37: Haliburton County | E37: Auto dealer | G37: Bronze Sponsor | H37: Prospect | L37: Not booked yet | M37: Cody | O37: 705-286-2890 | Q37: https://ridgewoodford.com | T37: =IF(OR(B37="",H37="Paid",H37="Not now",S37=""),"",IF(S37<=TODAY(),"DUE","")) | U37: Minden Ford dealer on Hwy 35; F-series trucks and a Haliburton County customer base fit a ringside banner. | W37: https://www.yellowpages.ca/search/si/1/Car+Dealers/Haliburton+ON
A38: 34 | B38: The Rockcliffe - Moore Falls | C38: Minden | D38: Haliburton County | E38: Restaurant / bar (ALCOHOL) | G38: Community Sponsor | H38: Prospect | L38: Not booked yet | M38: Cody | P38: info@therockcliffe.ca | T38: =IF(OR(B38="",H38="Paid",H38="Not now",S38=""),"",IF(S38<=TODAY(),"DUE","")) | U38: Minden-area restaurant and bar that could host a viewing party or the after-party. Alcohol sponsor. | V38: ALCOHOL: Cody decides. Keep their logo off youth bouts and kids' content. | W38: https://marketplace.thehighlander.ca/?p=405
A39: 35 | B39: Harper Powersports & Marine | C39: Minden / Haliburton | D39: Haliburton County | E39: Powersports / marine dealer | G39: Silver Sponsor | H39: Prospect | L39: Not booked yet | M39: Cody | O39: 705-286-2750 | Q39: https://www.harper-marine.com | T39: =IF(OR(B39="",H39="Paid",H39="Not now",S39=""),"",IF(S39<=TODAY(),"DUE","")) | U39: Authorized BRP dealer (Ski-Doo, Can-Am, Sea-Doo) with Minden and Haliburton stores; sells sleds and side-by-sides to the same young rural crowd that buys fight tickets. | W39: https://www.harper-marine.com
A40: 36 | B40: Harcourt TIM-BR Mart | C40: Wilberforce (Harcourt area) | D40: Haliburton County | E40: Building supply / hardware | G40: Community Sponsor | H40: Prospect | L40: Not booked yet | M40: Cody | O40: 705-448-2268 | T40: =IF(OR(B40="",H40="Paid",H40="Not now",S40=""),"",IF(S40<=TODAY(),"DUE","")) | U40: Small Highlands East building centre near Harcourt, Cody's hometown; a hometown angle for a small banner. | W40: https://www.yellowpages.ca/search/si/1/Hardware+Stores/Bancroft+ON
A41: 37 | B41: 97.7 Moose FM / My Bancroft Now | C41: Bancroft | D41: North Hastings | E41: Media partner | G41: Bronze Sponsor | H41: Prospect | L41: Not booked yet | M41: Cody | O41: 613-332-1423 | Q41: https://www.mybancroftnow.com | T41: =IF(OR(B41="",H41="Paid",H41="Not now",S41=""),"",IF(S41<=TODAY(),"DUE","")) | U41: MEDIA PARTNER: Bancroft's commercial radio station and news site; propose on-air ticket giveaways and promo trade. | W41: https://www.mybancroftnow.com/contact-us/
A42: 38 | B42: Bancroft Brew Pub | C42: Bancroft | D42: North Hastings | E42: Pub / restaurant (ALCOHOL) | G42: Community Sponsor | H42: Prospect | L42: Not booked yet | M42: Cody | Q42: https://www.bancroftbrewpub.ca/ | T42: =IF(OR(B42="",H42="Paid",H42="Not now",S42=""),"",IF(S42<=TODAY(),"DUE","")) | U42: Downtown Bancroft pub with live entertainment; natural official after-party or watch-party venue. Alcohol sponsor. | V42: ALCOHOL: Cody decides. Keep their logo off youth bouts and kids' content. | W42: https://hastings.ca/adventures/experiences/bancroft-brew-pub
A43: 39 | B43: Bancroft Home Hardware | C43: Bancroft | D43: North Hastings | E43: Building supply / hardware | G43: Bronze Sponsor | H43: Prospect | L43: Not booked yet | M43: Cody | O43: 613-332-2227 | Q43: https://www.homehardware.ca | T43: =IF(OR(B43="",H43="Paid",H43="Not now",S43=""),"",IF(S43<=TODAY(),"DUE","")) | U43: Bancroft's 50-year hardware store (formerly 'Wade's') under new owners keen to keep serving the community. | W43: https://www.bancroftthisweek.com/home-hardware-starts-a-new-chapter-in-its-50-year-history/
A44: 40 | B44: Bancroft This Week | C44: Bancroft | D44: North Hastings | E44: Media partner | G44: Bronze Sponsor | H44: Prospect | L44: Not booked yet | M44: Cody | O44: 613-332-2002 | Q44: https://www.bancroftthisweek.com | T44: =IF(OR(B44="",H44="Paid",H44="Not now",S44=""),"",IF(S44<=TODAY(),"DUE","")) | U44: MEDIA PARTNER: Bancroft weekly that has already profiled Bancroft Boxing & Grappling and CCCL; propose ad and coverage trade. | W44: https://www.bancroftthisweek.com/contact-information
A45: 41 | B45: Boyer Chevrolet Buick GMC Bancroft | C45: Bancroft | D45: North Hastings | E45: Auto dealer | G45: Silver Sponsor | H45: Prospect | L45: Not booked yet | M45: Cody | O45: 613-332-2438 | Q45: https://www.boyergmbancroft.com/ | T45: =IF(OR(B45="",H45="Paid",H45="Not now",S45=""),"",IF(S45<=TODAY(),"DUE","")) | U45: Proven local sponsor: sponsored the Bancroft Motors Midget Jets and the North Kawartha Knights Jr C, and Boyer Auto Group appears on the Knights' schedule; trucks fit the fight-night crowd. | W45: https://www.bancroftthisweek.com/boyer-auto-group-happy-to-be-in-bancroft/
A46: 42 | B46: Kawartha Credit Union - Bancroft branch | C46: Bancroft | D46: North Hastings | E46: Credit union | G46: Bronze Sponsor | H46: Prospect | L46: Not booked yet | M46: Cody | O46: 1-855-670-0510 | Q46: https://www.kawarthacu.com/ | T46: =IF(OR(B46="",H46="Paid",H46="Not now",S46=""),"",IF(S46<=TODAY(),"DUE","")) | U46: Regional credit union with a Bancroft branch (it absorbed the Coe Hill branch); credit unions sponsor community events in their branch towns. | W46: https://www.circulaire-en-ligne.ca/annuaire/ON/kawartha-credit-union/bancroft-90c-hastings-street-north
A47: 43 | B47: Lucky Duck Tattoo | C47: Bancroft | D47: North Hastings | E47: Tattoo shop | G47: Community Sponsor | H47: Prospect | L47: Not booked yet | M47: Cody | O47: 613-332-1331 | T47: =IF(OR(B47="",H47="Paid",H47="Not now",S47=""),"",IF(S47<=TODAY(),"DUE","")) | U47: Bancroft tattoo shop on Hastings St N; same fan overlap, and a cheap small-tier banner. | W47: https://www.yellowpages.ca/search/si/1/Tattoos/Bancroft+ON
A48: 44 | B48: Lynval Contracting Ltd | C48: Bancroft | D48: North Hastings | E48: Excavation / aggregate / septic | G48: Bronze Sponsor | H48: Prospect | L48: Not booked yet | M48: Cody | O48: 613-332-6010 | Q48: https://lynval.net | T48: =IF(OR(B48="",H48="Paid",H48="Not now",S48=""),"",IF(S48<=TODAY(),"DUE","")) | U48: Bancroft excavating, hydro-line, aggregate, septic and dumpster contractor; a big local trades employer. | W48: https://lynval.net
A49: 45 | B49: Niffers Clothing | C49: Bancroft | D49: North Hastings | E49: Clothing retailer | G49: Community Sponsor | H49: Prospect | L49: Not booked yet | M49: Cody | O49: 613-334-6354 | T49: =IF(OR(B49="",H49="Paid",H49="Not now",S49=""),"",IF(S49<=TODAY(),"DUE","")) | U49: Bancroft clothing store listed by the chamber; possible fight-night merch or apparel partner. | W49: https://bancroftontario.com/directory/niffers-clothing/
A50: 46 | B50: North Hastings Tire & Auto | C50: Bancroft | D50: North Hastings | E50: Auto repair / tires | G50: Community Sponsor | H50: Prospect | L50: Not booked yet | M50: Cody | O50: 613-332-5337 | Q50: https://nhauto.ca | T50: =IF(OR(B50="",H50="Paid",H50="Not now",S50=""),"",IF(S50<=TODAY(),"DUE","")) | U50: Bancroft tire and repair shop on Hwy 62; truck and ATV owners are its customers and fight fans. | W50: https://www.yellowpages.ca/search/si/1/Auto+Repair/Bancroft+ON
A51: 47 | B51: Paul Price Ford Sales Inc | C51: Bancroft | D51: North Hastings | E51: Auto dealer | G51: Bronze Sponsor | H51: Prospect | L51: Not booked yet | M51: Cody | O51: 1-877-798-7431 | Q51: http://www.paulpriceford.com/ | T51: =IF(OR(B51="",H51="Paid",H51="Not now",S51=""),"",IF(S51<=TODAY(),"DUE","")) | U51: Bancroft-area Ford dealer listed on Hastings St N; F-150 buyers are the core 25-45 ticket demographic. | W51: https://www.yellowpages.ca/search/si/1/Auto+Repair/Bancroft+ON
A52: 48 | B52: RONA Bancroft | C52: Bancroft | D52: North Hastings | E52: Building supply / hardware | G52: Bronze Sponsor | H52: Prospect | L52: Not booked yet | M52: Cody | O52: 613-332-3320 | Q52: https://www.rona.ca | T52: =IF(OR(B52="",H52="Paid",H52="Not now",S52=""),"",IF(S52<=TODAY(),"DUE","")) | U52: Proven local sponsor: supplied lumber for tables plus a truck and forklift for the 61st Rockhound Gemboree, and organizers called it 'so supportive of the show'. | W52: https://www.bancroftthisweek.com/opening-ceremony-for-the-61st-rockhound-gemboree/
A53: 49 | B53: SJC Cook Construction Inc | C53: Bancroft | D53: North Hastings | E53: Contractor / trades | G53: Community Sponsor | H53: Prospect | L53: Not booked yet | M53: Cody | O53: 613-334-9999 | Q53: https://scook.ca | T53: =IF(OR(B53="",H53="Paid",H53="Not now",S53=""),"",IF(S53<=TODAY(),"DUE","")) | U53: Bancroft general contractor; trades crews are core fight-night ticket buyers. | W53: https://www.yellowpages.ca/search/si/1/Contractors/Bancroft+ON
A54: 50 | B54: Sharon White Real Estate Ltd., Brokerage | C54: Bancroft | D54: North Hastings | E54: Real estate brokerage | G54: Bronze Sponsor | H54: Prospect | L54: Not booked yet | M54: Cody | O54: 613-332-5075 | Q54: http://www.sharonwhite.ca/ | T54: =IF(OR(B54="",H54="Paid",H54="Not now",S54=""),"",IF(S54<=TODAY(),"DUE","")) | U54: Well-known Bancroft brokerage on Hastings St N; real estate teams buy local visibility at community events. | W54: https://www.yellowpages.ca/search/si/1/Real+Estate/Bancroft+ON
A55: 51 | B55: The Painted Lady Parlour | C55: Bancroft | D55: North Hastings | E55: Tattoo shop | G55: Community Sponsor | H55: Prospect | L55: Not booked yet | M55: Cody | O55: 343-476-5239 | T55: =IF(OR(B55="",H55="Paid",H55="Not now",S55=""),"",IF(S55<=TODAY(),"DUE","")) | U55: Bancroft tattoo studio on Bridge St W; tattoo clients overlap heavily with combat-sports fans. | W55: https://www.yellowpages.ca/search/si/1/Tattoos/Bancroft+ON
A56: 52 | B56: Vance Motors Dodge Chrysler Jeep Ram | C56: Bancroft | D56: North Hastings | E56: Auto dealer | G56: Silver Sponsor | H56: Prospect | L56: Not booked yet | M56: Cody | O56: 866-940-7842 | Q56: https://www.vancebancroftdodge.ca/ | T56: =IF(OR(B56="",H56="Paid",H56="Not now",S56=""),"",IF(S56<=TODAY(),"DUE","")) | U56: Proven local sponsor: family-run since 1942, it lists about 200 groups it has supported, including Bancroft Hawks, Bancroft Minor Hockey, the Gemboree and the Tri-County Hockey Tournament. Top presenting prospect. | W56: https://www.vancebancroftdodge.ca/organizations-we-have-supported/
A57: 53 | B57: Watts Sutherland Auto Body Ltd | C57: Bancroft | D57: North Hastings | E57: Auto repair / body shop | G57: Community Sponsor | H57: Prospect | L57: Not booked yet | M57: Cody | O57: 613-332-3240 | Q57: https://wattssutherlandautobody.ca | T57: =IF(OR(B57="",H57="Paid",H57="Not now",S57=""),"",IF(S57<=TODAY(),"DUE","")) | U57: Bancroft collision shop on Valleyview Dr; local trade business that benefits from name recognition. | W57: https://www.yellowpages.ca/search/si/1/Auto+Repair/Bancroft+ON
A58: 54 | B58: Ball Real Estate Inc. Brokerage | C58: Bancroft (also Apsley, Haliburton, Lakefield HQ) | D58: North Hastings | E58: Real estate brokerage | G58: Silver Sponsor | H58: Prospect | L58: Not booked yet | M58: Cody | O58: 705-651-2255 | Q58: https://ballrealestate.ca | T58: =IF(OR(B58="",H58="Paid",H58="Not now",S58=""),"",IF(S58<=TODAY(),"DUE","")) | U58: Locally owned brokerage with 72 agents and offices in Bancroft, Apsley and Haliburton; one sponsor that covers three CCCL host towns. | W58: https://www.bancroftthisweek.com/having-a-ball-at-real-estate-office-grand-opening/
A59: 55 | B59: Am-Tech | C59: Apsley | D59: North Kawartha | E59: Excavation / septic / aggregate | G59: Bronze Sponsor | H59: Prospect | L59: Not booked yet | M59: Cody | O59: 705-656-8485 | Q59: https://am-tech.ca | T59: =IF(OR(B59="",H59="Paid",H59="Not now",S59=""),"",IF(S59<=TODAY(),"DUE","")) | U59: Apsley excavating, shoreline work, licensed septic installs and sand/gravel; local heavy-equipment business. | W59: https://media-001-ca.cdn.govstack.com/northkawartha-006-ca/media/ksbjbxg1/2024-colour-directory-layout-56-page.pdf
A60: 56 | B60: Apsley Auto Collision | C60: Apsley | D60: North Kawartha | E60: Auto repair / body shop | G60: Community Sponsor | H60: Prospect | L60: Not booked yet | M60: Cody | O60: 705-656-4982 | T60: =IF(OR(B60="",H60="Paid",H60="Not now",S60=""),"",IF(S60<=TODAY(),"DUE","")) | U60: Apsley collision shop on Wellington St; small-tier local trade sponsor. | W60: https://media-001-ca.cdn.govstack.com/northkawartha-006-ca/media/ksbjbxg1/2024-colour-directory-layout-56-page.pdf
A61: 57 | B61: Apsley Home Hardware Building Centre | C61: Apsley | D61: North Kawartha | E61: Building supply / hardware | G61: Bronze Sponsor | H61: Prospect | L61: Not booked yet | M61: Cody | O61: 705-656-4295 | Q61: http://www.apsleyhomebuildingcentre.ca | T61: =IF(OR(B61="",H61="Paid",H61="Not now",S61=""),"",IF(S61<=TODAY(),"DUE","")) | U61: Apsley's main building centre on Tucker St, serving the contractors and cottage builders who make up the local trades crowd. | W61: https://media-001-ca.cdn.govstack.com/northkawartha-006-ca/media/ksbjbxg1/2024-colour-directory-layout-56-page.pdf
A62: 58 | B62: Eels Lake Cottages & Marina | C62: Apsley | D62: North Kawartha | E62: Marina / cottages | G62: Community Sponsor | H62: Prospect | L62: Not booked yet | M62: Cody | O62: 705-656-1103 | P62: elcm@eelslake.com | Q62: https://www.eelslake.com | T62: =IF(OR(B62="",H62="Paid",H62="Not now",S62=""),"",IF(S62<=TODAY(),"DUE","")) | U62: Marina sales and service plus cottage rentals near Apsley; reaches cottagers and boaters. | W62: https://www.eelslake.com
A63: 59 | B63: Kemp's Garage & Mark's Towing | C63: Apsley | D63: North Kawartha | E63: Towing / auto repair | G63: Community Sponsor | H63: Prospect | L63: Not booked yet | M63: Cody | O63: 705-656-4311 | T63: =IF(OR(B63="",H63="Paid",H63="Not now",S63=""),"",IF(S63<=TODAY(),"DUE","")) | U63: Apsley garage and towing on Burleigh St; every local driver knows the name, so a cheap high-visibility banner. | W63: https://www.yellowpages.ca/search/si/1/Kemp%27s+Garage/Apsley+ON
A64: 60 | B64: North Kawartha Fitness Centre | C64: Apsley | D64: North Kawartha | E64: Gym / fitness | G64: Community Sponsor | H64: Prospect | L64: Not booked yet | M64: Cody | O64: 705-656-4445 | T64: =IF(OR(B64="",H64="Paid",H64="Not now",S64=""),"",IF(S64<=TODAY(),"DUE","")) | U64: Apsley's fitness centre, which doesn't compete with BBG in Bancroft; cross-promo partner for the fitness crowd. | W64: https://media-001-ca.cdn.govstack.com/northkawartha-006-ca/media/ksbjbxg1/2024-colour-directory-layout-56-page.pdf
A65: 61 | B65: Royal LePage Frank Real Estate (Apsley office) | C65: Apsley | D65: North Kawartha | E65: Real estate brokerage | G65: Bronze Sponsor | H65: Prospect | L65: Not booked yet | M65: Cody | O65: 705-656-1035 | T65: =IF(OR(B65="",H65="Paid",H65="Not now",S65=""),"",IF(S65<=TODAY(),"DUE","")) | U65: Apsley real-estate office on Burleigh St; agents want visibility with locals at community events. | W65: https://media-001-ca.cdn.govstack.com/northkawartha-006-ca/media/ksbjbxg1/2024-colour-directory-layout-56-page.pdf
A66: 62 | B66: Tucker's Marine | C66: Apsley | D66: North Kawartha | E66: Powersports / marine dealer | G66: Bronze Sponsor | H66: Prospect | L66: Not booked yet | M66: Cody | O66: 705-656-4402 | Q66: https://www.tuckersmarine.com | T66: =IF(OR(B66="",H66="Paid",H66="Not now",S66=""),"",IF(S66<=TODAY(),"DUE","")) | U66: Sells Yamaha ATVs and snowmobiles plus Lund and Bennington boats on Hwy 28; same buyers as fight-night ticket holders. | W66: https://www.tuckersmarine.com
A67: 63 | B67: Wally's Pub | C67: Apsley | D67: North Kawartha | E67: Pub (ALCOHOL) | G67: Community Sponsor | H67: Prospect | L67: Not booked yet | M67: Cody | O67: 705-656-4964 | T67: =IF(OR(B67="",H67="Paid",H67="Not now",S67=""),"",IF(S67<=TODAY(),"DUE","")) | U67: Apsley pub; natural local watch-party or after-party partner for an Apsley card. Alcohol sponsor. | V67: ALCOHOL: Cody decides. Keep their logo off youth bouts and kids' content. | W67: https://media-001-ca.cdn.govstack.com/northkawartha-006-ca/media/ksbjbxg1/2024-colour-directory-layout-56-page.pdf
A68: 64 | B68: Bowes & Cocks Limited, Brokerage | C68: Apsley (also Bancroft office) | D68: North Kawartha | E68: Real estate brokerage | G68: Bronze Sponsor | H68: Prospect | L68: Not booked yet | M68: Cody | O68: 705-656-4422 | Q68: http://www.bowesandcocks.com/ | T68: =IF(OR(B68="",H68="Paid",H68="Not now",S68=""),"",IF(S68<=TODAY(),"DUE","")) | U68: Peterborough-area brokerage with Apsley (123 Burleigh St) and Bancroft (613-332-1300) offices, so it covers two host towns. | W68: https://media-001-ca.cdn.govstack.com/northkawartha-006-ca/media/ksbjbxg1/2024-colour-directory-layout-56-page.pdf
A69: 65 | B69: Donia's TIMBER MART & Ace Hardware | C69: Apsley area (Hwy 28) | D69: North Kawartha | E69: Building supply / hardware | G69: Community Sponsor | H69: Prospect | L69: Not booked yet | M69: Cody | O69: 705-656-3100 | T69: =IF(OR(B69="",H69="Paid",H69="Not now",S69=""),"",IF(S69<=TODAY(),"DUE","")) | U69: Second building supplier on the Hwy 28 corridor; good small-to-standard banner prospect for an Apsley show. | W69: https://www.yellowpages.ca/search/si/1/Hardware+Stores/Bancroft+ON
A70: 66 | B70: Shewen Construction Limited | C70: Woodview | D70: North Kawartha | E70: Excavation / aggregate / contracting | G70: Community Sponsor | H70: Prospect | L70: Not booked yet | M70: Cody | O70: 705-654-3506 | T70: =IF(OR(B70="",H70="Paid",H70="Not now",S70=""),"",IF(S70<=TODAY(),"DUE","")) | U70: General contracting, aggregate, septic and snow plowing in Woodview; long-standing local trades employer. | W70: https://media-001-ca.cdn.govstack.com/northkawartha-006-ca/media/ksbjbxg1/2024-colour-directory-layout-56-page.pdf
A71: 67 | B71: Viamede Resort | C71: Woodview | D71: North Kawartha | E71: Resort / lodge | G71: Bronze Sponsor | H71: Prospect | L71: Not booked yet | M71: Cody | O71: 705-654-3344 | Q71: https://www.viamede.com | T71: =IF(OR(B71="",H71="Paid",H71="Not now",S71=""),"",IF(S71<=TODAY(),"DUE","")) | U71: Full-service resort on Stoney Lake with groups and events business; fighter/VIP accommodation or hospitality partner for an Apsley show. | W71: https://www.viamede.com
A72: 68 | B72: Kawartha Dairy | C72: Bobcaygeon HQ (stores in Minden and Bancroft) | D72: Kawartha Lakes | E72: Large regional employer / food | G72: Silver Sponsor | H72: Prospect | L72: Not booked yet | M72: Cody | O72: 705-738-5123 | P72: info@kawarthadairy.com | T72: =IF(OR(B72="",H72="Paid",H72="Not now",S72=""),"",IF(S72<=TODAY(),"DUE","")) | U72: Iconic cottage-country brand with retail stores in both Minden and Bancroft; a presenting-level name that covers two host towns. | W72: https://marketplace.thehighlander.ca/?p=405
A73: 69 | B73: Bent Anchor Bar & Restaurant | C73: Combermere | D73: other | E73: Bar / restaurant (ALCOHOL) | G73: Community Sponsor | H73: Prospect | L73: Not booked yet | M73: Cody | O73: 613-756-9558 | T73: =IF(OR(B73="",H73="Paid",H73="Not now",S73=""),"",IF(S73<=TODAY(),"DUE","")) | U73: Seasonal riverside bar with live music near Barry's Bay, listed in the Bancroft chamber directory; small banner prospect for a Barry's Bay/Bancroft show. Alcohol sponsor. | V73: ALCOHOL: Cody decides. Keep their logo off youth bouts and kids' content. | W73: https://bancroftontario.com/directory/bent-anchor-bar-restaurant/
A74: 70 | B74: Big Country MMA - Lindsay | C74: Lindsay | D74: Kawartha Lakes | E74: Gym / combat sports | G74: Community Sponsor | H74: Prospect | L74: Not booked yet | M74: Cody | O74: 705-344-2662 | P74: bigcountrymma1@gmail.com | Q74: https://bigcountrylindsay.gymdesk.com | T74: =IF(OR(B74="",H74="Paid",H74="Not now",S74=""),"",IF(S74<=TODAY(),"DUE","")) | U74: Lindsay MMA, BJJ and Muay Thai gym that had an amateur champion on the May 2 CCCL card; a combat-community partner rather than a cash sponsor. | W74: https://thehighlander.ca/2026/03/12/fight-night-coming-to-haliburton-county/
A75: 71 | B75: Shorelines Casino Peterborough | C75: Peterborough | D75: Peterborough | E75: Casino (GAMBLING) | G75: Silver Sponsor | H75: Prospect | L75: Not booked yet | M75: Cody | O75: 705-809-0880 | Q75: http://www.shorelinescasinos.com | T75: =IF(OR(B75="",H75="Paid",H75="Not now",S75=""),"",IF(S75<=TODAY(),"DUE","")) | U75: Regional casino whose adult entertainment audience overlaps with fight fans. Gambling sponsor: check OAC/AGCO rules and whether youth fighters are on the card. | V75: GAMBLING: Cody decides. Keep their logo off youth bouts and kids' content. | W75: https://www.worldcasinodirectory.com/casino/shorelines-casino-peterborough
A76: 72 | B76: Hayabusa Fightwear | C76: Kingston, ON | D76: Brand: fight gear | E76: Gear | G76: Silver Sponsor | H76: Prospect | L76: Not booked yet | M76: Cody | O76: 1-888-776-1662 | Q76: https://www.hayabusafight.com/pages/sponsorship-inquiry | T76: =IF(OR(B76="",H76="Paid",H76="Not now",S76=""),"",IF(S76<=TODAY(),"DUE","")) | U76: The best combat-native fit. Hayabusa is an Ontario brand based in Kingston, which is one of the 2027 target cities, about 2.5 hrs from Bancroft. In Oct 2025 it began sponsoring the ADCC North America Opens & Trials (grappling) with prize packages for Absolute Division winners. That model fits CCCL title fights and the youth grappling matches. It was historically Glory kickboxing's equipment provider. Its site has a public sponsorship inquiry form (options: Competition / Ambassador / Other). ASK: Official Fight Gear Partner of the CCCL 2027 series: Hayabusa gear for title-fight winners and the youth grappling medal winners (under $300 a fighter), gear in fighter bags, logo on the cage banner and livestream. Hold the Kingston show at a venue near their HQ and invite their team. Ask for in-kind worth about Silver, with cash as an upside. | V76: How to reach: Phone 1-888-776-1662 and live chat (https://hayabusafight.com/pages/contact-us); wholesale: https://www.hayabusafight.com/pages/wholesale-inquiry | W76: https://adcc-official.com/blogs/announcements/hayabusa-fightwear-announces-sponsorship
A77: 73 | B77: BioSteel (BioSteel Sports Inc.) | C77: Windsor, ON | D77: Brand: protein | E77: Protein | G77: Bronze Sponsor | H77: Prospect | L77: Not booked yet | M77: Cody | Q77: https://biosteel.ca/pages/partnerships | T77: =IF(OR(B77="",H77="Paid",H77="Not now",S77=""),"",IF(S77<=TODAY(),"DUE","")) | U77: The most active grassroots Ontario sponsor found. It was Football Ontario's official hydration partner for 2025: product at 10 events and camps, a sampling trailer at 6 of them, signage and digital promotion. It has a public partnerships application and a free Team Sponsorship Kit for youth teams. It's a sugar-free hydration brand, so it's safe to put next to kids (unlike alcohol or energy drinks). ASK: Official Hydration Partner of the CCCL 2027 series: hydration product for fighters, corners and officials, the sampling trailer or a booth at the biggest show (Peterborough or Oshawa), logo on the cage-side and livestream. Separately, get the BioSteel Team Kit for the youth grappling team. Pitch it together with Canadian Protein (same owner). | V77: How to reach: Partnership application form above; mailing address 13455 Sylvestre Dr, Windsor, ON N8N 2L9 (biosteel.ca) | W77: https://biosteel.ca/blogs/newsroom/biosteel-partners-with-football-ontario-to-fuel-2025-season
A78: 74 | B78: Canadian Protein | C78: Windsor, ON | D78: Brand: protein | E78: Protein | G78: In-kind Partner | H78: Prospect | L78: Not booked yet | M78: Cody | Q78: https://canadianprotein.com/pages/contact-us | T78: =IF(OR(B78="",H78="Paid",H78="Not now",S78=""),"",IF(S78<=TODAY(),"DUE","")) | U78: An Ontario-made protein brand with the same owner as BioSteel (Dan Crosby, per CBC). One pitch can cover protein (Canadian Protein) and hydration (BioSteel). Its value pricing fits fighters and gym members, and the 'Ontario fighters, Ontario-made protein' story is easy to tell. ASK: Protein product for fighter bags and prizes for a licensed raffle, a discount code for ticket buyers and Bancroft Boxing members, and logo on the livestream lower-third. Add a small cash Bronze if paired with BioSteel. | V78: How to reach: Contact form on the page above (routed via Zendesk to the right department). No sponsorship email published. | W78: https://www.cbc.ca/lite/story/1.7031386
A79: 75 | B79: MuscleTech / Six Star (Iovate Health Sciences) | C79: Oakville, ON | D79: Brand: protein | E79: Protein | G79: Silver Sponsor | H79: Prospect | L79: Not booked yet | M79: Cody | O79: 1-888-334-4448 | P79: info@iovate.com | Q79: https://www.iovate.com/contact-us/ | T79: =IF(OR(B79="",H79="Paid",H79="Not now",S79=""),"",IF(S79<=TODAY(),"DUE","")) | U79: The 'huge protein brand' that is actually Ontario-headquartered: Iovate owns MuscleTech, Six Star, Hydroxycut and Purely Inspired. Has a track record of event sponsorship built on sampling (Gold sponsor of 33 Musclecontest events in 2023, giving samples to competitors and spectators) and signs Canadian athletes to Team MuscleTech. Team MuscleTech today is an affiliate program ('The Hive'), so individual fighters can also join it for product and commission. ASK: Year 1: Six Star/MuscleTech product for every fighter bag, plus a sampling table at each 2027 show, with logo on the weigh-in backdrop and the livestream. Move to cash (Silver) only after you can show 2026 livestream and attendance numbers. Pitch it as Ontario brand + Ontario fighters across 4 cities. | V79: How to reach: info@iovate.com / 1-888-334-4448 (listed on iovate.com); MuscleTech web form at https://www.muscletech.com/pages/contact-us; fighters: https://www.muscletech.com/pages/team-muscletech (affiliate) | W79: https://www.iovate.com/press-release/muscletech-announces-gold-sponsorship-of-musclecontest-international-events
A80: 76 | B80: Allmax Nutrition | C80: North York | D80: Brand: protein | E80: Protein | G80: Bronze Sponsor | H80: Prospect | L80: Not booked yet | M80: Cody | Q80: https://www.allmaxnutrition.com/pages/allmax-show-competitors | T80: =IF(OR(B80="",H80="Paid",H80="Not now",S80=""),"",IF(S80<=TODAY(),"DUE","")) | U80: Toronto sports-nutrition brand that sponsors Canadian sport at a national level: title sponsor of Canada's Senior Men's National Tackle Team in 2025. Its site has a 'Business & Event Inquiries' link and a separate athletes/influencer portal. ASK: Product for fighter bags plus a sampling booth at 1-2 shows. Ask for a Bronze cash add-on if they take the 'presenting sponsor of the weigh-ins' slot. Put strong fighters forward for the athlete portal. | V80: How to reach: Contact form: https://www.allmaxnutrition.com/pages/contact | W80: https://footballcanada.com/news/allmax-nutrition-becomes-title-sponsor-for-canadas-senior-mens-national-tackle-team
A81: 77 | B81: STING Sports Canada | C81: Global HQ stated as Canada | D81: Brand: fight gear | E81: Gear | G81: In-kind Partner | H81: Prospect | L81: Not booked yet | M81: Cody | P81: salesca@stingsports.com | Q81: https://stingsports.ca/pages/contact | T81: =IF(OR(B81="",H81="Paid",H81="Not now",S81=""),"",IF(S81<=TODAY(),"DUE","")) | U81: Official equipment supplier and partner of Boxing Ontario (gloves and equipment for all Boxing Ontario events; Jan 2026 article) and of Boxing Canada. Says it supports local gyms and youth development. A natural partner for Bancroft Boxing as a boxing gym. ASK: Official glove/equipment supplier for CCCL (gloves, pads, headgear for youth), discounted gear for Bancroft Boxing members, prize packs. In-kind, plus a logo. | V81: How to reach: Contact form above; wholesale: salesca@stingsports.com (listed on stingsports.ca) | W81: https://stingsports.ca/blogs/news/sting-canada-boxing-ontario-partnership
A82: 78 | B82: Supplement King Canada (local franchise stores) | C82: Halifax, NS | D82: Brand: protein | E82: Protein | G82: In-kind Partner | H82: Prospect | L82: Not booked yet | M82: Cody | T82: =IF(OR(B82="",H82="Paid",H82="Not now",S82=""),"",IF(S82<=TODAY(),"DUE","")) | U82: Official Supplement Retail Store of the CFL (multi-year deal from 2023). In March 2024 it ran a KidSport youth-sport fundraiser in its stores, which helps the youth-grappling angle. Stores are owner-operated, so a local owner can say yes quickly. ASK: Ask the owner of the nearest store in each 2027 host city (Peterborough, Kingston, Oshawa, Lindsay) for product prizes, gift cards for fighter-of-the-night (under $300), a booth, and cross-promotion in store. Store owners are usually Community/Bronze level. | V82: How to reach: Local store owner (in person). No official sponsorship email verified. | W82: https://press.cfl.ca/supplement-king-canada-and-cfl-launch-multi-year-partnership
A83: 79 | B83: Popeye's Supplements Canada (local franchise stores) | C83: Not verified | D83: Brand: protein | E83: Protein | G83: In-kind Partner | H83: Prospect | L83: Not booked yet | M83: Cody | T83: =IF(OR(B83="",H83="Paid",H83="Not now",S83=""),"",IF(S83<=TODAY(),"DUE","")) | U83: Canada's largest sports-nutrition retail chain (140+ stores per a Nov 2025 Business Wire release). Official supplement provider of the CFL's Montreal Alouettes. Has stores near the 2027 targets of Kingston and Oshawa/Whitby. ASK: Local store product for fighter bags and prizes, a weigh-in sponsor slot, and a discount code for ticket buyers. | V83: How to reach: Local store (in person). No official sponsorship email verified. (Low confidence: check details first.) | W83: https://en.montrealalouettes.com/?p=347957
A84: 80 | B84: PVL (Pure Vita Labs / PVL Nutrients Ltd.) | C84: Port Coquitlam, BC | D84: Brand: protein | E84: Protein | G84: In-kind Partner | H84: Prospect | L84: Not booked yet | M84: Cody | Q84: https://pvl.com/pages/contact | T84: =IF(OR(B84="",H84="Paid",H84="Not now",S84=""),"",IF(S84<=TODAY(),"DUE","")) | U84: A Canadian brand that already sponsors combat athletes: pro boxer Triston Brookes, WBC Muay Thai champion Scott Mackenzie and a Silver Gloves amateur boxer. CFL Players' Association partner since Oct 2025. Its products are third-party tested, which matters for sanctioned fighters. ASK: Product for fighter bags, and individual sponsorship of 1-2 standout CCCL fighters (gear, logo on walkout shirt). Mostly in-kind. | V84: How to reach: Contact page above; no sponsorship email published | W84: https://pvl.com/pages/athletes
A85: 81 | B85: Nutrabolics | C85: Vancouver, BC | D85: Brand: protein | E85: Protein | G85: In-kind Partner | H85: Prospect | L85: Not booked yet | M85: Cody | Q85: https://nutrabolics.com/pages/contact | T85: =IF(OR(B85="",H85="Paid",H85="Not now",S85=""),"",IF(S85<=TODAY(),"DUE","")) | U85: A Canadian supplement brand with the longest MMA history found: past ambassadors include Anderson Silva, Bobby Lashley (2015 deal) and Khabib Nurmagomedov (per BIV). Its contact form has a dedicated 'Sponsorship' department. ASK: Product for fighter bags, plus a logo on the fight poster and livestream. In-kind only at this stage. | V85: How to reach: Web form above; mailing address #220 - 1917 West 4th Ave, Vancouver, BC V6J 1M7 | W85: https://www.newswire.com/news/nutrabolics-signs-deal-with-mma-star-bobby-lashley
A86: 82 | B86: VEGAIN | C86: Nanaimo, BC | D86: Brand: protein | E86: Protein | G86: In-kind Partner | H86: Prospect | L86: Not booked yet | M86: Cody | Q86: https://vegain.com | T86: =IF(OR(B86="",H86="Paid",H86="Not now",S86=""),"",IF(S86<=TODAY(),"DUE","")) | U86: A Canadian plant-based protein brand that signed UFC welterweight Ian Machado Garry as an ambassador in 2024, so it is open to combat sports. ASK: Product for fighter bags and prizes for a licensed raffle; in-kind. | V86: How to reach: Not verified. Use the contact link on vegain.com (Low confidence: check details first.) | W86: https://businessexaminer.ca/victoria-articles/item/nanaimo-based-vegain-inks-ufc-fighter-to-rep-sports-nutrition-brand
A87: 83 | B87: Maple Leaf Foods (Maple Leaf Mighty Protein) | C87: Mississauga, ON | D87: Brand: protein | E87: Protein | G87: In-kind Partner | H87: Prospect | L87: Not booked yet | M87: Cody | Q87: https://www.mapleleaffoods.com/wp-content/uploads/2018/04/Community-Involvement-Policy.pdf | T87: =IF(OR(B87="",H87="Paid",H87="Not now",S87=""),"",IF(S87<=TODAY(),"DUE","")) | U87: A huge Ontario 'protein' brand in the food sense: four-year Official Protein Partner of Team Canada (Dec 2025), with the 'Victory. But First, Protein.' campaign. But its Community Involvement Policy is about food security and excludes for-profit businesses. Long shot. ASK: Realistically none for the for-profit show. Possible only for a non-profit youth program with a nutrition / food-security angle (in-kind). | V87: Funds registered charities or non-profits only: needs a non-profit partner to apply. How to reach: Request contact is listed in the policy PDF above (2018 document, may be outdated) (Low confidence: check details first.) | W87: https://olympic.ca/press/maple-leaf-foods-joins-team-canada-as-official-protein-partner/
A88: 84 | B88: RDX Sports | C88: International brand | D88: Brand: fight gear | E88: Gear | G88: In-kind Partner | H88: Prospect | L88: Not booked yet | M88: Cody | T88: =IF(OR(B88="",H88="Paid",H88="Not now",S88=""),"",IF(S88<=TODAY(),"DUE","")) | U88: Official equipment supplier of IMMAF, the world amateur MMA federation, renewed for 2026. Directly relevant because CCCL runs amateur MMA under the Combative Sports Act. RDX also publishes many event and academy sponsorships worldwide. ASK: Gear prize packs and discounted shin guards / MMA gloves for amateur fighters; in-kind. | V88: How to reach: Not verified (Low confidence: check details first.) | W88: https://immaf.org/?p=57969
A89: 85 | B89: Proper No. Twelve Irish Whiskey (Proximo Spirits) | C89: Proximo Spirits: Jersey City, NJ | D89: Brand: alcohol | E89: Alcohol | G89: Gold Sponsor | H89: Prospect | L89: Not booked yet | M89: Cody | O89: (647) 344-3838 | Q89: https://www.proximospirits.com/contact | T89: =IF(OR(B89="",H89="Paid",H89="Not now",S89=""),"",IF(S89<=TODAY(),"DUE","")) | U89: Cody's dream sponsor. It has combat-sports history: title sponsor of Wilder vs Fury II (2020) and official whiskey partner of PFL Europe (2023). It also has hockey deals in Canada (Bell Centre/Canadiens 2021, run by Proximo Spirits Canada). It's listed at the LCBO (#11945). But Proximo dropped Conor McGregor in Nov 2024, and the youth grappling on the card collides with alcohol marketing rules (see alcohol_rules). ASK: Only an adults-only activation: a 19+ VIP lounge/after-party sponsor or VIP table at the biggest 2027 show (no youth matches on that card). Product through the venue's licence/permit, with no fighter endorsements. Pitch Gold at most. Expect a 'not yet', and come back with 1,000+ crowd numbers. | V89: ALCOHOL: Cody decides. Only for a 19+ show or 19+ area, never near youth bouts or kids' content. Check with the AGCO, the Athletics Commission and the venue first. How to reach: Proximo Spirits Canada, 111 Peter St., Suite 700, Toronto, ON M5V 2H1; (647) 344-3838 (listed on proximospirits.com/contact) | W89: https://whiskycast.com/proper-no-twelve-whiskey-cutting-ties-with-mcgregor/
A90: 86 | B90: Monster Energy | C90: Corona, CA | D90: Brand: other | E90: Energy drink (FLAG) | G90: In-kind Partner | H90: Prospect | L90: Not booked yet | M90: Cody | Q90: https://www.monsterenergy.com/contact-us/ | T90: =IF(OR(B90="",H90="Paid",H90="Not now",S90=""),"",IF(S90<=TODAY(),"DUE","")) | U90: The biggest energy-drink backer of combat sports: long-time UFC partner, and also Bellator and ONE Championship. It has a published route for event requests through its contact form. The big caveat is youth: energy drinks shouldn't be marketed or sampled to the kids competing in grappling. ASK: Product for adult fighters, crew and VIP; a branded booth or cage-side signage at adult cards. Small cash (Bronze) is a stretch for a regional show. Submit 10-12 weeks before the event. | V90: ENERGY DRINK: Cody decides. Keep it away from youth bouts and kids' content. How to reach: Event form above. Athlete requests by mail only: Monster Energy, Attn: Athlete Sponsorship Department, 1 Monster Way, Corona, CA 92879 (per FAQ) | W90: https://www.monsterenergy.com/en-us/faqs/
A91: 87 | B91: GURU Organic Energy | C91: Montreal, QC | D91: Brand: other | E91: Energy drink (FLAG) | G91: In-kind Partner | H91: Prospect | L91: Not booked yet | M91: Cody | P91: sponsorships@guruenergy.com | Q91: https://guruenergy.com/pages/sponsorships | T91: =IF(OR(B91="",H91="Paid",H91="Not now",S91=""),"",IF(S91<=TODAY(),"DUE","")) | U91: A Canadian energy drink that sponsors many grassroots events (30+ in summer 2022, including Ontario's Sea Otter at Blue Mountain, Vegandale Toronto, and Spartan Races). It has a dedicated sponsorship email for event organizers. Same youth caveat as Monster. ASK: Sampling product and a booth at adult cards, product for fighters and volunteers, with a logo. In-kind, or Bronze at most. | V91: ENERGY DRINK: Cody decides. Keep it away from youth bouts and kids' content. How to reach: sponsorships@guruenergy.com (listed on guruenergy.com) | W91: https://www.bevnet.com/news/2022/guru-announces-summer-event-sponsorship
A92: 88 | B92: Tim Hortons | C92: National chain | D92: Brand: other | E92: Other | G92: In-kind Partner | H92: Prospect | L92: Not booked yet | M92: Cody | P92: regionalmarketing@timhortons.com | Q92: https://help.timhortons.ca/hc/en-ca/articles/38495526405659-How-can-I-request-a-donation-or-sponsorship-for-an-event | T92: =IF(OR(B92="",H92="Paid",H92="Not now",S92=""),"",IF(S92<=TODAY(),"DUE","")) | U92: The best youth-safe national brand for the kids' grappling segment. Timbits youth sports programs are sponsored by local restaurant owners. Tims also accepts event sponsorship/donation requests through regional marketing. ASK: Community level: coffee and Timbits for volunteers, officials and the youth grappling division ('Timbits Youth Grappling'), plus a logo in youth-division graphics. Email a PDF 8-10 weeks ahead with event name, date, expected attendance and the specific ask. | V92: How to reach: regionalmarketing@timhortons.com (per Tim Hortons help centre; reply only if interested) | W92: https://alliancehockey.com/Articles/5076/Timbits_Jersey_Program/
A93: 89 | B93: Home Hardware | C93: St. Jacobs, ON | D93: Brand: other | E93: Other | G93: Bronze Sponsor | H93: Prospect | L93: Not booked yet | M93: Cody | Q93: https://www.homehardware.ca/en/flipgive-sports-teams | T93: =IF(OR(B93="",H93="Paid",H93="Not now",S93=""),"",IF(S93<=TODAY(),"DUE","")) | U93: An Ontario-headquartered building supplies and hardware brand with dealer-owned stores across cottage country. It runs Play More matching grants with FlipGive for youth sports teams. A local dealer is a natural trades-and-cottage-country sponsor. ASK: Local dealer in each host town: Bronze or Community level, with the logo on a 'Hardest Hitter' or 'Fight of the Night' award. The youth grappling team can raise funds through FlipGive and apply for the Play More match when it's open. | V93: How to reach: Local Home Hardware dealer. No national sponsorship email verified. | W93: https://www.newswire.ca/news-releases/home-hardware-and-flipgive-launch-grant-program-to-help-keep-kids-in-the-game-871719190.html
A94: 90 | B94: Canadian Tire Jumpstart Charities | C94: National | D94: Brand: other | E94: Other | G94: In-kind Partner | H94: Prospect | L94: Not booked yet | M94: Cody | Q94: https://jumpstart.canadiantire.ca/pages/faq | T94: =IF(OR(B94="",H94="Paid",H94="Not now",S94=""),"",IF(S94<=TODAY(),"DUE","")) | U94: The biggest youth-sport funder in Canada. Community Development Grants go up to $25,000 (Access) and $75,000 (Youth Development) for eligible organizations using sport for kids facing barriers. It's a fit for a youth grappling program, not the show itself: eligibility is for qualified organizations, and the FAQ refers to 'qualified donees'. ASK: Not event sponsorship. A grant for a Bancroft Boxing & Grappling youth program, run through or with a registered non-profit or charity partner. Local Canadian Tire dealers can separately be asked for Community-level event support. | V94: Funds registered charities or non-profits only: needs a non-profit partner to apply. How to reach: Through the Community Development Grant application linked from the FAQ | W94: https://jumpstart.canadiantire.ca/pages/faq
A95: 91 | B95: Kawartha Credit Union | C95: Kawartha region, ON | D95: Brand: other | E95: Other | G95: Bronze Sponsor | H95: Prospect | L95: Not booked yet | M95: Cody | P95: communications@kawarthacu.com | Q95: https://www.kawarthacu.com/assets/pdfs/KCU%20Community%20Involvement%20Program%20-%202026%20Application%20Guidelines.pdf | T95: =IF(OR(B95="",H95="Paid",H95="Not now",S95=""),"",IF(S95<=TODAY(),"DUE","")) | U95: The only regional financial brand with branches in Bancroft AND three of the 2027 host cities. But its Community Involvement Program is only for registered charities and non-profits, so for-profit promoters are explicitly ineligible. Most grants are $1,000-$5,000. The 2026-funding window was Aug 25 - Oct 3, 2025. ASK: A youth-program or community-component grant through a non-profit partner (apply in the late-summer window), not a show sponsorship. | V95: Funds registered charities or non-profits only: needs a non-profit partner to apply. How to reach: Online application form; supporting docs to communications@kawarthacu.com (per KCU guidelines) | W95: https://www.kawarthacu.com/assets/pdfs/KCU%20Community%20Involvement%20Program%20-%202026%20Application%20Guidelines.pdf
A96: 92 | B96: Ontario Power Generation (Regional Empowerment Grant) | C96: Ontario | D96: Brand: other | E96: Other | G96: Silver Sponsor | H96: Prospect | L96: Not booked yet | M96: Cody | Q96: https://www.opg.com/communities/community-investment/grants/ | T96: =IF(OR(B96="",H96="Paid",H96="Not now",S96=""),"",IF(S96<=TODAY(),"DUE","")) | U96: Funds grassroots initiatives in its host communities with grants of $2,000-$10,000 a year. Durham is named as a host area (Darlington, Pickering), which matters for an Oshawa show. Applications go through the Benevity portal in quarterly windows (current window Oct 1 - Nov 15). Benevity generally serves registered organizations, so confirm eligibility. ASK: A grant for the community or youth part of the Oshawa show (e.g., free youth grappling clinic, accessibility seating), through an eligible organization. | V96: Funds registered charities or non-profits only: needs a non-profit partner to apply. How to reach: Benevity application linked from the page above | W96: https://www.opg.com/communities/community-investment/grants/
A97: 93 | B97: Ford (Ford of Canada / Ontario Ford Dealers) | C97: Canada | D97: Brand: other | E97: Other | G97: Bronze Sponsor | H97: Prospect | L97: Not booked yet | M97: Cody | Q97: https://www.ford.ca/sponsorship/overview/ | T97: =IF(OR(B97="",H97="Paid",H97="Not now",S97=""),"",IF(S97<=TODAY(),"DUE","")) | U97: Trucks fit the cottage-country and trades crowd. Ford Canada sponsors sport from youth hockey to pro teams. Ontario Ford Dealers signed a 3-year Royal Agricultural Winter Fair deal (Sept 2025) aimed at rural customers, and also present The Royal Rodeo. National intake was closed for 2024-2025, so local dealers are the realistic route. ASK: Local Ford dealer in each host city: Bronze or Silver with a truck display in the arena lobby and a 'Built Tough Fight of the Night' award. Watch for the national application to reopen. | V97: How to reach: Local Ford dealers; national application form above | W97: https://canadianautodealer.ca/2025/09/ontario-ford-dealers-forge-rural-ties/
A98: 94 | B98: Kubota Canada | C98: Pickering, ON | D98: Brand: other | E98: Other | G98: Bronze Sponsor | H98: Prospect | L98: Not booked yet | M98: Cody | Q98: https://www.kubota.ca/community | T98: =IF(OR(B98="",H98="Paid",H98="Not now",S98=""),"",IF(S98<=TODAY(),"DUE","")) | U98: A rural equipment and trades brand headquartered next to Oshawa. It sponsors grassroots and rural Ontario properties: 4-H Ontario, the CHL and Canadian Tire Motorsport Park. Its community page has no request form; it points to local dealers. ASK: Local Kubota dealer near each host city: Community or Bronze level with an equipment display and logo. For an Oshawa show, try Kubota Canada's Pickering office through a dealer introduction. | V98: How to reach: Local Kubota dealer. No national sponsorship email verified. | W98: https://www.kubota.ca/community
A99: 95 | B99: DeWalt (Stanley Black & Decker), via a regional construction-supply dealer | C99: International brand | D99: Brand: other | E99: Other | G99: In-kind Partner | H99: Prospect | L99: Not booked yet | M99: Cody | T99: =IF(OR(B99="",H99="Paid",H99="Not now",S99=""),"",IF(S99<=TODAY(),"DUE","")) | U99: A tools brand with a combat-sports history (former UFC sponsor). An Ontario construction-supply dealer (Investments Hardware Ltd., Woodbridge) used its DeWalt relationship to run a UFC 129 customer event. The realistic route is a regional trades-supply dealer's co-op marketing, not DeWalt directly. The source is old (2011). ASK: Tool prize packs for fighter-of-the-night (under $300) or a licensed raffle, plus a logo, through a regional construction-supply store. In-kind. | V99: How to reach: Not verified. Approach a regional construction-supply dealer. (Low confidence: check details first.) | W99: https://canada.constructconnect.com/?p=52670
A100: =IF(B100="","",ROW()-4) | T100: =IF(OR(B100="",H100="Paid",H100="Not now",S100=""),"",IF(S100<=TODAY(),"DUE",""))
A101: =IF(B101="","",ROW()-4) | T101: =IF(OR(B101="",H101="Paid",H101="Not now",S101=""),"",IF(S101<=TODAY(),"DUE",""))
...

Sheet Packages
A1: SPONSOR PACKAGES
A2: Cody's 2026 packages, used again for 2027 until he changes them. Prices, perks and slots in yellow can be changed. Slots per show are a suggestion.
A4: Package | B4: Price ($) | C4: What the sponsor gets | D4: Slots | E4: Status
A5: Title Sponsor | B5: 7500 | C5: Naming rights ("presented by"), top logo on the cage and banners, featured on posters, ads and social media, named at fighter introductions, own posts before and after, VIP seating, a booth or display, recognised as the leading partner. Biggest logo on the event shirt and "presented by" on the livestream. | D5: 1 | E5: 2026 package (Cody). Same for 2027 unless Cody changes it. 2026: Dillabough Millwrighting & Welding. Cody calls this level Platinum.
A6: Gold Sponsor | B6: 4000 | C6: Priority logo around the cage, featured on posters and ads, social media posts, several announcer mentions, VIP tickets, room for their banner and display. Large logo on the event shirt and the livestream. | D6: 2 | E6: 2026 package (Cody). Same for 2027 unless Cody changes it. Shirt and livestream sizes by level: confirmed by Cody (Oct 20, 2026).
A7: Silver Sponsor | B7: 2000 | C7: Logo on selected posters and promos, CCCL social media mention, shared banner space at the venue, announcer mention, free tickets, listed as an official sponsor. Logo on the event shirt and the livestream. | D7: 4 | E7: 2026 package (Cody). Same for 2027 unless Cody changes it. Quote $2,000 (the 2026 price) until Cody confirms. He listed Silver at $2,500 in Oct 2026.
A8: Bronze Sponsor | B8: 1000 | C8: Logo on selected ads, social media sponsor announcement, named in sponsor thank-yous, announcer mention, free admission tickets. Small logo on the event shirt and the livestream sponsor slide. | D8: 10 | E8: 2026 package (Cody). Same for 2027 unless Cody changes it.
A9: Community Sponsor | B9: 300 | C9: CCCL social media mention, name or logo in selected sponsor promos, listed as an official community supporter. Name on the event shirt and the livestream sponsor slide. $300-$500. | D9: 20 | E9: 2026 package (Cody). Same for 2027 unless Cody changes it. Price is the minimum of the $300-$500 range.
A10: In-kind Partner | B10: 0 | C10: Product, prizes or services instead of cash: fighter bags, a sampling table, gear, prize packs. Perks agreed one-on-one, roughly matching the cash level of the same value. | D10: 6 | E10: For brands that give product. Agreed by Cody case by case. Only cash counts toward the sponsorship goal. Anything a fighter receives must be worth under $300 in total, or they lose amateur status; belts, medals and trophies are fine. No raffle without a lottery licence.
A11: VIP Corporate Table | B11: 1500 | C11: Cage-side table for 8-10 guests (depends on the venue's tables) for a business to host staff or clients. | D11: 6 | E11: $1,500 a table (Cody); 6 sold in 2026. Seats 8-10 depending on the venue's tables (Kyle, Oct 2026).

Sheet Fulfilment
A1: SPONSOR DELIVERY CHECKLIST
A2: When a sponsor signs, add them here (pick from the list) and tick off each promise as it's done. Every sponsor should get everything they paid for.
A4: Business | B4: Package | C4: Show | D4: Logo file received | E4: Banner ordered | F4: Banner hung at show | G4: Own thank-you post | H4: Tagged in fight-week posts | I4: On poster | J4: On the livestream | K4: On the shirts | L4: Tickets / VIP seats sent | M4: Announcer shout-out | N4: Photo + thank-you sent after | O4: All done? | P4: Notes
A5: (Example) Lockhart Bros Contracting | B5: Bronze Sponsor | C5: Show 1 · 2027 | D5: Yes | E5: N/A | F5: N/A | G5: Yes | H5: No | I5: Yes | J5: No | K5: No | L5: No | M5: No | N5: No | O5: =IF(A5="","",IF(COUNTIF(D5:N5,"Yes")+COUNTIF(D5:N5,"N/A")=11,"DONE",11-COUNTIF(D5:N5,"Yes")-COUNTIF(D5:N5,"N/A")&" left")) -> 6 left | P5: Example row showing the format. Bronze gets a logo on ads and the shirt, not its own banner, so the two banner columns are N/A. Replace it with a real sponsor.
O6: =IF(A6="","",IF(COUNTIF(D6:N6,"Yes")+COUNTIF(D6:N6,"N/A")=11,"DONE",11-COUNTIF(D6:N6,"Yes")-COUNTIF(D6:N6,"N/A")&" left"))
O7: =IF(A7="","",IF(COUNTIF(D7:N7,"Yes")+COUNTIF(D7:N7,"N/A")=11,"DONE",11-COUNTIF(D7:N7,"Yes")-COUNTIF(D7:N7,"N/A")&" left"))
O8: =IF(A8="","",IF(COUNTIF(D8:N8,"Yes")+COUNTIF(D8:N8,"N/A")=11,"DONE",11-COUNTIF(D8:N8,"Yes")-COUNTIF(D8:N8,"N/A")&" left"))
O9: =IF(A9="","",IF(COUNTIF(D9:N9,"Yes")+COUNTIF(D9:N9,"N/A")=11,"DONE",11-COUNTIF(D9:N9,"Yes")-COUNTIF(D9:N9,"N/A")&" left"))
O10: =IF(A10="","",IF(COUNTIF(D10:N10,"Yes")+COUNTIF(D10:N10,"N/A")=11,"DONE",11-COUNTIF(D10:N10,"Yes")-COUNTIF(D10:N10,"N/A")&" left"))
O11: =IF(A11="","",IF(COUNTIF(D11:N11,"Yes")+COUNTIF(D11:N11,"N/A")=11,"DONE",11-COUNTIF(D11:N11,"Yes")-COUNTIF(D11:N11,"N/A")&" left"))
O12: =IF(A12="","",IF(COUNTIF(D12:N12,"Yes")+COUNTIF(D12:N12,"N/A")=11,"DONE",11-COUNTIF(D12:N12,"Yes")-COUNTIF(D12:N12,"N/A")&" left"))
O13: =IF(A13="","",IF(COUNTIF(D13:N13,"Yes")+COUNTIF(D13:N13,"N/A")=11,"DONE",11-COUNTIF(D13:N13,"Yes")-COUNTIF(D13:N13,"N/A")&" left"))
O14: =IF(A14="","",IF(COUNTIF(D14:N14,"Yes")+COUNTIF(D14:N14,"N/A")=11,"DONE",11-COUNTIF(D14:N14,"Yes")-COUNTIF(D14:N14,"N/A")&" left"))
O15: =IF(A15="","",IF(COUNTIF(D15:N15,"Yes")+COUNTIF(D15:N15,"N/A")=11,"DONE",11-COUNTIF(D15:N15,"Yes")-COUNTIF(D15:N15,"N/A")&" left"))
O16: =IF(A16="","",IF(COUNTIF(D16:N16,"Yes")+COUNTIF(D16:N16,"N/A")=11,"DONE",11-COUNTIF(D16:N16,"Yes")-COUNTIF(D16:N16,"N/A")&" left"))
O17: =IF(A17="","",IF(COUNTIF(D17:N17,"Yes")+COUNTIF(D17:N17,"N/A")=11,"DONE",11-COUNTIF(D17:N17,"Yes")-COUNTIF(D17:N17,"N/A")&" left"))
... O64: =IF(A64="","",IF(COUNTIF(D64:N64,"Yes")+COUNTIF(D64:N64,"N/A")=11,"DONE",11-COUNTIF(D64:N64,"Yes")-COUNTIF(D64:N64,"N/A")&" left"))
