Workbook

Sheet Start Here
A1: BBG & CCCL CONTACTS
A2: Everyone we work with, in one place: venues, gyms, media, suppliers, officials and partners. It stays the same from show to show.
A4: 1 | B4: What it's for | C4: The permanent address book. The Fight Night Kit's Recruitment and Press tabs are per-show working lists (you copy the Kit for each show); this sheet keeps the relationship from one show to the next.
A5: 2 | B5: Sponsors live elsewhere | C5: Sponsors and prospects stay in the CCCL Sponsorship Pipeline (stages, money, follow-ups). Only add a sponsor here if they're also a supplier or partner.
A6: 3 | B6: Log every contact | C6: On the Log tab, add one row each time someone calls, emails or meets a contact. 'Last contact' on the Contacts tab fills in by itself.
A7: 4 | B7: Next step and date | C7: Put the next step and its date on the Contacts tab. 'Due?' turns red when it's overdue, and Claude's morning report lists what's due.
A8: 5 | B8: Starting data | C8: 110 contacts from Kyle's research (Oct 2026): venues, gyms, media and the Athletics Commission. Public business contact details only. Check a number before relying on it.
A9: 6 | B9: Privacy | C9: Public business contacts only: no personal cell numbers, home addresses or anything about health. Members, kids and Second Chance participants never go in this sheet.
B11: Relationship
B12: Not contacted | C12: From research; nobody has reached out yet
B13: Cold | C13: Contacted, no real conversation yet
B14: Warm | C14: Talking, or worked together once
B15: Strong | C15: Worked together more than once; picks up when Cody calls
B16: Partner | C16: Formal or ongoing arrangement (e.g. a venue or gym we always use)
B17: Not a fit | C17: Keep for reference; don't chase
B19: Colours
B20: Yellow, blue text | C20: You type here
B21: Black, bold | C21: Calculated: don't type over it

Sheet Summary
A1: SUMMARY
A2: Who we know and how well, and what's due. Updates by itself.
A4: Type | B4: Not contacted | C4: Cold | D4: Warm | E4: Strong | F4: Partner | G4: Not a fit | H4: Total | I4: Due this week
A5: Venue | B5: =COUNTIFS(Contacts!$B$5:$B$264,$A5,Contacts!$G$5:$G$264,"Not contacted") -> 45 | C5: =COUNTIFS(Contacts!$B$5:$B$264,$A5,Contacts!$G$5:$G$264,"Cold") -> 0 | D5: =COUNTIFS(Contacts!$B$5:$B$264,$A5,Contacts!$G$5:$G$264,"Warm") -> 0 | E5: =COUNTIFS(Contacts!$B$5:$B$264,$A5,Contacts!$G$5:$G$264,"Strong") -> 1 | F5: =COUNTIFS(Contacts!$B$5:$B$264,$A5,Contacts!$G$5:$G$264,"Partner") -> 0 | G5: =COUNTIFS(Contacts!$B$5:$B$264,$A5,Contacts!$G$5:$G$264,"Not a fit") -> 0 | H5: =COUNTIFS(Contacts!$B$5:$B$264,$A5) -> 46 | I5: =COUNTIFS(Contacts!$B$5:$B$264,$A5,Contacts!$L$5:$L$264,"OVERDUE")+COUNTIFS(Contacts!$B$5:$B$264,$A5,Contacts!$L$5:$L$264,"TODAY")+COUNTIFS(Contacts!$B$5:$B$264,$A5,Contacts!$L$5:$L$264,"THIS WEEK") -> 0
A6: Gym | B6: =COUNTIFS(Contacts!$B$5:$B$264,$A6,Contacts!$G$5:$G$264,"Not contacted") -> 32 | C6: =COUNTIFS(Contacts!$B$5:$B$264,$A6,Contacts!$G$5:$G$264,"Cold") -> 0 | D6: =COUNTIFS(Contacts!$B$5:$B$264,$A6,Contacts!$G$5:$G$264,"Warm") -> 2 | E6: =COUNTIFS(Contacts!$B$5:$B$264,$A6,Contacts!$G$5:$G$264,"Strong") -> 0 | F6: =COUNTIFS(Contacts!$B$5:$B$264,$A6,Contacts!$G$5:$G$264,"Partner") -> 0 | G6: =COUNTIFS(Contacts!$B$5:$B$264,$A6,Contacts!$G$5:$G$264,"Not a fit") -> 0 | H6: =COUNTIFS(Contacts!$B$5:$B$264,$A6) -> 34 | I6: =COUNTIFS(Contacts!$B$5:$B$264,$A6,Contacts!$L$5:$L$264,"OVERDUE")+COUNTIFS(Contacts!$B$5:$B$264,$A6,Contacts!$L$5:$L$264,"TODAY")+COUNTIFS(Contacts!$B$5:$B$264,$A6,Contacts!$L$5:$L$264,"THIS WEEK") -> 0
A7: Media | B7: =COUNTIFS(Contacts!$B$5:$B$264,$A7,Contacts!$G$5:$G$264,"Not contacted") -> 27 | C7: =COUNTIFS(Contacts!$B$5:$B$264,$A7,Contacts!$G$5:$G$264,"Cold") -> 0 | D7: =COUNTIFS(Contacts!$B$5:$B$264,$A7,Contacts!$G$5:$G$264,"Warm") -> 2 | E7: =COUNTIFS(Contacts!$B$5:$B$264,$A7,Contacts!$G$5:$G$264,"Strong") -> 0 | F7: =COUNTIFS(Contacts!$B$5:$B$264,$A7,Contacts!$G$5:$G$264,"Partner") -> 0 | G7: =COUNTIFS(Contacts!$B$5:$B$264,$A7,Contacts!$G$5:$G$264,"Not a fit") -> 0 | H7: =COUNTIFS(Contacts!$B$5:$B$264,$A7) -> 29 | I7: =COUNTIFS(Contacts!$B$5:$B$264,$A7,Contacts!$L$5:$L$264,"OVERDUE")+COUNTIFS(Contacts!$B$5:$B$264,$A7,Contacts!$L$5:$L$264,"TODAY")+COUNTIFS(Contacts!$B$5:$B$264,$A7,Contacts!$L$5:$L$264,"THIS WEEK") -> 0
A8: Supplier | B8: =COUNTIFS(Contacts!$B$5:$B$264,$A8,Contacts!$G$5:$G$264,"Not contacted") -> 0 | C8: =COUNTIFS(Contacts!$B$5:$B$264,$A8,Contacts!$G$5:$G$264,"Cold") -> 0 | D8: =COUNTIFS(Contacts!$B$5:$B$264,$A8,Contacts!$G$5:$G$264,"Warm") -> 0 | E8: =COUNTIFS(Contacts!$B$5:$B$264,$A8,Contacts!$G$5:$G$264,"Strong") -> 0 | F8: =COUNTIFS(Contacts!$B$5:$B$264,$A8,Contacts!$G$5:$G$264,"Partner") -> 0 | G8: =COUNTIFS(Contacts!$B$5:$B$264,$A8,Contacts!$G$5:$G$264,"Not a fit") -> 0 | H8: =COUNTIFS(Contacts!$B$5:$B$264,$A8) -> 0 | I8: =COUNTIFS(Contacts!$B$5:$B$264,$A8,Contacts!$L$5:$L$264,"OVERDUE")+COUNTIFS(Contacts!$B$5:$B$264,$A8,Contacts!$L$5:$L$264,"TODAY")+COUNTIFS(Contacts!$B$5:$B$264,$A8,Contacts!$L$5:$L$264,"THIS WEEK") -> 0
A9: Official | B9: =COUNTIFS(Contacts!$B$5:$B$264,$A9,Contacts!$G$5:$G$264,"Not contacted") -> 0 | C9: =COUNTIFS(Contacts!$B$5:$B$264,$A9,Contacts!$G$5:$G$264,"Cold") -> 0 | D9: =COUNTIFS(Contacts!$B$5:$B$264,$A9,Contacts!$G$5:$G$264,"Warm") -> 1 | E9: =COUNTIFS(Contacts!$B$5:$B$264,$A9,Contacts!$G$5:$G$264,"Strong") -> 0 | F9: =COUNTIFS(Contacts!$B$5:$B$264,$A9,Contacts!$G$5:$G$264,"Partner") -> 0 | G9: =COUNTIFS(Contacts!$B$5:$B$264,$A9,Contacts!$G$5:$G$264,"Not a fit") -> 0 | H9: =COUNTIFS(Contacts!$B$5:$B$264,$A9) -> 1 | I9: =COUNTIFS(Contacts!$B$5:$B$264,$A9,Contacts!$L$5:$L$264,"OVERDUE")+COUNTIFS(Contacts!$B$5:$B$264,$A9,Contacts!$L$5:$L$264,"TODAY")+COUNTIFS(Contacts!$B$5:$B$264,$A9,Contacts!$L$5:$L$264,"THIS WEEK") -> 0
A10: Sponsor | B10: =COUNTIFS(Contacts!$B$5:$B$264,$A10,Contacts!$G$5:$G$264,"Not contacted") -> 0 | C10: =COUNTIFS(Contacts!$B$5:$B$264,$A10,Contacts!$G$5:$G$264,"Cold") -> 0 | D10: =COUNTIFS(Contacts!$B$5:$B$264,$A10,Contacts!$G$5:$G$264,"Warm") -> 0 | E10: =COUNTIFS(Contacts!$B$5:$B$264,$A10,Contacts!$G$5:$G$264,"Strong") -> 0 | F10: =COUNTIFS(Contacts!$B$5:$B$264,$A10,Contacts!$G$5:$G$264,"Partner") -> 0 | G10: =COUNTIFS(Contacts!$B$5:$B$264,$A10,Contacts!$G$5:$G$264,"Not a fit") -> 0 | H10: =COUNTIFS(Contacts!$B$5:$B$264,$A10) -> 0 | I10: =COUNTIFS(Contacts!$B$5:$B$264,$A10,Contacts!$L$5:$L$264,"OVERDUE")+COUNTIFS(Contacts!$B$5:$B$264,$A10,Contacts!$L$5:$L$264,"TODAY")+COUNTIFS(Contacts!$B$5:$B$264,$A10,Contacts!$L$5:$L$264,"THIS WEEK") -> 0
A11: Partner | B11: =COUNTIFS(Contacts!$B$5:$B$264,$A11,Contacts!$G$5:$G$264,"Not contacted") -> 0 | C11: =COUNTIFS(Contacts!$B$5:$B$264,$A11,Contacts!$G$5:$G$264,"Cold") -> 0 | D11: =COUNTIFS(Contacts!$B$5:$B$264,$A11,Contacts!$G$5:$G$264,"Warm") -> 0 | E11: =COUNTIFS(Contacts!$B$5:$B$264,$A11,Contacts!$G$5:$G$264,"Strong") -> 0 | F11: =COUNTIFS(Contacts!$B$5:$B$264,$A11,Contacts!$G$5:$G$264,"Partner") -> 0 | G11: =COUNTIFS(Contacts!$B$5:$B$264,$A11,Contacts!$G$5:$G$264,"Not a fit") -> 0 | H11: =COUNTIFS(Contacts!$B$5:$B$264,$A11) -> 0 | I11: =COUNTIFS(Contacts!$B$5:$B$264,$A11,Contacts!$L$5:$L$264,"OVERDUE")+COUNTIFS(Contacts!$B$5:$B$264,$A11,Contacts!$L$5:$L$264,"TODAY")+COUNTIFS(Contacts!$B$5:$B$264,$A11,Contacts!$L$5:$L$264,"THIS WEEK") -> 0
A12: Other | B12: =COUNTIFS(Contacts!$B$5:$B$264,$A12,Contacts!$G$5:$G$264,"Not contacted") -> 0 | C12: =COUNTIFS(Contacts!$B$5:$B$264,$A12,Contacts!$G$5:$G$264,"Cold") -> 0 | D12: =COUNTIFS(Contacts!$B$5:$B$264,$A12,Contacts!$G$5:$G$264,"Warm") -> 0 | E12: =COUNTIFS(Contacts!$B$5:$B$264,$A12,Contacts!$G$5:$G$264,"Strong") -> 0 | F12: =COUNTIFS(Contacts!$B$5:$B$264,$A12,Contacts!$G$5:$G$264,"Partner") -> 0 | G12: =COUNTIFS(Contacts!$B$5:$B$264,$A12,Contacts!$G$5:$G$264,"Not a fit") -> 0 | H12: =COUNTIFS(Contacts!$B$5:$B$264,$A12) -> 0 | I12: =COUNTIFS(Contacts!$B$5:$B$264,$A12,Contacts!$L$5:$L$264,"OVERDUE")+COUNTIFS(Contacts!$B$5:$B$264,$A12,Contacts!$L$5:$L$264,"TODAY")+COUNTIFS(Contacts!$B$5:$B$264,$A12,Contacts!$L$5:$L$264,"THIS WEEK") -> 0
A13: All | B13: =SUM(B5:B12) -> 104 | C13: =SUM(C5:C12) -> 0 | D13: =SUM(D5:D12) -> 5 | E13: =SUM(E5:E12) -> 1 | F13: =SUM(F5:F12) -> 0 | G13: =SUM(G5:G12) -> 0 | H13: =SUM(H5:H12) -> 110 | I13: =SUM(I5:I12) -> 0
A15: Follow-ups
A16: Overdue | B16: =COUNTIFS(Contacts!$L$5:$L$264,"OVERDUE") -> 0
A17: Due today | B17: =COUNTIFS(Contacts!$L$5:$L$264,"TODAY") -> 0
A18: Due in the next 7 days | B18: =COUNTIFS(Contacts!$L$5:$L$264,"THIS WEEK") -> 0
A19: Gone quiet | B19: =COUNTIFS(Contacts!$G$5:$G$264,"Strong",Contacts!$O$5:$O$264,">90")+COUNTIFS(Contacts!$G$5:$G$264,"Partner",Contacts!$O$5:$O$264,">90") -> 0 | C19: Strong or Partner contacts with no logged contact in 90+ days: worth a quick call.
A20: Contacts logged | B20: =COUNTA(Log!$B$5:$B$2000) -> 0

Sheet Contacts
A1: CONTACTS
A2: One row per organization. Type the next step and date; 'Last contact' comes from the Log tab. Filter by Type or Due?.
A4: Organization | B4: Type | C4: Town / area | D4: Contact (public business details) | E4: Website | F4: For | G4: Relationship | H4: Last contact | I4: Next step | J4: Next date | K4: Owner | L4: Due? | M4: Notes | N4: Source | O4: Days since
A5: New Tecumseth Recreation Centre (main arena) | B5: Venue | C5: Alliston (New Tecumseth) | D5: Town of New Tecumseth | F5: CCCL | G5: Not contacted | H5: =IF(A5="","",IF(COUNTIFS(Log!$B$5:$B$2000,A5)=0,"",SUMPRODUCT(MAX((Log!$B$5:$B$2000=A5)*Log!$A$5:$A$2000)))) | K5: Cody | L5: =IF(OR(A5="",J5=""),"",IF(J5<TODAY(),"OVERDUE",IF(J5=TODAY(),"TODAY",IF(J5<=TODAY()+7,"THIS WEEK","")))) | M5: Capacity: Main arena seats 750 (2021) Rate: Not published | N5: https://newtectimes.com/new-tecumseth-recreation-centre-getting-a-new-roof/ | O5: =IF(H5="","",TODAY()-H5)
A6: Nottawasaga Inn Resort - Trade Centre | B6: Venue | C6: Alliston (New Tecumseth) | D6: Nottawasaga Resort sales | F6: CCCL | G6: Not contacted | H6: =IF(A6="","",IF(COUNTIFS(Log!$B$5:$B$2000,A6)=0,"",SUMPRODUCT(MAX((Log!$B$5:$B$2000=A6)*Log!$A$5:$A$2000)))) | K6: Cody | L6: =IF(OR(A6="",J6=""),"",IF(J6<TODAY(),"OVERDUE",IF(J6=TODAY(),"TODAY",IF(J6<=TODAY()+7,"THIS WEEK","")))) | M6: Capacity: Trade Centre 20,358 sq ft: 1,000 theatre / 1,000 banquet Rate: Not published | N6: https://www.successfulmeetings.com/Meeting-Event-Venues/Alliston-ON/Convention-Hotel/Nottawasaga-Inn-Resort-Conference-Ctr-p5578841 | O6: =IF(H6="","",TODAY()-H6)
A7: North Kawartha Community Centre (NKCC) | B7: Venue | C7: Apsley | D7: 705-656-4445; Shawn Tucker, Parks & Rec Supervisor, s.tucker@northkawartha.ca | F7: CCCL | G7: Not contacted | H7: =IF(A7="","",IF(COUNTIFS(Log!$B$5:$B$2000,A7)=0,"",SUMPRODUCT(MAX((Log!$B$5:$B$2000=A7)*Log!$A$5:$A$2000)))) | K7: Cody | L7: =IF(OR(A7="",J7=""),"",IF(J7<TODAY(),"OVERDUE",IF(J7=TODAY(),"TODAY",IF(J7<=TODAY()+7,"THIS WEEK","")))) | M7: Capacity: Arena floor not published; banquet hall up to 325 Rate: 2026, plus HST: arena special-event flat rate $600.00/day; hall $300/day + $50 kitchen/bar | N7: https://northkawartha.ca/living-here/facility-rentals | O7: =IF(H7="","",TODAY()-H7)
A8: North Hastings Community Centre (NHCC) arena | B8: Venue | C8: Bancroft | D8: 613-332-2062; communitycentre@bancroft.ca (2023) | F8: CCCL | G8: Not contacted | H8: =IF(A8="","",IF(COUNTIFS(Log!$B$5:$B$2000,A8)=0,"",SUMPRODUCT(MAX((Log!$B$5:$B$2000=A8)*Log!$A$5:$A$2000)))) | K8: Cody | L8: =IF(OR(A8="",J8=""),"",IF(J8<TODAY(),"OVERDUE",IF(J8=TODAY(),"TODAY",IF(J8<=TODAY()+7,"THIS WEEK","")))) | M8: Capacity: Not published Rate: Not published. The Town has said it wants year-round rentals; the arena ran a $207,350 deficit in 2023. | N8: https://bancroft.hosted.civiclive.com/living/recreation___leisure/north_hastings_community_centre | O8: =IF(H8="","",TODAY()-H8)
A9: Paul J. Yakabuski Community Centre (PJYCC) | B9: Venue | C9: Barry's Bay | D9: Hannah Gutoskie, 613-756-2747 ext. 220, recreation@madawaskavalley.ca | F9: CCCL | G9: Not contacted | H9: =IF(A9="","",IF(COUNTIFS(Log!$B$5:$B$2000,A9)=0,"",SUMPRODUCT(MAX((Log!$B$5:$B$2000=A9)*Log!$A$5:$A$2000)))) | K9: Cody | L9: =IF(OR(A9="",J9=""),"",IF(J9<TODAY(),"OVERDUE",IF(J9=TODAY(),"TODAY",IF(J9<=TODAY()+7,"THIS WEEK","")))) | M9: Capacity: Ice surface 800; upstairs Community Hall 285 Rate: 2026 Schedule of Fees: "PJYCC Renter Run Bar: downstairs ice surface" $1224; Municipal Run Bar downstairs $81… | N9: https://www.madawaskavalley.ca/recreation-tourism/facilities-rentals/paul-j-yakabuski-community-centre/ | O9: =IF(H9="","",TODAY()-H9)
A10: Belleville Armouries | B10: Venue | C10: Belleville | D10: Not found | F10: CCCL | G10: Not contacted | H10: =IF(A10="","",IF(COUNTIFS(Log!$B$5:$B$2000,A10)=0,"",SUMPRODUCT(MAX((Log!$B$5:$B$2000=A10)*Log!$A$5:$A$2000)))) | K10: Cody | L10: =IF(OR(A10="",J10=""),"",IF(J10<TODAY(),"OVERDUE",IF(J10=TODAY(),"TODAY",IF(J10<=TODAY()+7,"THIS WEEK","")))) | M10: Capacity: Not published Rate: Not published | N10: https://anishinabeknews.ca/2025/01/historic-mixed-martial-arts-event-will-be-staged-in-belleville/ | O10: =IF(H10="","",TODAY()-H10)
A11: Quinte Sports & Wellness Centre - main bowl (City lists 'CIBC Place'; Wikipedia: CAA Arena) | B11: Venue | C11: Belleville | D11: rentals@belleville.ca, 613-966-4632 | F11: CCCL | G11: Not contacted | H11: =IF(A11="","",IF(COUNTIFS(Log!$B$5:$B$2000,A11)=0,"",SUMPRODUCT(MAX((Log!$B$5:$B$2000=A11)*Log!$A$5:$A$2000)))) | K11: Cody | L11: =IF(OR(A11="",J11=""),"",IF(J11<TODAY(),"OVERDUE",IF(J11=TODAY(),"TODAY",IF(J11<=TODAY()+7,"THIS WEEK","")))) | M11: Capacity: Over 4,400 (City) / 4,365 hockey (Wikipedia); other pads 300, 200, 400 seats Rate: City page (excl. HST, year not stated): adult ball hockey/floor $119.75/hr, minor $81.75/hr; "Benefit Exhibit… | N11: https://www.belleville.ca/learn-and-play/facilities-and-rentals/arenas/ | O11: =IF(H11="","",TODAY()-H11)
A12: Bobcaygeon/Verulam Community Centre | B12: Venue | C12: Bobcaygeon | D12: 705-738-3331 | F12: CCCL | G12: Not contacted | H12: =IF(A12="","",IF(COUNTIFS(Log!$B$5:$B$2000,A12)=0,"",SUMPRODUCT(MAX((Log!$B$5:$B$2000=A12)*Log!$A$5:$A$2000)))) | K12: Cody | L12: =IF(OR(A12="",J12=""),"",IF(J12<TODAY(),"OVERDUE",IF(J12=TODAY(),"TODAY",IF(J12<=TODAY()+7,"THIS WEEK","")))) | M12: Capacity: Hall 200 Rate: Not published | N12: https://www.kawarthalakes.ca/explore-play/facility-and-park-rentals/community-hall-rentals/ | O12: =IF(H12="","",TODAY()-H12)
A13: Bracebridge Sportsplex | B13: Venue | C13: Bracebridge | D13: Town of Bracebridge 705-645-5264 | F13: CCCL | G13: Not contacted | H13: =IF(A13="","",IF(COUNTIFS(Log!$B$5:$B$2000,A13)=0,"",SUMPRODUCT(MAX((Log!$B$5:$B$2000=A13)*Log!$A$5:$A$2000)))) | K13: Cody | L13: =IF(OR(A13="",J13=""),"",IF(J13<TODAY(),"OVERDUE",IF(J13=TODAY(),"TODAY",IF(J13<=TODAY()+7,"THIS WEEK","")))) | M13: Capacity: Not published Rate: Not published | N13: https://www.bracebridge.ca/be-active/recreation-facilities-and-rentals/ | O13: =IF(H13="","",TODAY()-H13)
A14: Muskoka Lumber Arena (Muskoka Lumber Community Centre) | B14: Venue | C14: Bracebridge | D14: Josh Taylor, Bookings, 705-645-3037 ext. 3763, jtaylor@bracebridge.ca | F14: CCCL | G14: Not contacted | H14: =IF(A14="","",IF(COUNTIFS(Log!$B$5:$B$2000,A14)=0,"",SUMPRODUCT(MAX((Log!$B$5:$B$2000=A14)*Log!$A$5:$A$2000)))) | K14: Cody | L14: =IF(OR(A14="",J14=""),"",IF(J14<TODAY(),"OVERDUE",IF(J14=TODAY(),"TODAY",IF(J14<=TODAY()+7,"THIS WEEK","")))) | M14: Capacity: Not published Rate: Not published | N14: https://www.bracebridge.ca/be-active/recreation-facilities-and-rentals/ | O14: =IF(H14="","",TODAY()-H14)
A15: Sunny Life Recreation & Wellness Centre | B15: Venue | C15: Campbellford | D15: bookings@trenthills.ca; 705-653-1900 | F15: CCCL | G15: Not contacted | H15: =IF(A15="","",IF(COUNTIFS(Log!$B$5:$B$2000,A15)=0,"",SUMPRODUCT(MAX((Log!$B$5:$B$2000=A15)*Log!$A$5:$A$2000)))) | K15: Cody | L15: =IF(OR(A15="",J15=""),"",IF(J15<TODAY(),"OVERDUE",IF(J15=TODAY(),"TODAY",IF(J15<=TODAY()+7,"THIS WEEK","")))) | M15: Capacity: Not published Rate: Not published | N15: https://trenthills.ca/parks-recreation-community/sunny-life-recreation-wellness-centre | O15: =IF(H15="","",TODAY()-H15)
A16: Coboconk Community Centre (hall) | B16: Venue | C16: Coboconk | D16: City Facility Booking 705-324-9411 ext. 1226 | F16: CCCL | G16: Not contacted | H16: =IF(A16="","",IF(COUNTIFS(Log!$B$5:$B$2000,A16)=0,"",SUMPRODUCT(MAX((Log!$B$5:$B$2000=A16)*Log!$A$5:$A$2000)))) | K16: Cody | L16: =IF(OR(A16="",J16=""),"",IF(J16<TODAY(),"OVERDUE",IF(J16=TODAY(),"TODAY",IF(J16<=TODAY()+7,"THIS WEEK","")))) | M16: Capacity: 175 Rate: Not published | N16: https://www.kawarthalakes.ca/explore-play/facility-and-park-rentals/community-hall-rentals/ | O16: =IF(H16="","",TODAY()-H16)
... A50: Keith Tallman Memorial Arena | B50: Venue | C50: Wilberforce | D50: Highlands East municipal office | F50: CCCL | G50: Not contacted | H50: =IF(A50="","",IF(COUNTIFS(Log!$B$5:$B$2000,A50)=0,"",SUMPRODUCT(MAX((Log!$B$5:$B$2000=A50)*Log!$A$5:$A$2000)))) | K50: Cody | L50: =IF(OR(A50="",J50=""),"",IF(J50<TODAY(),"OVERDUE",IF(J50=TODAY(),"TODAY",IF(J50<=TODAY()+7,"THIS WEEK","")))) | M50: Capacity: Not published Rate: Highlands East page (year not stated): "Summer Prime Time ... $40 plus HST" per hour, "Summer Non-Prime ... $… | N50: https://www.highlandseast.ca/municipal-services/fees/facility-fees/ | O50: =IF(H50="","",TODAY()-H50)
A51: Ontario Athletics Commission | B51: Official | C51: Toronto (province-wide) | D51: AthleticsComm@ontario.ca; 416-326-0416 | E51: https://www.ontario.ca/page/amateur-combative-sports | F51: CCCL | G51: Warm | H51: =IF(A51="","",IF(COUNTIFS(Log!$B$5:$B$2000,A51)=0,"",SUMPRODUCT(MAX((Log!$B$5:$B$2000=A51)*Log!$A$5:$A$2000)))) | K51: Cody | L51: =IF(OR(A51="",J51=""),"",IF(J51<TODAY(),"OVERDUE",IF(J51=TODAY(),"TODAY",IF(J51<=TODAY()+7,"THIS WEEK","")))) | M51: Event permit ($600 per show), officials, rules questions, post-event report within 14 days. | N51: https://www.ontario.ca/page/amateur-combative-sports | O51: =IF(H51="","",TODAY()-H51)
A52: Empire Mixed Martial Arts & Fitness | B52: Gym | C52: Barrie | D52: info@empiremma.ca; 705-728-8885; 100 Caplan Ave Unit 8, Barrie (Let's Roll directory) | E52: https://empiremma.ca/ | F52: CCCL | G52: Not contacted | H52: =IF(A52="","",IF(COUNTIFS(Log!$B$5:$B$2000,A52)=0,"",SUMPRODUCT(MAX((Log!$B$5:$B$2000=A52)*Log!$A$5:$A$2000)))) | K52: Cody | L52: =IF(OR(A52="",J52=""),"",IF(J52<TODAY(),"OVERDUE",IF(J52=TODAY(),"TODAY",IF(J52<=TODAY()+7,"THIS WEEK","")))) | N52: https://letsroll.co/gym/empire-mixed-martial-arts-fitness-barrie-on | O52: =IF(H52="","",TODAY()-H52)
A53: Legacy Fight Club | B53: Gym | C53: Barrie | D53: teamlegacy.assistance@gmail.com; text (249) 501-9937; 351 King St Unit 7, Barrie | E53: https://www.legacyfightclub.com/ | F53: CCCL | G53: Not contacted | H53: =IF(A53="","",IF(COUNTIFS(Log!$B$5:$B$2000,A53)=0,"",SUMPRODUCT(MAX((Log!$B$5:$B$2000=A53)*Log!$A$5:$A$2000)))) | K53: Cody | L53: =IF(OR(A53="",J53=""),"",IF(J53<TODAY(),"OVERDUE",IF(J53=TODAY(),"TODAY",IF(J53<=TODAY()+7,"THIS WEEK","")))) | M53: At the edge of the 3 h radius. Barrie has its own shows (MM-Eh lists 'Fight Night Barrie', Nov 20 2026). | N53: https://www.legacyfightclub.com/ | O53: =IF(H53="","",TODAY()-H53)
A54: Infinite Martial Arts & Fitness | B54: Gym | C54: Belleville | D54: Info@Infinite-MMA.com; (613) 969-7653; 315 Bell Blvd, Belleville | E54: https://infinite-mma.com/ | F54: CCCL | G54: Not contacted | H54: =IF(A54="","",IF(COUNTIFS(Log!$B$5:$B$2000,A54)=0,"",SUMPRODUCT(MAX((Log!$B$5:$B$2000=A54)*Log!$A$5:$A$2000)))) | K54: Cody | L54: =IF(OR(A54="",J54=""),"",IF(J54<TODAY(),"OVERDUE",IF(J54=TODAY(),"TODAY",IF(J54<=TODAY()+7,"THIS WEEK","")))) | M54: The best MMA-style gym found in the Quinte area. Contact it for any Marmora or Madoc show. | N54: https://infinite-mma.com/ | O54: =IF(H54="","",TODAY()-H54)
A55: Pinnacle Boxing Academy | B55: Gym | C55: Belleville | D55: No official contact found. Ask Boxing Ontario or check the club's social pages. | F55: CCCL | G55: Not contacted | H55: =IF(A55="","",IF(COUNTIFS(Log!$B$5:$B$2000,A55)=0,"",SUMPRODUCT(MAX((Log!$B$5:$B$2000=A55)*Log!$A$5:$A$2000)))) | K55: Cody | L55: =IF(OR(A55="",J55=""),"",IF(J55<TODAY(),"OVERDUE",IF(J55=TODAY(),"TODAY",IF(J55<=TODAY()+7,"THIS WEEK","")))) | M55: Boxing only. Runs its own boxing club shows. | N55: https://www.inquinte.ca/2025/10/local-boxers-fight-their-way-to-medals-at-provincial-championships/ | O55: =IF(H55="","",TODAY()-H55)
A56: Big Country - Muskoka | B56: Gym | C56: Bracebridge | D56: bigcountrymuskoka@gmail.com; 705-706-1631; 75 Manitoba St, Bracebridge | E56: https://bigcountrymuskoka.gymdesk.com/ | F56: CCCL | G56: Not contacted | H56: =IF(A56="","",IF(COUNTIFS(Log!$B$5:$B$2000,A56)=0,"",SUMPRODUCT(MAX((Log!$B$5:$B$2000=A56)*Log!$A$5:$A$2000)))) | K56: Cody | L56: =IF(OR(A56="",J56=""),"",IF(J56<TODAY(),"OVERDUE",IF(J56=TODAY(),"TODAY",IF(J56<=TODAY()+7,"THIS WEEK","")))) | N56: https://bigcountrymuskoka.gymdesk.com/ | O56: =IF(H56="","",TODAY()-H56)
A57: United Brazilian Jiu-Jitsu & Muay Thai | B57: Gym | C57: Cobourg | D57: (905) 375-3113 (own site; email masked); 1040 Division St, Cobourg (directory) | E57: http://unitedbjj.ca/ | F57: CCCL | G57: Not contacted | H57: =IF(A57="","",IF(COUNTIFS(Log!$B$5:$B$2000,A57)=0,"",SUMPRODUCT(MAX((Log!$B$5:$B$2000=A57)*Log!$A$5:$A$2000)))) | K57: Cody | L57: =IF(OR(A57="",J57=""),"",IF(J57<TODAY(),"OVERDUE",IF(J57=TODAY(),"TODAY",IF(J57<=TODAY()+7,"THIS WEEK","")))) | N57: http://unitedbjj.ca/ | O57: =IF(H57="","",TODAY()-H57)
A58: The Chop Shop MMA | B58: Gym | C58: Haliburton | D58: 705-854-3773; 175 Industrial Park Rd Unit A, Haliburton; Facebook /TheChopShopHaliburton; Instagram @thechopshophaliburton | E58: https://www.thechopshop.ca/ | F58: CCCL | G58: Not contacted | H58: =IF(A58="","",IF(COUNTIFS(Log!$B$5:$B$2000,A58)=0,"",SUMPRODUCT(MAX((Log!$B$5:$B$2000=A58)*Log!$A$5:$A$2000)))) | K58: Cody | L58: =IF(OR(A58="",J58=""),"",IF(J58<TODAY(),"OVERDUE",IF(J58=TODAY(),"TODAY",IF(J58<=TODAY()+7,"THIS WEEK","")))) | M58: Closest gym to CCCL's Haliburton venue. Good for youth grappling bouts and as a local co-host. | N58: https://www.thechopshop.ca/ | O58: =IF(H58="","",TODAY()-H58)
A59: Grizzly Gym | B59: Gym | C59: Kingston | D59: mike@grizzlygym.com (decoded from its site); 613-483-7522; 541 Days Rd, Kingston | E59: https://www.grizzlygym.com/ | F59: CCCL | G59: Warm | H59: =IF(A59="","",IF(COUNTIFS(Log!$B$5:$B$2000,A59)=0,"",SUMPRODUCT(MAX((Log!$B$5:$B$2000=A59)*Log!$A$5:$A$2000)))) | K59: Cody | L59: =IF(OR(A59="",J59=""),"",IF(J59<TODAY(),"OVERDUE",IF(J59=TODAY(),"TODAY",IF(J59<=TODAY()+7,"THIS WEEK","")))) | M59: Has already sent a fighter to CCCL. Strong partner for a Kingston show. | N59: https://www.sherdog.com/fighter/Joshua-Henshaw-355453 | O59: =IF(H59="","",TODAY()-H59)
A60: Hayabusa Academy | B60: Gym | C60: Kingston | D60: info@Hayabusa-Academy.com; 613-484-5455; 677 Innovation Dr Unit 7, Kingston | E60: https://www.hayabusa-academy.com/ | F60: CCCL | G60: Not contacted | H60: =IF(A60="","",IF(COUNTIFS(Log!$B$5:$B$2000,A60)=0,"",SUMPRODUCT(MAX((Log!$B$5:$B$2000=A60)*Log!$A$5:$A$2000)))) | K60: Cody | L60: =IF(OR(A60="",J60=""),"",IF(J60<TODAY(),"OVERDUE",IF(J60=TODAY(),"TODAY",IF(J60<=TODAY()+7,"THIS WEEK","")))) | M60: Confirm the current owners and whether it is still operating. The Chop Shop's owners can introduce you. | N60: https://www.hayabusa-academy.com/ | O60: =IF(H60="","",TODAY()-H60)
A61: Jiu-Jitsu Kingston | B61: Gym | C61: Kingston | D61: Contact form on its site; (613) 449-8616 / 343-321-5852; 654 Norris Ct, Kingston | E61: https://jiu-jitsukingston.com/ | F61: CCCL | G61: Not contacted | H61: =IF(A61="","",IF(COUNTIFS(Log!$B$5:$B$2000,A61)=0,"",SUMPRODUCT(MAX((Log!$B$5:$B$2000=A61)*Log!$A$5:$A$2000)))) | K61: Cody | L61: =IF(OR(A61="",J61=""),"",IF(J61<TODAY(),"OVERDUE",IF(J61=TODAY(),"TODAY",IF(J61<=TODAY()+7,"THIS WEEK","")))) | M61: CORRECTION: earlier research listed 'Kingston Jiu Jitsu'. kingstonjiujitsu.com is a UK academy in Kingston upon Thames. The Kingston, Ontario gym is Jiu-Jitsu Kingston (jiu-jitsukingston.co… | N61: https://jiu-jitsukingston.com/ | O61: =IF(H61="","",TODAY()-H61)
A62: Kingston Combat Wrestling Club | B62: Gym | C62: Kingston | D62: Club contact on the OAWA club listing (https://www.oawa.ca/oawa-club-listing); the listed email is a personal address, so it isn't copied here | F62: CCCL | G62: Not contacted | H62: =IF(A62="","",IF(COUNTIFS(Log!$B$5:$B$2000,A62)=0,"",SUMPRODUCT(MAX((Log!$B$5:$B$2000=A62)*Log!$A$5:$A$2000)))) | K62: Cody | L62: =IF(OR(A62="",J62=""),"",IF(J62<TODAY(),"OVERDUE",IF(J62=TODAY(),"TODAY",IF(J62<=TODAY()+7,"THIS WEEK","")))) | N62: https://www.oawa.ca/oawa-club-listing | O62: =IF(H62="","",TODAY()-H62)
A63: Kingston Wrestling Club | B63: Gym | C63: Kingston | D63: Marcus Niemann: kingstonwrestling@hotmail.com (OAWA club listing) | F63: CCCL | G63: Not contacted | H63: =IF(A63="","",IF(COUNTIFS(Log!$B$5:$B$2000,A63)=0,"",SUMPRODUCT(MAX((Log!$B$5:$B$2000=A63)*Log!$A$5:$A$2000)))) | K63: Cody | L63: =IF(OR(A63="",J63=""),"",IF(J63<TODAY(),"OVERDUE",IF(J63=TODAY(),"TODAY",IF(J63<=TODAY()+7,"THIS WEEK","")))) | N63: https://www.oawa.ca/oawa-club-listing | O63: =IF(H63="","",TODAY()-H63)
A64: Nomad Martial Arts & Fitness | B64: Gym | C64: Kingston | D64: alimo@nomadma.net; 613-519-2588; The Bunker, 1300 Bath Rd, Kingston | E64: https://nomadma.net/ | F64: CCCL | G64: Not contacted | H64: =IF(A64="","",IF(COUNTIFS(Log!$B$5:$B$2000,A64)=0,"",SUMPRODUCT(MAX((Log!$B$5:$B$2000=A64)*Log!$A$5:$A$2000)))) | K64: Cody | L64: =IF(OR(A64="",J64=""),"",IF(J64<TODAY(),"OVERDUE",IF(J64=TODAY(),"TODAY",IF(J64<=TODAY()+7,"THIS WEEK","")))) | N64: https://nomadma.net/ | O64: =IF(H64="","",TODAY()-H64)
A65: TRACK2 Brazilian Jiu-Jitsu | B65: Gym | C65: Kingston | D65: hello@track2.ca (Let's Roll directory, not confirmed on the gym's site); 559 Bagot St, Kingston | E65: https://track2.ca/ | F65: CCCL | G65: Not contacted | H65: =IF(A65="","",IF(COUNTIFS(Log!$B$5:$B$2000,A65)=0,"",SUMPRODUCT(MAX((Log!$B$5:$B$2000=A65)*Log!$A$5:$A$2000)))) | K65: Cody | L65: =IF(OR(A65="",J65=""),"",IF(J65<TODAY(),"OVERDUE",IF(J65=TODAY(),"TODAY",IF(J65<=TODAY()+7,"THIS WEEK","")))) | N65: https://letsroll.co/gym/track2-brazilian-jiu-jitsu-kingston-on | O65: =IF(H65="","",TODAY()-H65)
A66: YGK Combatives Group | B66: Gym | C66: Kingston | D66: Contact page on its site (email masked); 613-389-7378 (directory listing); 745 Development Dr, Kingston | E66: https://www.ygkcombativesgroup.com/ | F66: CCCL | G66: Not contacted | H66: =IF(A66="","",IF(COUNTIFS(Log!$B$5:$B$2000,A66)=0,"",SUMPRODUCT(MAX((Log!$B$5:$B$2000=A66)*Log!$A$5:$A$2000)))) | K66: Cody | L66: =IF(OR(A66="",J66=""),"",IF(J66<TODAY(),"OVERDUE",IF(J66=TODAY(),"TODAY",IF(J66<=TODAY()+7,"THIS WEEK","")))) | N66: https://www.ygkcombativesgroup.com/ | O66: =IF(H66="","",TODAY()-H66)
A67: van Jango Studio of Martial Arts | B67: Gym | C67: Kingston | D67: manager@vanjango.com; 343-333-8433; 629 Division St (lower level), Kingston | E67: https://www.vanjango.com/ | F67: CCCL | G67: Not contacted | H67: =IF(A67="","",IF(COUNTIFS(Log!$B$5:$B$2000,A67)=0,"",SUMPRODUCT(MAX((Log!$B$5:$B$2000=A67)*Log!$A$5:$A$2000)))) | K67: Cody | L67: =IF(OR(A67="",J67=""),"",IF(J67<TODAY(),"OVERDUE",IF(J67=TODAY(),"TODAY",IF(J67<=TODAY()+7,"THIS WEEK","")))) | N67: https://www.sherdog.com/fighter/Jesse-Van-Vlack-464451 | O67: =IF(H67="","",TODAY()-H67)
A68: Big Country MMA - Lindsay | B68: Gym | C68: Lindsay | D68: bigcountrymma1@gmail.com; 705-344-2662; 50 Mary St W, Lindsay | E68: https://bigcountrylindsay.gymdesk.com/ | F68: CCCL | G68: Warm | H68: =IF(A68="","",IF(COUNTIFS(Log!$B$5:$B$2000,A68)=0,"",SUMPRODUCT(MAX((Log!$B$5:$B$2000=A68)*Log!$A$5:$A$2000)))) | K68: Cody | L68: =IF(OR(A68="",J68=""),"",IF(J68<TODAY(),"OVERDUE",IF(J68=TODAY(),"TODAY",IF(J68<=TODAY()+7,"THIS WEEK","")))) | M68: The best partner gym: it already sends several fighters per card. Head coach Joe Elliott (BJJ black, Muay Thai red) teaches across all three Big Country locations. | N68: https://bigcountrylindsay.gymdesk.com/page/home | O68: =IF(H68="","",TODAY()-H68)
A69: Big Country - Orillia | B69: Gym | C69: Orillia | D69: orilliabigcountry@gmail.com; 27 West St S, Orillia | E69: https://bigcountryorillia.gymdesk.com | F69: CCCL | G69: Not contacted | H69: =IF(A69="","",IF(COUNTIFS(Log!$B$5:$B$2000,A69)=0,"",SUMPRODUCT(MAX((Log!$B$5:$B$2000=A69)*Log!$A$5:$A$2000)))) | K69: Cody | L69: =IF(OR(A69="",J69=""),"",IF(J69<TODAY(),"OVERDUE",IF(J69=TODAY(),"TODAY",IF(J69<=TODAY()+7,"THIS WEEK","")))) | N69: https://bigcountryorillia.gymdesk.com | O69: =IF(H69="","",TODAY()-H69)
A70: Mariposa Wrestling Club | B70: Gym | C70: Orillia | D70: Club contact on the OAWA club listing (https://www.oawa.ca/oawa-club-listing); the listed email is a personal address, so it isn't copied here | F70: CCCL | G70: Not contacted | H70: =IF(A70="","",IF(COUNTIFS(Log!$B$5:$B$2000,A70)=0,"",SUMPRODUCT(MAX((Log!$B$5:$B$2000=A70)*Log!$A$5:$A$2000)))) | K70: Cody | L70: =IF(OR(A70="",J70=""),"",IF(J70<TODAY(),"OVERDUE",IF(J70=TODAY(),"TODAY",IF(J70<=TODAY()+7,"THIS WEEK","")))) | N70: https://www.oawa.ca/oawa-club-listing | O70: =IF(H70="","",TODAY()-H70)
A71: Surge MMA | B71: Gym | C71: Orléans (Ottawa) | D71: SMS (343) 600-3066; email masked on site; 180 Vanguard Dr, Orléans | E71: https://www.surgemma.com/ | F71: CCCL | G71: Not contacted | H71: =IF(A71="","",IF(COUNTIFS(Log!$B$5:$B$2000,A71)=0,"",SUMPRODUCT(MAX((Log!$B$5:$B$2000=A71)*Log!$A$5:$A$2000)))) | K71: Cody | L71: =IF(OR(A71="",J71=""),"",IF(J71<TODAY(),"OVERDUE",IF(J71=TODAY(),"TODAY",IF(J71<=TODAY()+7,"THIS WEEK","")))) | M71: A competing promoter on the eastern edge of the range. Possible fighter-exchange partner, but expect it to prioritise its own cards. | N71: https://www.eventbrite.ca/e/next-wave-combat-tickets-1990798629291 | O71: =IF(H71="","",TODAY()-H71)
A72: Mamute Martial Arts | B72: Gym | C72: Oshawa | D72: info@mamutemaa.com; (647) 648-1662; 907 Simcoe St N, Oshawa | E72: https://mamutemaa.com/ | F72: CCCL | G72: Not contacted | H72: =IF(A72="","",IF(COUNTIFS(Log!$B$5:$B$2000,A72)=0,"",SUMPRODUCT(MAX((Log!$B$5:$B$2000=A72)*Log!$A$5:$A$2000)))) | K72: Cody | L72: =IF(OR(A72="",J72=""),"",IF(J72<TODAY(),"OVERDUE",IF(J72=TODAY(),"TODAY",IF(J72<=TODAY()+7,"THIS WEEK","")))) | N72: https://mamutemaa.com/ | O72: =IF(H72="","",TODAY()-H72)
A73: Oshawa BJJ & Fitness | B73: Gym | C73: Oshawa | D73: mocaiberbjj@gmail.com; 289-980-0484; 350 Wentworth St E Unit 4-5, Oshawa (waiver lists 1160 Simcoe St S) | E73: https://oshawabjj.com/ | F73: CCCL | G73: Not contacted | H73: =IF(A73="","",IF(COUNTIFS(Log!$B$5:$B$2000,A73)=0,"",SUMPRODUCT(MAX((Log!$B$5:$B$2000=A73)*Log!$A$5:$A$2000)))) | K73: Cody | L73: =IF(OR(A73="",J73=""),"",IF(J73<TODAY(),"OVERDUE",IF(J73=TODAY(),"TODAY",IF(J73<=TODAY()+7,"THIS WEEK","")))) | M73: Good source of youth grapplers. A BBG 12-year-old won gold at the Durham Classic BJJ event in Oshawa (Feb 2026). | N73: https://oshawabjj.com/ | O73: =IF(H73="","",TODAY()-H73)
A74: Evolution Jiu Jitsu (Petawawa) | B74: Gym | C74: Petawawa | D74: evolutionbjjpetawawa@hotmail.com; 613-687-2833; Army Fitness Centre, 3 Festubert Blvd Bldg Q-103, Petawawa | F74: CCCL | G74: Not contacted | H74: =IF(A74="","",IF(COUNTIFS(Log!$B$5:$B$2000,A74)=0,"",SUMPRODUCT(MAX((Log!$B$5:$B$2000=A74)*Log!$A$5:$A$2000)))) | K74: Cody | L74: =IF(OR(A74="",J74=""),"",IF(J74<TODAY(),"OVERDUE",IF(J74=TODAY(),"TODAY",IF(J74<=TODAY()+7,"THIS WEEK","")))) | M74: On CFB Petawawa, with a military athlete pool. About as close to Bancroft as Peterborough, via Barry's Bay. | N74: https://cfmws.ca/petawawa/evolution-jiu-jitsu-club | O74: =IF(H74="","",TODAY()-H74)
A75: Ottawa Valley Boxing | B75: Gym | C75: Petawawa | D75: Nshangraw@ottawavalleysports.com; 1959 Petawawa Blvd Unit 3 (per a Town of Petawawa story) | E75: https://ottawavalleyboxing.com/ | F75: CCCL | G75: Not contacted | H75: =IF(A75="","",IF(COUNTIFS(Log!$B$5:$B$2000,A75)=0,"",SUMPRODUCT(MAX((Log!$B$5:$B$2000=A75)*Log!$A$5:$A$2000)))) | K75: Cody | L75: =IF(OR(A75="",J75=""),"",IF(J75<TODAY(),"OVERDUE",IF(J75=TODAY(),"TODAY",IF(J75<=TODAY()+7,"THIS WEEK","")))) | M75: Boxing only. | N75: https://ottawavalleyboxing.com/ | O75: =IF(H75="","",TODAY()-H75)
A76: Pinnacle Wrestling Club | B76: Gym | C76: Petawawa | D76: Nigel Yantha: pinnaclewrestling2025@gmail.com (OAWA club listing) | F76: CCCL | G76: Not contacted | H76: =IF(A76="","",IF(COUNTIFS(Log!$B$5:$B$2000,A76)=0,"",SUMPRODUCT(MAX((Log!$B$5:$B$2000=A76)*Log!$A$5:$A$2000)))) | K76: Cody | L76: =IF(OR(A76="",J76=""),"",IF(J76<TODAY(),"OVERDUE",IF(J76=TODAY(),"TODAY",IF(J76<=TODAY()+7,"THIS WEEK","")))) | N76: https://www.oawa.ca/oawa-club-listing | O76: =IF(H76="","",TODAY()-H76)
A77: Eastside Boxing & Wellness | B77: Gym | C77: Peterborough | D77: 311 George St N, Peterborough (no public email or phone found) | F77: CCCL | G77: Not contacted | H77: =IF(A77="","",IF(COUNTIFS(Log!$B$5:$B$2000,A77)=0,"",SUMPRODUCT(MAX((Log!$B$5:$B$2000=A77)*Log!$A$5:$A$2000)))) | K77: Cody | L77: =IF(OR(A77="",J77=""),"",IF(J77<TODAY(),"OVERDUE",IF(J77=TODAY(),"TODAY",IF(J77<=TODAY()+7,"THIS WEEK","")))) | M77: Boxing only. Low value as a source of MMA fighters. | N77: https://www.ptbotoday.ca/?p=102471 | O77: =IF(H77="","",TODAY()-H77)
A78: Eris Martial Arts / 10th Planet Jiu Jitsu Peterborough | B78: Gym | C78: Peterborough | D78: info@erismartialarts.com; 705-768-1514; 306 George St N, Peterborough | E78: http://erismartialarts.com/ | F78: CCCL | G78: Not contacted | H78: =IF(A78="","",IF(COUNTIFS(Log!$B$5:$B$2000,A78)=0,"",SUMPRODUCT(MAX((Log!$B$5:$B$2000=A78)*Log!$A$5:$A$2000)))) | K78: Cody | L78: =IF(OR(A78="",J78=""),"",IF(J78<TODAY(),"OVERDUE",IF(J78=TODAY(),"TODAY",IF(J78<=TODAY()+7,"THIS WEEK","")))) | M78: The 10th Planet listing gives an older address (910 High St Unit 15). Use the George St N address from Eris's own site. | N78: http://erismartialarts.com/ | O78: =IF(H78="","",TODAY()-H78)
A79: Kawartha Combat | B79: Gym | C79: Peterborough | D79: kawarthacombat@live.com (on its own site); 705-868-1119 (directory listing); 910 High St Unit 15 | E79: https://www.kawarthacombat.com/ | F79: CCCL | G79: Not contacted | H79: =IF(A79="","",IF(COUNTIFS(Log!$B$5:$B$2000,A79)=0,"",SUMPRODUCT(MAX((Log!$B$5:$B$2000=A79)*Log!$A$5:$A$2000)))) | K79: Cody | L79: =IF(OR(A79="",J79=""),"",IF(J79<TODAY(),"OVERDUE",IF(J79=TODAY(),"TODAY",IF(J79<=TODAY()+7,"THIS WEEK","")))) | N79: https://www.kawarthacombat.com/ | O79: =IF(H79="","",TODAY()-H79)
A80: Kawartha Wrestling Club | B80: Gym | C80: Peterborough | D80: Club contact on the OAWA club listing (https://www.oawa.ca/oawa-club-listing); the listed email is a personal address, so it isn't copied here | F80: CCCL | G80: Not contacted | H80: =IF(A80="","",IF(COUNTIFS(Log!$B$5:$B$2000,A80)=0,"",SUMPRODUCT(MAX((Log!$B$5:$B$2000=A80)*Log!$A$5:$A$2000)))) | K80: Cody | L80: =IF(OR(A80="",J80=""),"",IF(J80<TODAY(),"OVERDUE",IF(J80=TODAY(),"TODAY",IF(J80<=TODAY()+7,"THIS WEEK","")))) | M80: Wrestlers transitioning to MMA are good novice-card prospects. | N80: https://www.oawa.ca/oawa-club-listing | O80: =IF(H80="","",TODAY()-H80)
A81: World Championship Martial Arts | B81: Gym | C81: Peterborough | D81: 705-304-9084; 'Email Us' link on its site (address masked); 871 Chemong Rd Unit 6 & 7 (Brookdale Plaza) | E81: https://worldchampionship.ca/ | F81: CCCL | G81: Not contacted | H81: =IF(A81="","",IF(COUNTIFS(Log!$B$5:$B$2000,A81)=0,"",SUMPRODUCT(MAX((Log!$B$5:$B$2000=A81)*Log!$A$5:$A$2000)))) | K81: Cody | L81: =IF(OR(A81="",J81=""),"",IF(J81<TODAY(),"OVERDUE",IF(J81=TODAY(),"TODAY",IF(J81<=TODAY()+7,"THIS WEEK","")))) | N81: https://worldchampionship.ca/ | O81: =IF(H81="","",TODAY()-H81)
A82: Corcoran's Boxing Club & Fitness Centre (BEL Boxing Club listed at same address) | B82: Gym | C82: Peterborough / Selwyn Twp | D82: corcoranboxing@gmail.com; 705-872-1086 / 705-957-1142; 1625 Chemong Rd. BEL Boxing Club (same address): belboxing@gmail.com, 705-768-0340 (from its kawarthaNOW… | E82: https://corcoransboxingandfitness.com | F82: CCCL | G82: Not contacted | H82: =IF(A82="","",IF(COUNTIFS(Log!$B$5:$B$2000,A82)=0,"",SUMPRODUCT(MAX((Log!$B$5:$B$2000=A82)*Log!$A$5:$A$2000)))) | K82: Cody | L82: =IF(OR(A82="",J82=""),"",IF(J82<TODAY(),"OVERDUE",IF(J82=TODAY(),"TODAY",IF(J82<=TODAY()+7,"THIS WEEK","")))) | M82: Boxing only, no MMA, but it runs its own amateur boxing shows. Check whether BEL Boxing is the same club rebranded. | N82: https://corcoransboxingandfitness.com | O82: =IF(H82="","",TODAY()-H82)
A83: Limitless Martial Arts Trenton | B83: Gym | C83: Trenton (Quinte West) | D83: limitlessbjjtrenton@gmail.com; (613) 827-7401 / 613-955-0343; 99 Dufferin Ave, Trenton | E83: https://www.limitlessbjjtrenton.com/ | F83: CCCL | G83: Not contacted | H83: =IF(A83="","",IF(COUNTIFS(Log!$B$5:$B$2000,A83)=0,"",SUMPRODUCT(MAX((Log!$B$5:$B$2000=A83)*Log!$A$5:$A$2000)))) | K83: Cody | L83: =IF(OR(A83="",J83=""),"",IF(J83<TODAY(),"OVERDUE",IF(J83=TODAY(),"TODAY",IF(J83<=TODAY()+7,"THIS WEEK","")))) | N83: https://www.limitlessbjjtrenton.com/ | O83: =IF(H83="","",TODAY()-H83)
A84: Four-Eleven Brazilian Jiu Jitsu | B84: Gym | C84: Whitby | D84: info@fourelevenbjj.ca; 905-665-7998; 277 Michael Blvd Unit 6, Whitby (Let's Roll directory) | E84: https://fourelevenbjj.ca/ | F84: CCCL | G84: Not contacted | H84: =IF(A84="","",IF(COUNTIFS(Log!$B$5:$B$2000,A84)=0,"",SUMPRODUCT(MAX((Log!$B$5:$B$2000=A84)*Log!$A$5:$A$2000)))) | K84: Cody | L84: =IF(OR(A84="",J84=""),"",IF(J84<TODAY(),"OVERDUE",IF(J84=TODAY(),"TODAY",IF(J84<=TODAY()+7,"THIS WEEK","")))) | N84: https://letsroll.co/gym/four-eleven-brazilian-jiu-jitsu-whitby-on | O84: =IF(H84="","",TODAY()-H84)
A85: Team DNA BJJ | B85: Gym | C85: Whitby | D85: info@dnabjj.com; 416-988-6548; 2001 Thickson Rd S Unit 15, Whitby (Let's Roll directory) | E85: https://www.dnabjj.com/ | F85: CCCL | G85: Not contacted | H85: =IF(A85="","",IF(COUNTIFS(Log!$B$5:$B$2000,A85)=0,"",SUMPRODUCT(MAX((Log!$B$5:$B$2000=A85)*Log!$A$5:$A$2000)))) | K85: Cody | L85: =IF(OR(A85="",J85=""),"",IF(J85<TODAY(),"OVERDUE",IF(J85=TODAY(),"TODAY",IF(J85<=TODAY()+7,"THIS WEEK","")))) | N85: https://letsroll.co/gym/team-dna-bjj-whitby-on | O85: =IF(H85="","",TODAY()-H85)
A86: Bancroft This Week | B86: Media | C86: Bancroft / North Hastings | D86: Reporter Michael Riley: michael@haliburtonpress.com; letters to the editor: jenniferm@haliburtonpress.com (Jennifer McEathron, GM); office 613-332-2002; 254 Hastings St… | F86: Both | G86: Warm | H86: =IF(A86="","",IF(COUNTIFS(Log!$B$5:$B$2000,A86)=0,"",SUMPRODUCT(MAX((Log!$B$5:$B$2000=A86)*Log!$A$5:$A$2000)))) | K86: Cody | L86: =IF(OR(A86="",J86=""),"",IF(J86<TODAY(),"OVERDUE",IF(J86=TODAY(),"TODAY",IF(J86<=TODAY()+7,"THIS WEEK","")))) | M86: Already covers CCCL: 'Bancroft Boxing expanding programs for all ages' (Bill Kilpatrick, Feb 18 2026) describes CCCL and the May 2 Haliburton show; 2019 'Purtell's first… | N86: https://www.bancroftthisweek.com/contact-information | O86: =IF(H86="","",TODAY()-H86)
A87: My Bancroft Now / 97.7 Moose FM (CHMS-FM) | B87: Media | C87: Bancroft / North Hastings | D87: News tip form: https://www.mybancroftnow.com/submit-news-tip/ (Department = 'News & Media', tick 'Is this a news tip?', photos up to 20 MB). Community calendar: https://… | F87: Both | G87: Not contacted | H87: =IF(A87="","",IF(COUNTIFS(Log!$B$5:$B$2000,A87)=0,"",SUMPRODUCT(MAX((Log!$B$5:$B$2000=A87)*Log!$A$5:$A$2000)))) | K87: Cody | L87: =IF(OR(A87="",J87=""),"",IF(J87<TODAY(),"OVERDUE",IF(J87=TODAY(),"TODAY",IF(J87<=TODAY()+7,"THIS WEEK","")))) | M87: Vista Radio station. Its news site mybancroftnow.com ran stories on the NHCC arena renovation. The calendar is free and takes recurring and multi-day events. | N87: https://www.mybancroftnow.com/contact/ | O87: =IF(H87="","",TODAY()-H87)
A88: Belleville Intelligencer (Postmedia) | B88: Media | C88: Belleville / Quinte | D88: No contact verified. The site blocked automated access. Get the newsroom email from the outlet's own Contact Us page at https://www.intelligencer.ca/contact-us | F88: Both | G88: Not contacted | H88: =IF(A88="","",IF(COUNTIFS(Log!$B$5:$B$2000,A88)=0,"",SUMPRODUCT(MAX((Log!$B$5:$B$2000=A88)*Log!$A$5:$A$2000)))) | K88: Cody | L88: =IF(OR(A88="",J88=""),"",IF(J88<TODAY(),"OVERDUE",IF(J88=TODAY(),"TODAY",IF(J88<=TODAY()+7,"THIS WEEK","")))) | M88: Daily for Belleville. Low confidence until the contact is checked by hand. | N88: https://www.intelligencer.ca/contact-us | O88: =IF(H88="","",TODAY()-H88)
A89: Quinte News (Quinte Broadcasting: Mix 97, CJBQ 800, Rock 107) | B89: Media | C89: Belleville / Quinte / Central Hastings (Marmora, Madoc) | D89: News Director Tim Durkin: timdurkin@cjbq.com; reporter John Spitters: johnspitters@rock107.ca; newsroom hotline 613-968-5803. Event calendar form: https://tockify.com/tk… | F89: Both | G89: Not contacted | H89: =IF(A89="","",IF(COUNTIFS(Log!$B$5:$B$2000,A89)=0,"",SUMPRODUCT(MAX((Log!$B$5:$B$2000=A89)*Log!$A$5:$A$2000)))) | K89: Cody | L89: =IF(OR(A89="",J89=""),"",IF(J89<TODAY(),"OVERDUE",IF(J89=TODAY(),"TODAY",IF(J89<=TODAY()+7,"THIS WEEK","")))) | M89: The main radio newsroom for Quinte and Central Hastings. The events page sends commercial events to its sales team, so a ticketed show may be treated as advertising. | N89: https://www.quintenews.com/meet-the-news-team | O89: =IF(H89="","",TODAY()-H89)
A90: inQuinte.ca (affiliated with Cool 100 / Hits 95.5) | B90: Media | C90: Belleville / Quinte West / Hastings | D90: Story form: https://www.inquinte.ca/submit-a-story (categories include Sports; full contact info required). Community calendar form: https://www.inquinte.ca/community-ca… | F90: Both | G90: Not contacted | H90: =IF(A90="","",IF(COUNTIFS(Log!$B$5:$B$2000,A90)=0,"",SUMPRODUCT(MAX((Log!$B$5:$B$2000=A90)*Log!$A$5:$A$2000)))) | K90: Cody | L90: =IF(OR(A90="",J90=""),"",IF(J90<TODAY(),"OVERDUE",IF(J90=TODAY(),"TODAY",IF(J90<=TODAY()+7,"THIS WEEK","")))) | M90: Its 2025 coverage of Pinnacle Boxing's provincial medals shows it covers combat sports. | N90: https://inquinte.ca/ | O90: =IF(H90="","",TODAY()-H90)
A91: MM-Eh (mm-eh.ca) and The MM-EH Show podcast | B91: Media | C91: Canada-wide (strong Ontario regional coverage) | D91: Andy Cotterill: andy@mm-eh.ca (the email in the site header). Also @MMehAndy on X and Instagram. | F91: Both | G91: Not contacted | H91: =IF(A91="","",IF(COUNTIFS(Log!$B$5:$B$2000,A91)=0,"",SUMPRODUCT(MAX((Log!$B$5:$B$2000=A91)*Log!$A$5:$A$2000)))) | K91: Cody | L91: =IF(OR(A91="",J91=""),"",IF(J91<TODAY(),"OVERDUE",IF(J91=TODAY(),"TODAY",IF(J91<=TODAY()+7,"THIS WEEK","")))) | M91: 'Just Canadian MMA.' Lists CCCL 1 (02 May 2026) among completed events but not in its upcoming list, so send every 2027 date to get on its Upcoming Fights page. Publishe… | N91: https://mm-eh.ca/about/ | O91: =IF(H91="","",TODAY()-H91)
A92: Durham Tourism events calendar | B92: Media | C92: Durham Region | D92: Click 'Submit an Event' at DurhamTourism.ca/events (account required). | F92: Both | G92: Not contacted | H92: =IF(A92="","",IF(COUNTIFS(Log!$B$5:$B$2000,A92)=0,"",SUMPRODUCT(MAX((Log!$B$5:$B$2000=A92)*Log!$A$5:$A$2000)))) | K92: Cody | L92: =IF(OR(A92="",J92=""),"",IF(J92<TODAY(),"OVERDUE",IF(J92=TODAY(),"TODAY",IF(J92<=TODAY()+7,"THIS WEEK","")))) | M92: Its policy excludes 'Competitions, fashion shows, pageants' and requires public events with their own landing page, so an MMA card may be refused. Low priority. | N92: https://media-003-ca.cdn.govstack.com/durham-ca/media/1zdcemqd/durham-tourism-event-calendar-submission-policy.pdf | O92: =IF(H92="","",TODAY()-H92)
A93: Sherdog Fight Finder | B93: Media | C93: Global records database | D93: Promoters send results by email to the Fight Finder team. The address is masked on the article page; the 'Official Sherdog Fight Finder Guide' linked from it gives the a… | F93: Both | G93: Not contacted | H93: =IF(A93="","",IF(COUNTIFS(Log!$B$5:$B$2000,A93)=0,"",SUMPRODUCT(MAX((Log!$B$5:$B$2000=A93)*Log!$A$5:$A$2000)))) | K93: Cody | L93: =IF(OR(A93="",J93=""),"",IF(J93<TODAY(),"OVERDUE",IF(J93=TODAY(),"TODAY",IF(J93<=TODAY()+7,"THIS WEEK","")))) | M93: CCCL 1 results are already on Sherdog (event page /events/CCCL-1-Cottage-Country-Combat-League-112672). Keep submitting results after each show so fighters' records stay… | N93: https://sherdog.com/news/articles/The-FFFiles-The-Dos-and-Donts-of-Fight-Finder-The-Dos-181585 | O93: =IF(H93="","",TODAY()-H93)
A94: Canoe FM 100.9 (CKHA-FM) | B94: Media | C94: Haliburton County | D94: info@canoefm.com for Public Service Announcements and 'Highland Happenings'; station manager: manager@canoefm.com; 705-457-1009. Events calendar: https://canoefm.com/can… | F94: Both | G94: Not contacted | H94: =IF(A94="","",IF(COUNTIFS(Log!$B$5:$B$2000,A94)=0,"",SUMPRODUCT(MAX((Log!$B$5:$B$2000=A94)*Log!$A$5:$A$2000)))) | K94: Cody | L94: =IF(OR(A94="",J94=""),"",IF(J94<TODAY(),"OVERDUE",IF(J94=TODAY(),"TODAY",IF(J94<=TODAY()+7,"THIS WEEK","")))) | M94: Community radio. Free PSAs are only for not-for-profits, clubs and local governments, and Highland Happenings only for not-for-profit events. A for-profit CCCL show may… | N94: https://canoefm.com/contact-us/services/ | O94: =IF(H94="","",TODAY()-H94)
A95: Haliburton County Echo | B95: Media | C95: Haliburton County | D95: Editor Emily Stonehouse: emily@haliburtonpress.com; main line 705-457-1037; 146 Highland St, PO Box 360, Haliburton K0M 1S0. Reporter Thomas Smith's address appears as t… | F95: Both | G95: Not contacted | H95: =IF(A95="","",IF(COUNTIFS(Log!$B$5:$B$2000,A95)=0,"",SUMPRODUCT(MAX((Log!$B$5:$B$2000=A95)*Log!$A$5:$A$2000)))) | K95: Cody | L95: =IF(OR(A95="",J95=""),"",IF(J95<TODAY(),"OVERDUE",IF(J95=TODAY(),"TODAY",IF(J95<=TODAY()+7,"THIS WEEK","")))) | M95: Haliburton Press weekly. Shares its editor with the Minden Times. | N95: https://haliburtonecho.ca/contact-us/ | O95: =IF(H95="","",TODAY()-H95)
A96: My Haliburton Now / 93.5 Moose FM | B96: Media | C96: Haliburton County | D96: News tip form: https://www.myhaliburtonnow.com/submit-news-tip/ ; event form: https://www.myhaliburtonnow.com/event-submission/ ; studio 705-457-4855, office 705-457-389… | F96: Both | G96: Not contacted | H96: =IF(A96="","",IF(COUNTIFS(Log!$B$5:$B$2000,A96)=0,"",SUMPRODUCT(MAX((Log!$B$5:$B$2000=A96)*Log!$A$5:$A$2000)))) | K96: Cody | L96: =IF(OR(A96="",J96=""),"",IF(J96<TODAY(),"OVERDUE",IF(J96=TODAY(),"TODAY",IF(J96<=TODAY()+7,"THIS WEEK","")))) | M96: Vista Radio sister station of Moose FM Bancroft, with the same form system. | N96: https://www.myhaliburtonnow.com/contact/ | O96: =IF(H96="","",TODAY()-H96)
A97: The Highlander | B97: Media | C97: Haliburton County | D97: News, tips, photos: news@thehighlander.ca; editor Lisa Gervais: editor@thehighlander.ca; assistant editor Mike Baker: mike@thehighlander.ca; 705-457-2900. | F97: Both | G97: Warm | H97: =IF(A97="","",IF(COUNTIFS(Log!$B$5:$B$2000,A97)=0,"",SUMPRODUCT(MAX((Log!$B$5:$B$2000=A97)*Log!$A$5:$A$2000)))) | K97: Cody | L97: =IF(OR(A97="",J97=""),"",IF(J97<TODAY(),"OVERDUE",IF(J97=TODAY(),"TODAY",IF(J97<=TODAY()+7,"THIS WEEK","")))) | M97: Best proven outlet. Mike Baker wrote 'Fight night coming to Haliburton County' (Mar 12 2026) previewing CCCL 1 and 'Bringing hi-yah to Haliburton' (May 21 2026) on The C… | N97: https://thehighlander.ca/about/ | O97: =IF(H97="","",TODAY()-H97)
... A114: kawarthaNOW | B114: Media | C114: Peterborough & the Kawarthas (also Kawartha Lakes, Northumberland, Haliburton, Hastings) | D114: Media releases and PSAs by email: editor@kawarthanow.com. Free event listings: https://kawarthanow.com/submit-an-event/ (takes at least 48 h to approve; no posters, ALL… | F114: Both | G114: Not contacted | H114: =IF(A114="","",IF(COUNTIFS(Log!$B$5:$B$2000,A114)=0,"",SUMPRODUCT(MAX((Log!$B$5:$B$2000=A114)*Log!$A$5:$A$2000)))) | K114: Cody | L114: =IF(OR(A114="",J114=""),"",IF(J114<TODAY(),"OVERDUE",IF(J114=TODAY(),"TODAY",IF(J114<=TODAY()+7,"THIS WEEK","")))) | M114: The largest regional what's-on site. Its event coverage includes Haliburton County and Hastings County, so every CCCL show in the target towns qualifies. | N114: https://kawarthanow.com/contact/ | O114: =IF(H114="","",TODAY()-H114)
H115: =IF(A115="","",IF(COUNTIFS(Log!$B$5:$B$2000,A115)=0,"",SUMPRODUCT(MAX((Log!$B$5:$B$2000=A115)*Log!$A$5:$A$2000)))) | L115: =IF(OR(A115="",J115=""),"",IF(J115<TODAY(),"OVERDUE",IF(J115=TODAY(),"TODAY",IF(J115<=TODAY()+7,"THIS WEEK","")))) | O115: =IF(H115="","",TODAY()-H115)
H116: =IF(A116="","",IF(COUNTIFS(Log!$B$5:$B$2000,A116)=0,"",SUMPRODUCT(MAX((Log!$B$5:$B$2000=A116)*Log!$A$5:$A$2000)))) | L116: =IF(OR(A116="",J116=""),"",IF(J116<TODAY(),"OVERDUE",IF(J116=TODAY(),"TODAY",IF(J116<=TODAY()+7,"THIS WEEK","")))) | O116: =IF(H116="","",TODAY()-H116)
H117: =IF(A117="","",IF(COUNTIFS(Log!$B$5:$B$2000,A117)=0,"",SUMPRODUCT(MAX((Log!$B$5:$B$2000=A117)*Log!$A$5:$A$2000)))) | L117: =IF(OR(A117="",J117=""),"",IF(J117<TODAY(),"OVERDUE",IF(J117=TODAY(),"TODAY",IF(J117<=TODAY()+7,"THIS WEEK","")))) | O117: =IF(H117="","",TODAY()-H117)
H118: =IF(A118="","",IF(COUNTIFS(Log!$B$5:$B$2000,A118)=0,"",SUMPRODUCT(MAX((Log!$B$5:$B$2000=A118)*Log!$A$5:$A$2000)))) | L118: =IF(OR(A118="",J118=""),"",IF(J118<TODAY(),"OVERDUE",IF(J118=TODAY(),"TODAY",IF(J118<=TODAY()+7,"THIS WEEK","")))) | O118: =IF(H118="","",TODAY()-H118)
H119: =IF(A119="","",IF(COUNTIFS(Log!$B$5:$B$2000,A119)=0,"",SUMPRODUCT(MAX((Log!$B$5:$B$2000=A119)*Log!$A$5:$A$2000)))) | L119: =IF(OR(A119="",J119=""),"",IF(J119<TODAY(),"OVERDUE",IF(J119=TODAY(),"TODAY",IF(J119<=TODAY()+7,"THIS WEEK","")))) | O119: =IF(H119="","",TODAY()-H119)
H120: =IF(A120="","",IF(COUNTIFS(Log!$B$5:$B$2000,A120)=0,"",SUMPRODUCT(MAX((Log!$B$5:$B$2000=A120)*Log!$A$5:$A$2000)))) | L120: =IF(OR(A120="",J120=""),"",IF(J120<TODAY(),"OVERDUE",IF(J120=TODAY(),"TODAY",IF(J120<=TODAY()+7,"THIS WEEK","")))) | O120: =IF(H120="","",TODAY()-H120)
H121: =IF(A121="","",IF(COUNTIFS(Log!$B$5:$B$2000,A121)=0,"",SUMPRODUCT(MAX((Log!$B$5:$B$2000=A121)*Log!$A$5:$A$2000)))) | L121: =IF(OR(A121="",J121=""),"",IF(J121<TODAY(),"OVERDUE",IF(J121=TODAY(),"TODAY",IF(J121<=TODAY()+7,"THIS WEEK","")))) | O121: =IF(H121="","",TODAY()-H121)
H122: =IF(A122="","",IF(COUNTIFS(Log!$B$5:$B$2000,A122)=0,"",SUMPRODUCT(MAX((Log!$B$5:$B$2000=A122)*Log!$A$5:$A$2000)))) | L122: =IF(OR(A122="",J122=""),"",IF(J122<TODAY(),"OVERDUE",IF(J122=TODAY(),"TODAY",IF(J122<=TODAY()+7,"THIS WEEK","")))) | O122: =IF(H122="","",TODAY()-H122)
H123: =IF(A123="","",IF(COUNTIFS(Log!$B$5:$B$2000,A123)=0,"",SUMPRODUCT(MAX((Log!$B$5:$B$2000=A123)*Log!$A$5:$A$2000)))) | L123: =IF(OR(A123="",J123=""),"",IF(J123<TODAY(),"OVERDUE",IF(J123=TODAY(),"TODAY",IF(J123<=TODAY()+7,"THIS WEEK","")))) | O123: =IF(H123="","",TODAY()-H123)
H124: =IF(A124="","",IF(COUNTIFS(Log!$B$5:$B$2000,A124)=0,"",SUMPRODUCT(MAX((Log!$B$5:$B$2000=A124)*Log!$A$5:$A$2000)))) | L124: =IF(OR(A124="",J124=""),"",IF(J124<TODAY(),"OVERDUE",IF(J124=TODAY(),"TODAY",IF(J124<=TODAY()+7,"THIS WEEK","")))) | O124: =IF(H124="","",TODAY()-H124)
H125: =IF(A125="","",IF(COUNTIFS(Log!$B$5:$B$2000,A125)=0,"",SUMPRODUCT(MAX((Log!$B$5:$B$2000=A125)*Log!$A$5:$A$2000)))) | L125: =IF(OR(A125="",J125=""),"",IF(J125<TODAY(),"OVERDUE",IF(J125=TODAY(),"TODAY",IF(J125<=TODAY()+7,"THIS WEEK","")))) | O125: =IF(H125="","",TODAY()-H125)
H126: =IF(A126="","",IF(COUNTIFS(Log!$B$5:$B$2000,A126)=0,"",SUMPRODUCT(MAX((Log!$B$5:$B$2000=A126)*Log!$A$5:$A$2000)))) | L126: =IF(OR(A126="",J126=""),"",IF(J126<TODAY(),"OVERDUE",IF(J126=TODAY(),"TODAY",IF(J126<=TODAY()+7,"THIS WEEK","")))) | O126: =IF(H126="","",TODAY()-H126)
... H264: =IF(A264="","",IF(COUNTIFS(Log!$B$5:$B$2000,A264)=0,"",SUMPRODUCT(MAX((Log!$B$5:$B$2000=A264)*Log!$A$5:$A$2000)))) | L264: =IF(OR(A264="",J264=""),"",IF(J264<TODAY(),"OVERDUE",IF(J264=TODAY(),"TODAY",IF(J264<=TODAY()+7,"THIS WEEK","")))) | O264: =IF(H264="","",TODAY()-H264)

Sheet Log
A1: CONTACT LOG
A2: One row every time someone calls, emails, texts or meets a contact. Newest at the bottom. Copy the next step and date onto the Contacts tab.
A4: Date | B4: Organization (pick from Contacts) | C4: Who (staff) | D4: How | E4: What happened | F4: Next step | G4: Next date
