Workbook

Sheet Start Here
A1: BBG & CCCL MONEY SUMMARY
A2: Paste what the bank, Eventbrite and Gymdesk export. Each line sorts itself by business and category, and the Monthly tab adds it up.
A4: 1 | B4: Export | C4: Once a month, download the transactions as a CSV from the business bank account (and the credit card), plus the Eventbrite payout report and the Gymdesk payments report if you want the detail.
A5: 2 | B5: Delete account numbers first | C5: Bank CSVs often include the account or card number in a column. Delete that column before pasting. Never paste account numbers, card numbers or anyone's banking details into this sheet.
A6: 3 | B6: Paste | C6: On the Transactions tab, paste the date, description and amount into the yellow columns (money in is positive, money out is negative). Pick where it came from.
A7: 4 | B7: Let the rules sort it | C7: Business and Category fill in from the Rules tab (the first keyword found in the description wins). Anything marked Check needs a quick decision: type it in the Override columns.
A8: 5 | B8: Read the Monthly tab | C8: Income, spending and what's left for BBG and CCCL each month, plus shared costs. The Categories tab shows where the money goes over the year.
A9: 6 | B9: Keep the rules growing | C9: When the same kind of line keeps showing up as Check, add a keyword for it on the Rules tab. After a couple of months almost everything sorts itself.
A10: 7 | B10: Second Chance | C10: Second Chance is a separate nonprofit: give it its own bank account and its own copy of this sheet. Never mix its money with BBG or CCCL.
A11: 8 | B11: What this is (and isn't) | C11: A clear monthly picture, built from what actually went through the bank (so only money that was paid counts). It isn't bookkeeping or tax advice: your accountant still does the books and HST.
B13: Business choices
B14: BBG | C14: The gym
B15: CCCL | C15: The fight league and its shows
B16: Shared | C16: Costs that serve both (phone, software, fuel, bank fees). Shown separately on the Monthly tab.
B17: Exclude | C17: Not income or spending: moving money between your own accounts, owner money in or out, personal
B18: Check | C18: The rules couldn't tell: decide and type it in Override
B20: Colours
B21: Yellow, blue text | C21: You type or paste here
B22: Black, bold | C22: Calculated: don't type over it

Sheet Monthly
A1: MONTHLY
A2: Money in, money out and what's left, by business. Excludes transfers, owner money and personal. Shared costs (phone, software, fuel, bank fees) are shown on their own.
A3: Year | B3: 2026 | C3: Change the year to see a different one.
A4: Month | B4: BBG in | C4: BBG out | D4: BBG left | E4: CCCL in | F4: CCCL out | G4: CCCL left | H4: Shared costs (net) | I4: All left | J4: Lines to check
A5: =DATE($B$3,1,1) -> 46023 | B5: =SUMIFS(Transactions!$C$5:$C$3004,Transactions!$I$5:$I$3004,"BBG",Transactions!$K$5:$K$3004,$A5,Transactions!$C$5:$C$3004,">0") -> 0 | C5: =-SUMIFS(Transactions!$C$5:$C$3004,Transactions!$I$5:$I$3004,"BBG",Transactions!$K$5:$K$3004,$A5,Transactions!$C$5:$C$3004,"<0") -> 0 | D5: =B5-C5 -> 0 | E5: =SUMIFS(Transactions!$C$5:$C$3004,Transactions!$I$5:$I$3004,"CCCL",Transactions!$K$5:$K$3004,$A5,Transactions!$C$5:$C$3004,">0") -> 0 | F5: =-SUMIFS(Transactions!$C$5:$C$3004,Transactions!$I$5:$I$3004,"CCCL",Transactions!$K$5:$K$3004,$A5,Transactions!$C$5:$C$3004,"<0") -> 0 | G5: =E5-F5 -> 0 | H5: =-SUMIFS(Transactions!$C$5:$C$3004,Transactions!$I$5:$I$3004,"Shared",Transactions!$K$5:$K$3004,$A5) -> 0 | I5: =D5+G5-H5 -> 0 | J5: =COUNTIFS(Transactions!$I$5:$I$3004,"Check",Transactions!$K$5:$K$3004,$A5) -> 0
A6: =DATE($B$3,2,1) -> 46054 | B6: =SUMIFS(Transactions!$C$5:$C$3004,Transactions!$I$5:$I$3004,"BBG",Transactions!$K$5:$K$3004,$A6,Transactions!$C$5:$C$3004,">0") -> 0 | C6: =-SUMIFS(Transactions!$C$5:$C$3004,Transactions!$I$5:$I$3004,"BBG",Transactions!$K$5:$K$3004,$A6,Transactions!$C$5:$C$3004,"<0") -> 0 | D6: =B6-C6 -> 0 | E6: =SUMIFS(Transactions!$C$5:$C$3004,Transactions!$I$5:$I$3004,"CCCL",Transactions!$K$5:$K$3004,$A6,Transactions!$C$5:$C$3004,">0") -> 0 | F6: =-SUMIFS(Transactions!$C$5:$C$3004,Transactions!$I$5:$I$3004,"CCCL",Transactions!$K$5:$K$3004,$A6,Transactions!$C$5:$C$3004,"<0") -> 0 | G6: =E6-F6 -> 0 | H6: =-SUMIFS(Transactions!$C$5:$C$3004,Transactions!$I$5:$I$3004,"Shared",Transactions!$K$5:$K$3004,$A6) -> 0 | I6: =D6+G6-H6 -> 0 | J6: =COUNTIFS(Transactions!$I$5:$I$3004,"Check",Transactions!$K$5:$K$3004,$A6) -> 0
A7: =DATE($B$3,3,1) -> 46082 | B7: =SUMIFS(Transactions!$C$5:$C$3004,Transactions!$I$5:$I$3004,"BBG",Transactions!$K$5:$K$3004,$A7,Transactions!$C$5:$C$3004,">0") -> 0 | C7: =-SUMIFS(Transactions!$C$5:$C$3004,Transactions!$I$5:$I$3004,"BBG",Transactions!$K$5:$K$3004,$A7,Transactions!$C$5:$C$3004,"<0") -> 0 | D7: =B7-C7 -> 0 | E7: =SUMIFS(Transactions!$C$5:$C$3004,Transactions!$I$5:$I$3004,"CCCL",Transactions!$K$5:$K$3004,$A7,Transactions!$C$5:$C$3004,">0") -> 0 | F7: =-SUMIFS(Transactions!$C$5:$C$3004,Transactions!$I$5:$I$3004,"CCCL",Transactions!$K$5:$K$3004,$A7,Transactions!$C$5:$C$3004,"<0") -> 0 | G7: =E7-F7 -> 0 | H7: =-SUMIFS(Transactions!$C$5:$C$3004,Transactions!$I$5:$I$3004,"Shared",Transactions!$K$5:$K$3004,$A7) -> 0 | I7: =D7+G7-H7 -> 0 | J7: =COUNTIFS(Transactions!$I$5:$I$3004,"Check",Transactions!$K$5:$K$3004,$A7) -> 0
A8: =DATE($B$3,4,1) -> 46113 | B8: =SUMIFS(Transactions!$C$5:$C$3004,Transactions!$I$5:$I$3004,"BBG",Transactions!$K$5:$K$3004,$A8,Transactions!$C$5:$C$3004,">0") -> 0 | C8: =-SUMIFS(Transactions!$C$5:$C$3004,Transactions!$I$5:$I$3004,"BBG",Transactions!$K$5:$K$3004,$A8,Transactions!$C$5:$C$3004,"<0") -> 0 | D8: =B8-C8 -> 0 | E8: =SUMIFS(Transactions!$C$5:$C$3004,Transactions!$I$5:$I$3004,"CCCL",Transactions!$K$5:$K$3004,$A8,Transactions!$C$5:$C$3004,">0") -> 0 | F8: =-SUMIFS(Transactions!$C$5:$C$3004,Transactions!$I$5:$I$3004,"CCCL",Transactions!$K$5:$K$3004,$A8,Transactions!$C$5:$C$3004,"<0") -> 0 | G8: =E8-F8 -> 0 | H8: =-SUMIFS(Transactions!$C$5:$C$3004,Transactions!$I$5:$I$3004,"Shared",Transactions!$K$5:$K$3004,$A8) -> 0 | I8: =D8+G8-H8 -> 0 | J8: =COUNTIFS(Transactions!$I$5:$I$3004,"Check",Transactions!$K$5:$K$3004,$A8) -> 0
A9: =DATE($B$3,5,1) -> 46143 | B9: =SUMIFS(Transactions!$C$5:$C$3004,Transactions!$I$5:$I$3004,"BBG",Transactions!$K$5:$K$3004,$A9,Transactions!$C$5:$C$3004,">0") -> 0 | C9: =-SUMIFS(Transactions!$C$5:$C$3004,Transactions!$I$5:$I$3004,"BBG",Transactions!$K$5:$K$3004,$A9,Transactions!$C$5:$C$3004,"<0") -> 0 | D9: =B9-C9 -> 0 | E9: =SUMIFS(Transactions!$C$5:$C$3004,Transactions!$I$5:$I$3004,"CCCL",Transactions!$K$5:$K$3004,$A9,Transactions!$C$5:$C$3004,">0") -> 0 | F9: =-SUMIFS(Transactions!$C$5:$C$3004,Transactions!$I$5:$I$3004,"CCCL",Transactions!$K$5:$K$3004,$A9,Transactions!$C$5:$C$3004,"<0") -> 0 | G9: =E9-F9 -> 0 | H9: =-SUMIFS(Transactions!$C$5:$C$3004,Transactions!$I$5:$I$3004,"Shared",Transactions!$K$5:$K$3004,$A9) -> 0 | I9: =D9+G9-H9 -> 0 | J9: =COUNTIFS(Transactions!$I$5:$I$3004,"Check",Transactions!$K$5:$K$3004,$A9) -> 0
A10: =DATE($B$3,6,1) -> 46174 | B10: =SUMIFS(Transactions!$C$5:$C$3004,Transactions!$I$5:$I$3004,"BBG",Transactions!$K$5:$K$3004,$A10,Transactions!$C$5:$C$3004,">0") -> 0 | C10: =-SUMIFS(Transactions!$C$5:$C$3004,Transactions!$I$5:$I$3004,"BBG",Transactions!$K$5:$K$3004,$A10,Transactions!$C$5:$C$3004,"<0") -> 0 | D10: =B10-C10 -> 0 | E10: =SUMIFS(Transactions!$C$5:$C$3004,Transactions!$I$5:$I$3004,"CCCL",Transactions!$K$5:$K$3004,$A10,Transactions!$C$5:$C$3004,">0") -> 0 | F10: =-SUMIFS(Transactions!$C$5:$C$3004,Transactions!$I$5:$I$3004,"CCCL",Transactions!$K$5:$K$3004,$A10,Transactions!$C$5:$C$3004,"<0") -> 0 | G10: =E10-F10 -> 0 | H10: =-SUMIFS(Transactions!$C$5:$C$3004,Transactions!$I$5:$I$3004,"Shared",Transactions!$K$5:$K$3004,$A10) -> 0 | I10: =D10+G10-H10 -> 0 | J10: =COUNTIFS(Transactions!$I$5:$I$3004,"Check",Transactions!$K$5:$K$3004,$A10) -> 0
A11: =DATE($B$3,7,1) -> 46204 | B11: =SUMIFS(Transactions!$C$5:$C$3004,Transactions!$I$5:$I$3004,"BBG",Transactions!$K$5:$K$3004,$A11,Transactions!$C$5:$C$3004,">0") -> 0 | C11: =-SUMIFS(Transactions!$C$5:$C$3004,Transactions!$I$5:$I$3004,"BBG",Transactions!$K$5:$K$3004,$A11,Transactions!$C$5:$C$3004,"<0") -> 0 | D11: =B11-C11 -> 0 | E11: =SUMIFS(Transactions!$C$5:$C$3004,Transactions!$I$5:$I$3004,"CCCL",Transactions!$K$5:$K$3004,$A11,Transactions!$C$5:$C$3004,">0") -> 0 | F11: =-SUMIFS(Transactions!$C$5:$C$3004,Transactions!$I$5:$I$3004,"CCCL",Transactions!$K$5:$K$3004,$A11,Transactions!$C$5:$C$3004,"<0") -> 0 | G11: =E11-F11 -> 0 | H11: =-SUMIFS(Transactions!$C$5:$C$3004,Transactions!$I$5:$I$3004,"Shared",Transactions!$K$5:$K$3004,$A11) -> 0 | I11: =D11+G11-H11 -> 0 | J11: =COUNTIFS(Transactions!$I$5:$I$3004,"Check",Transactions!$K$5:$K$3004,$A11) -> 0
A12: =DATE($B$3,8,1) -> 46235 | B12: =SUMIFS(Transactions!$C$5:$C$3004,Transactions!$I$5:$I$3004,"BBG",Transactions!$K$5:$K$3004,$A12,Transactions!$C$5:$C$3004,">0") -> 0 | C12: =-SUMIFS(Transactions!$C$5:$C$3004,Transactions!$I$5:$I$3004,"BBG",Transactions!$K$5:$K$3004,$A12,Transactions!$C$5:$C$3004,"<0") -> 0 | D12: =B12-C12 -> 0 | E12: =SUMIFS(Transactions!$C$5:$C$3004,Transactions!$I$5:$I$3004,"CCCL",Transactions!$K$5:$K$3004,$A12,Transactions!$C$5:$C$3004,">0") -> 0 | F12: =-SUMIFS(Transactions!$C$5:$C$3004,Transactions!$I$5:$I$3004,"CCCL",Transactions!$K$5:$K$3004,$A12,Transactions!$C$5:$C$3004,"<0") -> 0 | G12: =E12-F12 -> 0 | H12: =-SUMIFS(Transactions!$C$5:$C$3004,Transactions!$I$5:$I$3004,"Shared",Transactions!$K$5:$K$3004,$A12) -> 0 | I12: =D12+G12-H12 -> 0 | J12: =COUNTIFS(Transactions!$I$5:$I$3004,"Check",Transactions!$K$5:$K$3004,$A12) -> 0
A13: =DATE($B$3,9,1) -> 46266 | B13: =SUMIFS(Transactions!$C$5:$C$3004,Transactions!$I$5:$I$3004,"BBG",Transactions!$K$5:$K$3004,$A13,Transactions!$C$5:$C$3004,">0") -> 0 | C13: =-SUMIFS(Transactions!$C$5:$C$3004,Transactions!$I$5:$I$3004,"BBG",Transactions!$K$5:$K$3004,$A13,Transactions!$C$5:$C$3004,"<0") -> 0 | D13: =B13-C13 -> 0 | E13: =SUMIFS(Transactions!$C$5:$C$3004,Transactions!$I$5:$I$3004,"CCCL",Transactions!$K$5:$K$3004,$A13,Transactions!$C$5:$C$3004,">0") -> 0 | F13: =-SUMIFS(Transactions!$C$5:$C$3004,Transactions!$I$5:$I$3004,"CCCL",Transactions!$K$5:$K$3004,$A13,Transactions!$C$5:$C$3004,"<0") -> 0 | G13: =E13-F13 -> 0 | H13: =-SUMIFS(Transactions!$C$5:$C$3004,Transactions!$I$5:$I$3004,"Shared",Transactions!$K$5:$K$3004,$A13) -> 0 | I13: =D13+G13-H13 -> 0 | J13: =COUNTIFS(Transactions!$I$5:$I$3004,"Check",Transactions!$K$5:$K$3004,$A13) -> 0
A14: =DATE($B$3,10,1) -> 46296 | B14: =SUMIFS(Transactions!$C$5:$C$3004,Transactions!$I$5:$I$3004,"BBG",Transactions!$K$5:$K$3004,$A14,Transactions!$C$5:$C$3004,">0") -> 0 | C14: =-SUMIFS(Transactions!$C$5:$C$3004,Transactions!$I$5:$I$3004,"BBG",Transactions!$K$5:$K$3004,$A14,Transactions!$C$5:$C$3004,"<0") -> 0 | D14: =B14-C14 -> 0 | E14: =SUMIFS(Transactions!$C$5:$C$3004,Transactions!$I$5:$I$3004,"CCCL",Transactions!$K$5:$K$3004,$A14,Transactions!$C$5:$C$3004,">0") -> 0 | F14: =-SUMIFS(Transactions!$C$5:$C$3004,Transactions!$I$5:$I$3004,"CCCL",Transactions!$K$5:$K$3004,$A14,Transactions!$C$5:$C$3004,"<0") -> 0 | G14: =E14-F14 -> 0 | H14: =-SUMIFS(Transactions!$C$5:$C$3004,Transactions!$I$5:$I$3004,"Shared",Transactions!$K$5:$K$3004,$A14) -> 0 | I14: =D14+G14-H14 -> 0 | J14: =COUNTIFS(Transactions!$I$5:$I$3004,"Check",Transactions!$K$5:$K$3004,$A14) -> 0
A15: =DATE($B$3,11,1) -> 46327 | B15: =SUMIFS(Transactions!$C$5:$C$3004,Transactions!$I$5:$I$3004,"BBG",Transactions!$K$5:$K$3004,$A15,Transactions!$C$5:$C$3004,">0") -> 0 | C15: =-SUMIFS(Transactions!$C$5:$C$3004,Transactions!$I$5:$I$3004,"BBG",Transactions!$K$5:$K$3004,$A15,Transactions!$C$5:$C$3004,"<0") -> 0 | D15: =B15-C15 -> 0 | E15: =SUMIFS(Transactions!$C$5:$C$3004,Transactions!$I$5:$I$3004,"CCCL",Transactions!$K$5:$K$3004,$A15,Transactions!$C$5:$C$3004,">0") -> 0 | F15: =-SUMIFS(Transactions!$C$5:$C$3004,Transactions!$I$5:$I$3004,"CCCL",Transactions!$K$5:$K$3004,$A15,Transactions!$C$5:$C$3004,"<0") -> 0 | G15: =E15-F15 -> 0 | H15: =-SUMIFS(Transactions!$C$5:$C$3004,Transactions!$I$5:$I$3004,"Shared",Transactions!$K$5:$K$3004,$A15) -> 0 | I15: =D15+G15-H15 -> 0 | J15: =COUNTIFS(Transactions!$I$5:$I$3004,"Check",Transactions!$K$5:$K$3004,$A15) -> 0
A16: =DATE($B$3,12,1) -> 46357 | B16: =SUMIFS(Transactions!$C$5:$C$3004,Transactions!$I$5:$I$3004,"BBG",Transactions!$K$5:$K$3004,$A16,Transactions!$C$5:$C$3004,">0") -> 0 | C16: =-SUMIFS(Transactions!$C$5:$C$3004,Transactions!$I$5:$I$3004,"BBG",Transactions!$K$5:$K$3004,$A16,Transactions!$C$5:$C$3004,"<0") -> 0 | D16: =B16-C16 -> 0 | E16: =SUMIFS(Transactions!$C$5:$C$3004,Transactions!$I$5:$I$3004,"CCCL",Transactions!$K$5:$K$3004,$A16,Transactions!$C$5:$C$3004,">0") -> 0 | F16: =-SUMIFS(Transactions!$C$5:$C$3004,Transactions!$I$5:$I$3004,"CCCL",Transactions!$K$5:$K$3004,$A16,Transactions!$C$5:$C$3004,"<0") -> 0 | G16: =E16-F16 -> 0 | H16: =-SUMIFS(Transactions!$C$5:$C$3004,Transactions!$I$5:$I$3004,"Shared",Transactions!$K$5:$K$3004,$A16) -> 0 | I16: =D16+G16-H16 -> 0 | J16: =COUNTIFS(Transactions!$I$5:$I$3004,"Check",Transactions!$K$5:$K$3004,$A16) -> 0
A17: Year | B17: =SUM(B5:B16) -> 0 | C17: =SUM(C5:C16) -> 0 | D17: =SUM(D5:D16) -> 0 | E17: =SUM(E5:E16) -> 0 | F17: =SUM(F5:F16) -> 0 | G17: =SUM(G5:G16) -> 0 | H17: =SUM(H5:H16) -> 0 | I17: =SUM(I5:I16) -> 0 | J17: =SUM(J5:J16) -> 0
A19: Good to know
A20: 'Left' is money in minus money out for the month. It isn't profit for tax purposes (no HST, depreciation or owner pay adjustments).
A21: A show's money lands in the months it moved: sponsor payments when they paid, Eventbrite when it paid out, costs when they were paid.
A22: Lines to check: rows still marked Check. Sort them on the Transactions tab and the totals update.

Sheet Categories
A1: CATEGORIES
A2: Where the money comes from and goes, for the year on the Monthly tab.
A4: Category | B4: Type | C4: BBG | D4: CCCL | E4: Shared | F4: Total
A5: Memberships and classes | B5: Income | C5: =SUMIFS(Transactions!$C$5:$C$3004,Transactions!$J$5:$J$3004,$A5,Transactions!$I$5:$I$3004,"BBG",Transactions!$K$5:$K$3004,">="&DATE(Monthly!$B$3,1,1),Transactions!$K$5:$K$3004,"<="&DATE(Monthly!$B$3,12,1)) -> 0 | D5: =SUMIFS(Transactions!$C$5:$C$3004,Transactions!$J$5:$J$3004,$A5,Transactions!$I$5:$I$3004,"CCCL",Transactions!$K$5:$K$3004,">="&DATE(Monthly!$B$3,1,1),Transactions!$K$5:$K$3004,"<="&DATE(Monthly!$B$3,12,1)) -> 0 | E5: =SUMIFS(Transactions!$C$5:$C$3004,Transactions!$J$5:$J$3004,$A5,Transactions!$I$5:$I$3004,"Shared",Transactions!$K$5:$K$3004,">="&DATE(Monthly!$B$3,1,1),Transactions!$K$5:$K$3004,"<="&DATE(Monthly!$B$3,12,1)) -> 0 | F5: =SUM(C5:E5) -> 0
A6: Drop-ins and trials | B6: Income | C6: =SUMIFS(Transactions!$C$5:$C$3004,Transactions!$J$5:$J$3004,$A6,Transactions!$I$5:$I$3004,"BBG",Transactions!$K$5:$K$3004,">="&DATE(Monthly!$B$3,1,1),Transactions!$K$5:$K$3004,"<="&DATE(Monthly!$B$3,12,1)) -> 0 | D6: =SUMIFS(Transactions!$C$5:$C$3004,Transactions!$J$5:$J$3004,$A6,Transactions!$I$5:$I$3004,"CCCL",Transactions!$K$5:$K$3004,">="&DATE(Monthly!$B$3,1,1),Transactions!$K$5:$K$3004,"<="&DATE(Monthly!$B$3,12,1)) -> 0 | E6: =SUMIFS(Transactions!$C$5:$C$3004,Transactions!$J$5:$J$3004,$A6,Transactions!$I$5:$I$3004,"Shared",Transactions!$K$5:$K$3004,">="&DATE(Monthly!$B$3,1,1),Transactions!$K$5:$K$3004,"<="&DATE(Monthly!$B$3,12,1)) -> 0 | F6: =SUM(C6:E6) -> 0
A7: Personal training | B7: Income | C7: =SUMIFS(Transactions!$C$5:$C$3004,Transactions!$J$5:$J$3004,$A7,Transactions!$I$5:$I$3004,"BBG",Transactions!$K$5:$K$3004,">="&DATE(Monthly!$B$3,1,1),Transactions!$K$5:$K$3004,"<="&DATE(Monthly!$B$3,12,1)) -> 0 | D7: =SUMIFS(Transactions!$C$5:$C$3004,Transactions!$J$5:$J$3004,$A7,Transactions!$I$5:$I$3004,"CCCL",Transactions!$K$5:$K$3004,">="&DATE(Monthly!$B$3,1,1),Transactions!$K$5:$K$3004,"<="&DATE(Monthly!$B$3,12,1)) -> 0 | E7: =SUMIFS(Transactions!$C$5:$C$3004,Transactions!$J$5:$J$3004,$A7,Transactions!$I$5:$I$3004,"Shared",Transactions!$K$5:$K$3004,">="&DATE(Monthly!$B$3,1,1),Transactions!$K$5:$K$3004,"<="&DATE(Monthly!$B$3,12,1)) -> 0 | F7: =SUM(C7:E7) -> 0
A8: Parties and camps | B8: Income | C8: =SUMIFS(Transactions!$C$5:$C$3004,Transactions!$J$5:$J$3004,$A8,Transactions!$I$5:$I$3004,"BBG",Transactions!$K$5:$K$3004,">="&DATE(Monthly!$B$3,1,1),Transactions!$K$5:$K$3004,"<="&DATE(Monthly!$B$3,12,1)) -> 0 | D8: =SUMIFS(Transactions!$C$5:$C$3004,Transactions!$J$5:$J$3004,$A8,Transactions!$I$5:$I$3004,"CCCL",Transactions!$K$5:$K$3004,">="&DATE(Monthly!$B$3,1,1),Transactions!$K$5:$K$3004,"<="&DATE(Monthly!$B$3,12,1)) -> 0 | E8: =SUMIFS(Transactions!$C$5:$C$3004,Transactions!$J$5:$J$3004,$A8,Transactions!$I$5:$I$3004,"Shared",Transactions!$K$5:$K$3004,">="&DATE(Monthly!$B$3,1,1),Transactions!$K$5:$K$3004,"<="&DATE(Monthly!$B$3,12,1)) -> 0 | F8: =SUM(C8:E8) -> 0
A9: Ticket sales | B9: Income | C9: =SUMIFS(Transactions!$C$5:$C$3004,Transactions!$J$5:$J$3004,$A9,Transactions!$I$5:$I$3004,"BBG",Transactions!$K$5:$K$3004,">="&DATE(Monthly!$B$3,1,1),Transactions!$K$5:$K$3004,"<="&DATE(Monthly!$B$3,12,1)) -> 0 | D9: =SUMIFS(Transactions!$C$5:$C$3004,Transactions!$J$5:$J$3004,$A9,Transactions!$I$5:$I$3004,"CCCL",Transactions!$K$5:$K$3004,">="&DATE(Monthly!$B$3,1,1),Transactions!$K$5:$K$3004,"<="&DATE(Monthly!$B$3,12,1)) -> 0 | E9: =SUMIFS(Transactions!$C$5:$C$3004,Transactions!$J$5:$J$3004,$A9,Transactions!$I$5:$I$3004,"Shared",Transactions!$K$5:$K$3004,">="&DATE(Monthly!$B$3,1,1),Transactions!$K$5:$K$3004,"<="&DATE(Monthly!$B$3,12,1)) -> 0 | F9: =SUM(C9:E9) -> 0
A10: Sponsorship | B10: Income | C10: =SUMIFS(Transactions!$C$5:$C$3004,Transactions!$J$5:$J$3004,$A10,Transactions!$I$5:$I$3004,"BBG",Transactions!$K$5:$K$3004,">="&DATE(Monthly!$B$3,1,1),Transactions!$K$5:$K$3004,"<="&DATE(Monthly!$B$3,12,1)) -> 0 | D10: =SUMIFS(Transactions!$C$5:$C$3004,Transactions!$J$5:$J$3004,$A10,Transactions!$I$5:$I$3004,"CCCL",Transactions!$K$5:$K$3004,">="&DATE(Monthly!$B$3,1,1),Transactions!$K$5:$K$3004,"<="&DATE(Monthly!$B$3,12,1)) -> 0 | E10: =SUMIFS(Transactions!$C$5:$C$3004,Transactions!$J$5:$J$3004,$A10,Transactions!$I$5:$I$3004,"Shared",Transactions!$K$5:$K$3004,">="&DATE(Monthly!$B$3,1,1),Transactions!$K$5:$K$3004,"<="&DATE(Monthly!$B$3,12,1)) -> 0 | F10: =SUM(C10:E10) -> 0
A11: Merch | B11: Income | C11: =SUMIFS(Transactions!$C$5:$C$3004,Transactions!$J$5:$J$3004,$A11,Transactions!$I$5:$I$3004,"BBG",Transactions!$K$5:$K$3004,">="&DATE(Monthly!$B$3,1,1),Transactions!$K$5:$K$3004,"<="&DATE(Monthly!$B$3,12,1)) -> 0 | D11: =SUMIFS(Transactions!$C$5:$C$3004,Transactions!$J$5:$J$3004,$A11,Transactions!$I$5:$I$3004,"CCCL",Transactions!$K$5:$K$3004,">="&DATE(Monthly!$B$3,1,1),Transactions!$K$5:$K$3004,"<="&DATE(Monthly!$B$3,12,1)) -> 0 | E11: =SUMIFS(Transactions!$C$5:$C$3004,Transactions!$J$5:$J$3004,$A11,Transactions!$I$5:$I$3004,"Shared",Transactions!$K$5:$K$3004,">="&DATE(Monthly!$B$3,1,1),Transactions!$K$5:$K$3004,"<="&DATE(Monthly!$B$3,12,1)) -> 0 | F11: =SUM(C11:E11) -> 0
A12: Livestream | B12: Income | C12: =SUMIFS(Transactions!$C$5:$C$3004,Transactions!$J$5:$J$3004,$A12,Transactions!$I$5:$I$3004,"BBG",Transactions!$K$5:$K$3004,">="&DATE(Monthly!$B$3,1,1),Transactions!$K$5:$K$3004,"<="&DATE(Monthly!$B$3,12,1)) -> 0 | D12: =SUMIFS(Transactions!$C$5:$C$3004,Transactions!$J$5:$J$3004,$A12,Transactions!$I$5:$I$3004,"CCCL",Transactions!$K$5:$K$3004,">="&DATE(Monthly!$B$3,1,1),Transactions!$K$5:$K$3004,"<="&DATE(Monthly!$B$3,12,1)) -> 0 | E12: =SUMIFS(Transactions!$C$5:$C$3004,Transactions!$J$5:$J$3004,$A12,Transactions!$I$5:$I$3004,"Shared",Transactions!$K$5:$K$3004,">="&DATE(Monthly!$B$3,1,1),Transactions!$K$5:$K$3004,"<="&DATE(Monthly!$B$3,12,1)) -> 0 | F12: =SUM(C12:E12) -> 0
A13: Grants | B13: Income | C13: =SUMIFS(Transactions!$C$5:$C$3004,Transactions!$J$5:$J$3004,$A13,Transactions!$I$5:$I$3004,"BBG",Transactions!$K$5:$K$3004,">="&DATE(Monthly!$B$3,1,1),Transactions!$K$5:$K$3004,"<="&DATE(Monthly!$B$3,12,1)) -> 0 | D13: =SUMIFS(Transactions!$C$5:$C$3004,Transactions!$J$5:$J$3004,$A13,Transactions!$I$5:$I$3004,"CCCL",Transactions!$K$5:$K$3004,">="&DATE(Monthly!$B$3,1,1),Transactions!$K$5:$K$3004,"<="&DATE(Monthly!$B$3,12,1)) -> 0 | E13: =SUMIFS(Transactions!$C$5:$C$3004,Transactions!$J$5:$J$3004,$A13,Transactions!$I$5:$I$3004,"Shared",Transactions!$K$5:$K$3004,">="&DATE(Monthly!$B$3,1,1),Transactions!$K$5:$K$3004,"<="&DATE(Monthly!$B$3,12,1)) -> 0 | F13: =SUM(C13:E13) -> 0
A14: Other income | B14: Income | C14: =SUMIFS(Transactions!$C$5:$C$3004,Transactions!$J$5:$J$3004,$A14,Transactions!$I$5:$I$3004,"BBG",Transactions!$K$5:$K$3004,">="&DATE(Monthly!$B$3,1,1),Transactions!$K$5:$K$3004,"<="&DATE(Monthly!$B$3,12,1)) -> 0 | D14: =SUMIFS(Transactions!$C$5:$C$3004,Transactions!$J$5:$J$3004,$A14,Transactions!$I$5:$I$3004,"CCCL",Transactions!$K$5:$K$3004,">="&DATE(Monthly!$B$3,1,1),Transactions!$K$5:$K$3004,"<="&DATE(Monthly!$B$3,12,1)) -> 0 | E14: =SUMIFS(Transactions!$C$5:$C$3004,Transactions!$J$5:$J$3004,$A14,Transactions!$I$5:$I$3004,"Shared",Transactions!$K$5:$K$3004,">="&DATE(Monthly!$B$3,1,1),Transactions!$K$5:$K$3004,"<="&DATE(Monthly!$B$3,12,1)) -> 0 | F14: =SUM(C14:E14) -> 0
A15: Rent | B15: Expense | C15: =SUMIFS(Transactions!$C$5:$C$3004,Transactions!$J$5:$J$3004,$A15,Transactions!$I$5:$I$3004,"BBG",Transactions!$K$5:$K$3004,">="&DATE(Monthly!$B$3,1,1),Transactions!$K$5:$K$3004,"<="&DATE(Monthly!$B$3,12,1)) -> 0 | D15: =SUMIFS(Transactions!$C$5:$C$3004,Transactions!$J$5:$J$3004,$A15,Transactions!$I$5:$I$3004,"CCCL",Transactions!$K$5:$K$3004,">="&DATE(Monthly!$B$3,1,1),Transactions!$K$5:$K$3004,"<="&DATE(Monthly!$B$3,12,1)) -> 0 | E15: =SUMIFS(Transactions!$C$5:$C$3004,Transactions!$J$5:$J$3004,$A15,Transactions!$I$5:$I$3004,"Shared",Transactions!$K$5:$K$3004,">="&DATE(Monthly!$B$3,1,1),Transactions!$K$5:$K$3004,"<="&DATE(Monthly!$B$3,12,1)) -> 0 | F15: =SUM(C15:E15) -> 0
A16: Utilities | B16: Expense | C16: =SUMIFS(Transactions!$C$5:$C$3004,Transactions!$J$5:$J$3004,$A16,Transactions!$I$5:$I$3004,"BBG",Transactions!$K$5:$K$3004,">="&DATE(Monthly!$B$3,1,1),Transactions!$K$5:$K$3004,"<="&DATE(Monthly!$B$3,12,1)) -> 0 | D16: =SUMIFS(Transactions!$C$5:$C$3004,Transactions!$J$5:$J$3004,$A16,Transactions!$I$5:$I$3004,"CCCL",Transactions!$K$5:$K$3004,">="&DATE(Monthly!$B$3,1,1),Transactions!$K$5:$K$3004,"<="&DATE(Monthly!$B$3,12,1)) -> 0 | E16: =SUMIFS(Transactions!$C$5:$C$3004,Transactions!$J$5:$J$3004,$A16,Transactions!$I$5:$I$3004,"Shared",Transactions!$K$5:$K$3004,">="&DATE(Monthly!$B$3,1,1),Transactions!$K$5:$K$3004,"<="&DATE(Monthly!$B$3,12,1)) -> 0 | F16: =SUM(C16:E16) -> 0
... A30: Other expense | B30: Expense | C30: =SUMIFS(Transactions!$C$5:$C$3004,Transactions!$J$5:$J$3004,$A30,Transactions!$I$5:$I$3004,"BBG",Transactions!$K$5:$K$3004,">="&DATE(Monthly!$B$3,1,1),Transactions!$K$5:$K$3004,"<="&DATE(Monthly!$B$3,12,1)) -> 0 | D30: =SUMIFS(Transactions!$C$5:$C$3004,Transactions!$J$5:$J$3004,$A30,Transactions!$I$5:$I$3004,"CCCL",Transactions!$K$5:$K$3004,">="&DATE(Monthly!$B$3,1,1),Transactions!$K$5:$K$3004,"<="&DATE(Monthly!$B$3,12,1)) -> 0 | E30: =SUMIFS(Transactions!$C$5:$C$3004,Transactions!$J$5:$J$3004,$A30,Transactions!$I$5:$I$3004,"Shared",Transactions!$K$5:$K$3004,">="&DATE(Monthly!$B$3,1,1),Transactions!$K$5:$K$3004,"<="&DATE(Monthly!$B$3,12,1)) -> 0 | F30: =SUM(C30:E30) -> 0
A31: Income total | C31: =SUMIFS(C5:C30,$B$5:$B$30,"Income") -> 0 | D31: =SUMIFS(D5:D30,$B$5:$B$30,"Income") -> 0 | E31: =SUMIFS(E5:E30,$B$5:$B$30,"Income") -> 0 | F31: =SUMIFS(F5:F30,$B$5:$B$30,"Income") -> 0
A32: Spending total | C32: =SUMIFS(C5:C30,$B$5:$B$30,"Expense") -> 0 | D32: =SUMIFS(D5:D30,$B$5:$B$30,"Expense") -> 0 | E32: =SUMIFS(E5:E30,$B$5:$B$30,"Expense") -> 0 | F32: =SUMIFS(F5:F30,$B$5:$B$30,"Expense") -> 0
A34: Spending shows as negative numbers. Uncategorized lines (Check) and Exclude lines aren't counted here.

Sheet Transactions
A1: TRANSACTIONS
A2: Paste date, description and amount into the yellow columns. Business and Category come from the Rules tab; type in Override to change one.
A4: Date | B4: Description (from the bank) | C4: Amount (+ in, - out) | D4: From | E4: Rule business | F4: Rule category | G4: Override business | H4: Override category | I4: Business | J4: Category | K4: Month | L4: Type | M4: Note | N4: Rule row
E5: =IF(OR(B5="",N(N5)=0,N5=1000),IF(B5="","","Check"),INDEX(Rules!$B:$B,N5)) | F5: =IF(OR(B5="",N(N5)=0,N5=1000),"",INDEX(Rules!$C:$C,N5)) | I5: =IF(B5="","",IF(G5<>"",G5,E5)) | J5: =IF(B5="","",IF(H5<>"",H5,F5)) | K5: =IF(A5="","",DATE(YEAR(A5),MONTH(A5),1)) | L5: =IF(J5="",IF(B5="","",IF(N(C5)>=0,"Income","Expense")),IFERROR(INDEX(Lists!$B$2:$B$30,MATCH(J5,Lists!$A$2:$A$30,0)),"")) | N5: =IF(B5="","",IFERROR(1000-SUMPRODUCT(MAX(ISNUMBER(SEARCH(Rules!$A$5:$A$204,B5))*(Rules!$A$5:$A$204<>"")*(1000-ROW(Rules!$A$5:$A$204)))),""))
E6: =IF(OR(B6="",N(N6)=0,N6=1000),IF(B6="","","Check"),INDEX(Rules!$B:$B,N6)) | F6: =IF(OR(B6="",N(N6)=0,N6=1000),"",INDEX(Rules!$C:$C,N6)) | I6: =IF(B6="","",IF(G6<>"",G6,E6)) | J6: =IF(B6="","",IF(H6<>"",H6,F6)) | K6: =IF(A6="","",DATE(YEAR(A6),MONTH(A6),1)) | L6: =IF(J6="",IF(B6="","",IF(N(C6)>=0,"Income","Expense")),IFERROR(INDEX(Lists!$B$2:$B$30,MATCH(J6,Lists!$A$2:$A$30,0)),"")) | N6: =IF(B6="","",IFERROR(1000-SUMPRODUCT(MAX(ISNUMBER(SEARCH(Rules!$A$5:$A$204,B6))*(Rules!$A$5:$A$204<>"")*(1000-ROW(Rules!$A$5:$A$204)))),""))
E7: =IF(OR(B7="",N(N7)=0,N7=1000),IF(B7="","","Check"),INDEX(Rules!$B:$B,N7)) | F7: =IF(OR(B7="",N(N7)=0,N7=1000),"",INDEX(Rules!$C:$C,N7)) | I7: =IF(B7="","",IF(G7<>"",G7,E7)) | J7: =IF(B7="","",IF(H7<>"",H7,F7)) | K7: =IF(A7="","",DATE(YEAR(A7),MONTH(A7),1)) | L7: =IF(J7="",IF(B7="","",IF(N(C7)>=0,"Income","Expense")),IFERROR(INDEX(Lists!$B$2:$B$30,MATCH(J7,Lists!$A$2:$A$30,0)),"")) | N7: =IF(B7="","",IFERROR(1000-SUMPRODUCT(MAX(ISNUMBER(SEARCH(Rules!$A$5:$A$204,B7))*(Rules!$A$5:$A$204<>"")*(1000-ROW(Rules!$A$5:$A$204)))),""))
E8: =IF(OR(B8="",N(N8)=0,N8=1000),IF(B8="","","Check"),INDEX(Rules!$B:$B,N8)) | F8: =IF(OR(B8="",N(N8)=0,N8=1000),"",INDEX(Rules!$C:$C,N8)) | I8: =IF(B8="","",IF(G8<>"",G8,E8)) | J8: =IF(B8="","",IF(H8<>"",H8,F8)) | K8: =IF(A8="","",DATE(YEAR(A8),MONTH(A8),1)) | L8: =IF(J8="",IF(B8="","",IF(N(C8)>=0,"Income","Expense")),IFERROR(INDEX(Lists!$B$2:$B$30,MATCH(J8,Lists!$A$2:$A$30,0)),"")) | N8: =IF(B8="","",IFERROR(1000-SUMPRODUCT(MAX(ISNUMBER(SEARCH(Rules!$A$5:$A$204,B8))*(Rules!$A$5:$A$204<>"")*(1000-ROW(Rules!$A$5:$A$204)))),""))
E9: =IF(OR(B9="",N(N9)=0,N9=1000),IF(B9="","","Check"),INDEX(Rules!$B:$B,N9)) | F9: =IF(OR(B9="",N(N9)=0,N9=1000),"",INDEX(Rules!$C:$C,N9)) | I9: =IF(B9="","",IF(G9<>"",G9,E9)) | J9: =IF(B9="","",IF(H9<>"",H9,F9)) | K9: =IF(A9="","",DATE(YEAR(A9),MONTH(A9),1)) | L9: =IF(J9="",IF(B9="","",IF(N(C9)>=0,"Income","Expense")),IFERROR(INDEX(Lists!$B$2:$B$30,MATCH(J9,Lists!$A$2:$A$30,0)),"")) | N9: =IF(B9="","",IFERROR(1000-SUMPRODUCT(MAX(ISNUMBER(SEARCH(Rules!$A$5:$A$204,B9))*(Rules!$A$5:$A$204<>"")*(1000-ROW(Rules!$A$5:$A$204)))),""))
E10: =IF(OR(B10="",N(N10)=0,N10=1000),IF(B10="","","Check"),INDEX(Rules!$B:$B,N10)) | F10: =IF(OR(B10="",N(N10)=0,N10=1000),"",INDEX(Rules!$C:$C,N10)) | I10: =IF(B10="","",IF(G10<>"",G10,E10)) | J10: =IF(B10="","",IF(H10<>"",H10,F10)) | K10: =IF(A10="","",DATE(YEAR(A10),MONTH(A10),1)) | L10: =IF(J10="",IF(B10="","",IF(N(C10)>=0,"Income","Expense")),IFERROR(INDEX(Lists!$B$2:$B$30,MATCH(J10,Lists!$A$2:$A$30,0)),"")) | N10: =IF(B10="","",IFERROR(1000-SUMPRODUCT(MAX(ISNUMBER(SEARCH(Rules!$A$5:$A$204,B10))*(Rules!$A$5:$A$204<>"")*(1000-ROW(Rules!$A$5:$A$204)))),""))
E11: =IF(OR(B11="",N(N11)=0,N11=1000),IF(B11="","","Check"),INDEX(Rules!$B:$B,N11)) | F11: =IF(OR(B11="",N(N11)=0,N11=1000),"",INDEX(Rules!$C:$C,N11)) | I11: =IF(B11="","",IF(G11<>"",G11,E11)) | J11: =IF(B11="","",IF(H11<>"",H11,F11)) | K11: =IF(A11="","",DATE(YEAR(A11),MONTH(A11),1)) | L11: =IF(J11="",IF(B11="","",IF(N(C11)>=0,"Income","Expense")),IFERROR(INDEX(Lists!$B$2:$B$30,MATCH(J11,Lists!$A$2:$A$30,0)),"")) | N11: =IF(B11="","",IFERROR(1000-SUMPRODUCT(MAX(ISNUMBER(SEARCH(Rules!$A$5:$A$204,B11))*(Rules!$A$5:$A$204<>"")*(1000-ROW(Rules!$A$5:$A$204)))),""))
E12: =IF(OR(B12="",N(N12)=0,N12=1000),IF(B12="","","Check"),INDEX(Rules!$B:$B,N12)) | F12: =IF(OR(B12="",N(N12)=0,N12=1000),"",INDEX(Rules!$C:$C,N12)) | I12: =IF(B12="","",IF(G12<>"",G12,E12)) | J12: =IF(B12="","",IF(H12<>"",H12,F12)) | K12: =IF(A12="","",DATE(YEAR(A12),MONTH(A12),1)) | L12: =IF(J12="",IF(B12="","",IF(N(C12)>=0,"Income","Expense")),IFERROR(INDEX(Lists!$B$2:$B$30,MATCH(J12,Lists!$A$2:$A$30,0)),"")) | N12: =IF(B12="","",IFERROR(1000-SUMPRODUCT(MAX(ISNUMBER(SEARCH(Rules!$A$5:$A$204,B12))*(Rules!$A$5:$A$204<>"")*(1000-ROW(Rules!$A$5:$A$204)))),""))
E13: =IF(OR(B13="",N(N13)=0,N13=1000),IF(B13="","","Check"),INDEX(Rules!$B:$B,N13)) | F13: =IF(OR(B13="",N(N13)=0,N13=1000),"",INDEX(Rules!$C:$C,N13)) | I13: =IF(B13="","",IF(G13<>"",G13,E13)) | J13: =IF(B13="","",IF(H13<>"",H13,F13)) | K13: =IF(A13="","",DATE(YEAR(A13),MONTH(A13),1)) | L13: =IF(J13="",IF(B13="","",IF(N(C13)>=0,"Income","Expense")),IFERROR(INDEX(Lists!$B$2:$B$30,MATCH(J13,Lists!$A$2:$A$30,0)),"")) | N13: =IF(B13="","",IFERROR(1000-SUMPRODUCT(MAX(ISNUMBER(SEARCH(Rules!$A$5:$A$204,B13))*(Rules!$A$5:$A$204<>"")*(1000-ROW(Rules!$A$5:$A$204)))),""))
E14: =IF(OR(B14="",N(N14)=0,N14=1000),IF(B14="","","Check"),INDEX(Rules!$B:$B,N14)) | F14: =IF(OR(B14="",N(N14)=0,N14=1000),"",INDEX(Rules!$C:$C,N14)) | I14: =IF(B14="","",IF(G14<>"",G14,E14)) | J14: =IF(B14="","",IF(H14<>"",H14,F14)) | K14: =IF(A14="","",DATE(YEAR(A14),MONTH(A14),1)) | L14: =IF(J14="",IF(B14="","",IF(N(C14)>=0,"Income","Expense")),IFERROR(INDEX(Lists!$B$2:$B$30,MATCH(J14,Lists!$A$2:$A$30,0)),"")) | N14: =IF(B14="","",IFERROR(1000-SUMPRODUCT(MAX(ISNUMBER(SEARCH(Rules!$A$5:$A$204,B14))*(Rules!$A$5:$A$204<>"")*(1000-ROW(Rules!$A$5:$A$204)))),""))
E15: =IF(OR(B15="",N(N15)=0,N15=1000),IF(B15="","","Check"),INDEX(Rules!$B:$B,N15)) | F15: =IF(OR(B15="",N(N15)=0,N15=1000),"",INDEX(Rules!$C:$C,N15)) | I15: =IF(B15="","",IF(G15<>"",G15,E15)) | J15: =IF(B15="","",IF(H15<>"",H15,F15)) | K15: =IF(A15="","",DATE(YEAR(A15),MONTH(A15),1)) | L15: =IF(J15="",IF(B15="","",IF(N(C15)>=0,"Income","Expense")),IFERROR(INDEX(Lists!$B$2:$B$30,MATCH(J15,Lists!$A$2:$A$30,0)),"")) | N15: =IF(B15="","",IFERROR(1000-SUMPRODUCT(MAX(ISNUMBER(SEARCH(Rules!$A$5:$A$204,B15))*(Rules!$A$5:$A$204<>"")*(1000-ROW(Rules!$A$5:$A$204)))),""))
E16: =IF(OR(B16="",N(N16)=0,N16=1000),IF(B16="","","Check"),INDEX(Rules!$B:$B,N16)) | F16: =IF(OR(B16="",N(N16)=0,N16=1000),"",INDEX(Rules!$C:$C,N16)) | I16: =IF(B16="","",IF(G16<>"",G16,E16)) | J16: =IF(B16="","",IF(H16<>"",H16,F16)) | K16: =IF(A16="","",DATE(YEAR(A16),MONTH(A16),1)) | L16: =IF(J16="",IF(B16="","",IF(N(C16)>=0,"Income","Expense")),IFERROR(INDEX(Lists!$B$2:$B$30,MATCH(J16,Lists!$A$2:$A$30,0)),"")) | N16: =IF(B16="","",IFERROR(1000-SUMPRODUCT(MAX(ISNUMBER(SEARCH(Rules!$A$5:$A$204,B16))*(Rules!$A$5:$A$204<>"")*(1000-ROW(Rules!$A$5:$A$204)))),""))
... E3004: =IF(OR(B3004="",N(N3004)=0,N3004=1000),IF(B3004="","","Check"),INDEX(Rules!$B:$B,N3004)) | F3004: =IF(OR(B3004="",N(N3004)=0,N3004=1000),"",INDEX(Rules!$C:$C,N3004)) | I3004: =IF(B3004="","",IF(G3004<>"",G3004,E3004)) | J3004: =IF(B3004="","",IF(H3004<>"",H3004,F3004)) | K3004: =IF(A3004="","",DATE(YEAR(A3004),MONTH(A3004),1)) | L3004: =IF(J3004="",IF(B3004="","",IF(N(C3004)>=0,"Income","Expense")),IFERROR(INDEX(Lists!$B$2:$B$30,MATCH(J3004,Lists!$A$2:$A$30,0)),"")) | N3004: =IF(B3004="","",IFERROR(1000-SUMPRODUCT(MAX(ISNUMBER(SEARCH(Rules!$A$5:$A$204,B3004))*(Rules!$A$5:$A$204<>"")*(1000-ROW(Rules!$A$5:$A$204)))),""))

Sheet Rules
A1: RULES
A2: If a transaction's description contains the keyword (capitals don't matter), it gets this business and category. The first rule that matches wins, so put specific keywords above general ones.
A4: Keyword in the description | B4: Business | C4: Category | D4: Notes
A5: EVENTBRITE | B5: CCCL | C5: Ticket sales | D5: Eventbrite payouts (already after Eventbrite's fees)
A6: GYMDESK | B6: BBG | C6: Memberships and classes | D6: Gymdesk payouts; check the wording on your statement
A7: ONTARIO ATHLETICS | B7: CCCL | C7: Permits and fees | D7: Athletics Commission permit
A8: FACEBK | B8: Check | C8: Marketing and ads | D8: Meta ads: pick BBG or CCCL for each one
A9: META | B9: Check | C9: Marketing and ads | D9: Meta ads: pick BBG or CCCL
A10: CANVA | B10: Shared | C10: Software and subscriptions
A11: GOOGLE | B11: Shared | C11: Software and subscriptions | D11: Google Workspace or storage
A12: ANTHROPIC | B12: Shared | C12: Software and subscriptions | D12: Claude subscription
A13: CLAUDE.AI | B13: Shared | C13: Software and subscriptions | D13: Claude subscription
A14: HYDRO | B14: BBG | C14: Utilities | D14: Gym hydro
A15: ENBRIDGE | B15: BBG | C15: Utilities | D15: Gas
A16: BELL | B16: Shared | C16: Phone and internet
A17: ROGERS | B17: Shared | C17: Phone and internet
A18: INSURANCE | B18: Check | C18: Insurance | D18: Gym or event insurance: pick the business
A19: SERVICE CHARGE | B19: Shared | C19: Bank and payment fees
A20: MONTHLY FEE | B20: Shared | C20: Bank and payment fees
A21: E-TRANSFER | B21: Check | C21: Other income | D21: Interac e-Transfers: could be a member, a sponsor or a transfer. Pick each one
A22: ETRANSFER | B22: Check | C22: Other income | D22: Same as above
A23: TRANSFER TO | B23: Exclude | C23: Transfer | D23: Moving money between your own accounts isn't income or spending
A24: TRANSFER FROM | B24: Exclude | C24: Transfer
A25: AMAZON | B25: Check | C25: Supplies | D25: Pick the business
A26: CANADIAN TIRE | B26: Check | C26: Supplies
A27: HOME DEPOT | B27: BBG | C27: Supplies
A28: STAPLES | B28: Shared | C28: Supplies | D28: Printing, office
A29: ESSO | B29: Shared | C29: Travel | D29: Fuel
A30: PETRO | B30: Shared | C30: Travel | D30: Fuel
A31: SHELL | B31: Shared | C31: Travel | D31: Fuel

Sheet Lists
A1: Category | B1: Type | D1: Business
A2: Memberships and classes | B2: Income | D2: BBG
A3: Drop-ins and trials | B3: Income | D3: CCCL
A4: Personal training | B4: Income | D4: Shared
A5: Parties and camps | B5: Income | D5: Exclude
A6: Ticket sales | B6: Income | D6: Check
A7: Sponsorship | B7: Income
A8: Merch | B8: Income
A9: Livestream | B9: Income
A10: Grants | B10: Income
A11: Other income | B11: Income
A12: Rent | B12: Expense
A13: Utilities | B13: Expense
A14: Phone and internet | B14: Expense
A15: Insurance | B15: Expense
A16: Equipment | B16: Expense
A17: Software and subscriptions | B17: Expense
A18: Marketing and ads | B18: Expense
... A30: Personal | B30: Other
