Workbook

Sheet Start Here
A1: CONSTRICTOR HQ: START HERE
A2: Cody's command centre for BBG and CCCL. Built by Kyle. Opens in Google Sheets or Excel.
B4: Dashboard | C4: The one screen: approvals waiting, overdue tasks, this week's posts, the weekly numbers.
B5: Tasks | C5: Every job for the team. Owner, due date, status. Overdue ones turn red on the Dashboard.
B6: Approvals | C6: Everything waiting for a yes before it goes out: sponsor pitches, posts, member messages, money.
B7: Content Calendar | C7: Planned posts. The first four weeks are drafted. Check class times before posting.
B8: Links | C8: Paste the Google Drive link of each other sheet here.
B9: Every morning | C9: Claude's morning report reads this sheet plus Gmail, Calendar, the Sponsorship Pipeline and the Leads sheet, and tells Cody what matters today.
B10: Colour key | C10: Yellow cells with blue text are for typing. Red text and black text are calculated. Rows marked (Example) show the format; delete them.
B12: Handoff date
C13: Kyle types the sit-down date here before upload. The starter tasks' due dates count from it, and the first four weeks of posts start the Monday after.

Sheet Dashboard
A1: THE CONSTRICTOR HQ
A2: Cody's one screen. Open it every morning (it works on a phone). Tasks, approvals and posts update by themselves; the weekly numbers are filled in from Monday's report.
A4: Today | B4: =TODAY() -> 46322
A6: NEEDS CODY NOW
A7: Approvals waiting | B7: =COUNTIFS(Approvals!$G$5:$G$304,"Waiting",Approvals!$B$5:$B$304,"<>") -> 1
A8: Oldest approval waiting (days) | B8: =IFERROR(_xlfn.MAXIFS(Approvals!$I$5:$I$304,Approvals!$G$5:$G$304,"Waiting"),0) -> 7
A9: Tasks overdue | B9: =COUNTIF(Tasks!$G$5:$G$404,"OVERDUE") -> 0
A10: Tasks due today | B10: =COUNTIF(Tasks!$G$5:$G$404,"TODAY") -> 0
A12: TEAM TASKS
A13: Open tasks | B13: =COUNTIFS(Tasks!$A$5:$A$404,"<>",Tasks!$F$5:$F$404,"<>Done") -> 24
A14: Due in the next 7 days | B14: =COUNTIFS(Tasks!$F$5:$F$404,"<>Done",Tasks!$D$5:$D$404,">="&TODAY(),Tasks!$D$5:$D$404,"<="&(TODAY()+7)) -> 0
A15: Done in the last 7 days | B15: =COUNTIFS(Tasks!$F$5:$F$404,"Done",Tasks!$I$5:$I$404,">="&(TODAY()-7)) -> 0
A16: Open for Cody | B16: =COUNTIFS(Tasks!$C$5:$C$404,"Cody",Tasks!$F$5:$F$404,"<>Done",Tasks!$A$5:$A$404,"<>") -> 22
A17: Open for Kyle | B17: =COUNTIFS(Tasks!$C$5:$C$404,"Kyle",Tasks!$F$5:$F$404,"<>Done",Tasks!$A$5:$A$404,"<>") -> 2
A18: Open for Sean | B18: =COUNTIFS(Tasks!$C$5:$C$404,"Sean",Tasks!$F$5:$F$404,"<>Done",Tasks!$A$5:$A$404,"<>") -> 0
A19: Open for Jordan | B19: =COUNTIFS(Tasks!$C$5:$C$404,"Jordan",Tasks!$F$5:$F$404,"<>Done",Tasks!$A$5:$A$404,"<>") -> 0
A20: Open for Front desk | B20: =COUNTIFS(Tasks!$C$5:$C$404,"Front desk",Tasks!$F$5:$F$404,"<>Done",Tasks!$A$5:$A$404,"<>") -> 0
A21: Open for Volunteer | B21: =COUNTIFS(Tasks!$C$5:$C$404,"Volunteer",Tasks!$F$5:$F$404,"<>Done",Tasks!$A$5:$A$404,"<>") -> 0
A23: POSTS THIS WEEK (MON-SUN)
A24: Idea | B24: =COUNTIFS('Content Calendar'!$A$5:$A$304,">="&(TODAY()-WEEKDAY(TODAY(),3)),'Content Calendar'!$A$5:$A$304,"<="&((TODAY()-WEEKDAY(TODAY(),3))+6),'Content Calendar'!$G$5:$G$304,"Idea") -> 0
A25: Drafted | B25: =COUNTIFS('Content Calendar'!$A$5:$A$304,">="&(TODAY()-WEEKDAY(TODAY(),3)),'Content Calendar'!$A$5:$A$304,"<="&((TODAY()-WEEKDAY(TODAY(),3))+6),'Content Calendar'!$G$5:$G$304,"Drafted") -> 0
A26: Approved | B26: =COUNTIFS('Content Calendar'!$A$5:$A$304,">="&(TODAY()-WEEKDAY(TODAY(),3)),'Content Calendar'!$A$5:$A$304,"<="&((TODAY()-WEEKDAY(TODAY(),3))+6),'Content Calendar'!$G$5:$G$304,"Approved") -> 0
A27: Posted | B27: =COUNTIFS('Content Calendar'!$A$5:$A$304,">="&(TODAY()-WEEKDAY(TODAY(),3)),'Content Calendar'!$A$5:$A$304,"<="&((TODAY()-WEEKDAY(TODAY(),3))+6),'Content Calendar'!$G$5:$G$304,"Posted") -> 0
A29: WEEKLY NUMBERS (from Monday's report)
A30: Week of | D30: Claude's Monday report lists these. Type them in, or have Claude update this sheet if the Google Sheets connector is on.
A31: Sponsorship paid so far ($)
A32: Sponsorship signed, not paid ($)
A33: Sponsor follow-ups due
A34: Gym inquiries last week
A35: Free trials last week
A36: New members last week
A37: Tickets sold for next show
A38: Tickets needed to break even

Sheet Tasks
A1: TASKS
A2: Everything the team has to do, one row each. Claude's morning report reads this. Mark Done and the date when it's finished.
A4: Task | B4: Business | C4: Owner | D4: Due | E4: Priority | F4: Status | G4: Overdue? | H4: Added | I4: Done on | J4: Notes
A5: Open BBG's CRA payroll account (RP) if it isn't done yet: the Canada Summer Jobs form asks for the payroll number | B5: BBG | C5: Cody | D5: =IF('Start Here'!$C$12="","",'Start Here'!$C$12+2) | E5: High | F5: To do | G5: =IF(OR(A5="",F5="Done",D5=""),"",IF(D5<TODAY(),"OVERDUE",IF(D5=TODAY(),"TODAY",""))) | H5: =IF('Start Here'!$C$12="","",'Start Here'!$C$12)
A6: Set up GCOS and submit Canada Summer Jobs 2027 from the draft (Command Centre > CSJ 2027 Application Draft). It opened Oct 27; the close date isn't published (the 2026 call closed Dec 11), so submit early | B6: BBG | C6: Cody | D6: =IF('Start Here'!$C$12="","",'Start Here'!$C$12+14) | E6: High | F6: To do | G6: =IF(OR(A6="",F6="Done",D6=""),"",IF(D6<TODAY(),"OVERDUE",IF(D6=TODAY(),"TODAY",""))) | H6: =IF('Start Here'!$C$12="","",'Start Here'!$C$12)
A7: Change the CCCL Google password now that Kyle's setup is done, and check 2-Step Verification is on | B7: Office | C7: Cody | D7: =IF('Start Here'!$C$12="","",'Start Here'!$C$12+1) | E7: High | F7: To do | G7: =IF(OR(A7="",F7="Done",D7=""),"",IF(D7<TODAY(),"OVERDUE",IF(D7=TODAY(),"TODAY",""))) | H7: =IF('Start Here'!$C$12="","",'Start Here'!$C$12)
A8: Check the morning report arrived in Gmail drafts with the laptop shut overnight | B8: Office | C8: Cody | D8: =IF('Start Here'!$C$12="","",'Start Here'!$C$12+1) | E8: High | F8: To do | G8: =IF(OR(A8="",F8="Done",D8=""),"",IF(D8<TODAY(),"OVERDUE",IF(D8=TODAY(),"TODAY",""))) | H8: =IF('Start Here'!$C$12="","",'Start Here'!$C$12)
A9: Second Chance: make its own Gmail, upload the four Second Chance files to its Drive, share the folder with the board and with ontario.cccl@gmail.com (Handoff Guide, section 4) | B9: Second Chance | C9: Cody | D9: =IF('Start Here'!$C$12="","",'Start Here'!$C$12+7) | E9: High | F9: To do | G9: =IF(OR(A9="",F9="Done",D9=""),"",IF(D9<TODAY(),"OVERDUE",IF(D9=TODAY(),"TODAY",""))) | H9: =IF('Start Here'!$C$12="","",'Start Here'!$C$12)
A10: Second Chance: check where the incorporation filing stands and confirm the board (Second Chance Tracker, Setup and Board tabs) | B10: Second Chance | C10: Cody | D10: =IF('Start Here'!$C$12="","",'Start Here'!$C$12+7) | E10: High | F10: To do | G10: =IF(OR(A10="",F10="Done",D10=""),"",IF(D10<TODAY(),"OVERDUE",IF(D10=TODAY(),"TODAY",""))) | H10: =IF('Start Here'!$C$12="","",'Start Here'!$C$12)
A11: Second Chance: ask a partner charity about leading a United Way application (due Dec 11) | B11: Second Chance | C11: Cody | D11: 46357 | E11: Normal | F11: To do | G11: =IF(OR(A11="",F11="Done",D11=""),"",IF(D11<TODAY(),"OVERDUE",IF(D11=TODAY(),"TODAY",""))) | H11: =IF('Start Here'!$C$12="","",'Start Here'!$C$12)
A12: Add a free first class option to the Gymdesk signup page: one class of any kind (boxing, kickboxing, jiu-jitsu, wrestling, MMA) | B12: BBG | C12: Cody | D12: =IF('Start Here'!$C$12="","",'Start Here'!$C$12+7) | E12: High | F12: To do | G12: =IF(OR(A12="",F12="Done",D12=""),"",IF(D12<TODAY(),"OVERDUE",IF(D12=TODAY(),"TODAY",""))) | H12: =IF('Start Here'!$C$12="","",'Start Here'!$C$12)
A13: Thank the 2026 sponsors and gym-wall supporters, and give them first pick for 2027 | B13: CCCL | C13: Cody | D13: =IF('Start Here'!$C$12="","",'Start Here'!$C$12+10) | E13: Normal | F13: To do | G13: =IF(OR(A13="",F13="Done",D13=""),"",IF(D13<TODAY(),"OVERDUE",IF(D13=TODAY(),"TODAY",""))) | H13: =IF('Start Here'!$C$12="","",'Start Here'!$C$12)
A14: Call the top venues on the Compare tab for capacity, full event price, 2027 dates and bar terms | B14: CCCL | C14: Cody | D14: =IF('Start Here'!$C$12="","",'Start Here'!$C$12+14) | E14: High | F14: To do | G14: =IF(OR(A14="",F14="Done",D14=""),"",IF(D14<TODAY(),"OVERDUE",IF(D14=TODAY(),"TODAY",""))) | H14: =IF('Start Here'!$C$12="","",'Start Here'!$C$12)
A15: Decide if a 2027 show is adults-only (19+): the 19+ Show Check tab shows what CCCL needs from the bar | B15: CCCL | C15: Cody | D15: =IF('Start Here'!$C$12="","",'Start Here'!$C$12+21) | E15: High | F15: To do | G15: =IF(OR(A15="",F15="Done",D15=""),"",IF(D15<TODAY(),"OVERDUE",IF(D15=TODAY(),"TODAY",""))) | H15: =IF('Start Here'!$C$12="","",'Start Here'!$C$12)
A16: Ask the Ontario Athletics Commission whether CCCL needs a single-event permit ($600) or a tournament permit ($1,600) for an 8-12 bout card with youth grappling | B16: CCCL | C16: Cody | D16: =IF('Start Here'!$C$12="","",'Start Here'!$C$12+14) | E16: Normal | F16: To do | G16: =IF(OR(A16="",F16="Done",D16=""),"",IF(D16<TODAY(),"OVERDUE",IF(D16=TODAY(),"TODAY",""))) | H16: =IF('Start Here'!$C$12="","",'Start Here'!$C$12)
A17: Make the fighter sign-up Google Form (template 3 in the Fight Night Templates) | B17: CCCL | C17: Cody | D17: =IF('Start Here'!$C$12="","",'Start Here'!$C$12+21) | E17: Normal | F17: To do | G17: =IF(OR(A17="",F17="Done",D17=""),"",IF(D17<TODAY(),"OVERDUE",IF(D17=TODAY(),"TODAY",""))) | H17: =IF('Start Here'!$C$12="","",'Start Here'!$C$12)
A18: Import the 16 CCCL starter designs into Canva and save them as CCCL templates | B18: CCCL | C18: Kyle | D18: =IF('Start Here'!$C$12="","",'Start Here'!$C$12+14) | E18: Normal | F18: To do | G18: =IF(OR(A18="",F18="Done",D18=""),"",IF(D18<TODAY(),"OVERDUE",IF(D18=TODAY(),"TODAY",""))) | H18: =IF('Start Here'!$C$12="","",'Start Here'!$C$12)
A19: Sign and date the health and safety policy and the violence and harassment policy (BBG First Employee Basics) | B19: BBG | C19: Cody | D19: =IF('Start Here'!$C$12="","",'Start Here'!$C$12+30) | E19: Normal | F19: To do | G19: =IF(OR(A19="",F19="Done",D19=""),"",IF(D19<TODAY(),"OVERDUE",IF(D19=TODAY(),"TODAY",""))) | H19: =IF('Start Here'!$C$12="","",'Start Here'!$C$12)
A20: Before the summer student starts: WSIB or insurance, posters, awareness training, first aid kit (BBG First Employee Basics checklist) | B20: BBG | C20: Cody | D20: =IF('Start Here'!$C$12="","",'Start Here'!$C$12+180) | E20: Normal | F20: To do | G20: =IF(OR(A20="",F20="Done",D20=""),"",IF(D20<TODAY(),"OVERDUE",IF(D20=TODAY(),"TODAY",""))) | H20: =IF('Start Here'!$C$12="","",'Start Here'!$C$12)
A21: Check whether BBG is registered on Transfer Payment Ontario (most Ontario grants need it) | B21: Office | C21: Cody | D21: =IF('Start Here'!$C$12="","",'Start Here'!$C$12+14) | E21: Normal | F21: To do | G21: =IF(OR(A21="",F21="Done",D21=""),"",IF(D21<TODAY(),"OVERDUE",IF(D21=TODAY(),"TODAY",""))) | H21: =IF('Start Here'!$C$12="","",'Start Here'!$C$12)
A22: Paste last month's bank export into the Money Summary (delete the account-number column first) and sort the Check lines | B22: Office | C22: Cody | D22: =IF('Start Here'!$C$12="","",'Start Here'!$C$12+14) | E22: Normal | F22: To do | G22: =IF(OR(A22="",F22="Done",D22=""),"",IF(D22<TODAY(),"OVERDUE",IF(D22=TODAY(),"TODAY",""))) | H22: =IF('Start Here'!$C$12="","",'Start Here'!$C$12)
A23: Monthly backup: download the Bancroft Boxing folder from Drive to the USB drive (Workstation Plan, section 7) | B23: Office | C23: Cody | D23: =IF('Start Here'!$C$12="","",'Start Here'!$C$12+30) | E23: Normal | F23: To do | G23: =IF(OR(A23="",F23="Done",D23=""),"",IF(D23<TODAY(),"OVERDUE",IF(D23=TODAY(),"TODAY",""))) | H23: =IF('Start Here'!$C$12="","",'Start Here'!$C$12)
A24: Decide whether to register BBG with Boxing Ontario (needed for KidSport to cover kids' fees, and sets coach and insurance rules) | B24: BBG | C24: Cody | D24: =IF('Start Here'!$C$12="","",'Start Here'!$C$12+30) | E24: Normal | F24: To do | G24: =IF(OR(A24="",F24="Done",D24=""),"",IF(D24<TODAY(),"OVERDUE",IF(D24=TODAY(),"TODAY",""))) | H24: =IF('Start Here'!$C$12="","",'Start Here'!$C$12)
A25: NCCP training for the coaches who don't have it yet (the Community Coaching Grant can help) | B25: BBG | C25: Cody | D25: =IF('Start Here'!$C$12="","",'Start Here'!$C$12+45) | E25: Normal | F25: To do | G25: =IF(OR(A25="",F25="Done",D25=""),"",IF(D25<TODAY(),"OVERDUE",IF(D25=TODAY(),"TODAY",""))) | H25: =IF('Start Here'!$C$12="","",'Start Here'!$C$12)
A26: Add the kids and youth to the Skills Passport roster (first names only) and start logging skills | B26: BBG | C26: Cody | D26: =IF('Start Here'!$C$12="","",'Start Here'!$C$12+21) | E26: Normal | F26: To do | G26: =IF(OR(A26="",F26="Done",D26=""),"",IF(D26<TODAY(),"OVERDUE",IF(D26=TODAY(),"TODAY",""))) | H26: =IF('Start Here'!$C$12="","",'Start Here'!$C$12)
A27: Athlete brand: make the Facebook athlete page, switch Instagram to a Creator account, and film the first four Constrictor Tips | B27: Athlete brand | C27: Cody | D27: =IF('Start Here'!$C$12="","",'Start Here'!$C$12+7) | E27: Normal | F27: To do | G27: =IF(OR(A27="",F27="Done",D27=""),"",IF(D27<TODAY(),"OVERDUE",IF(D27=TODAY(),"TODAY",""))) | H27: =IF('Start Here'!$C$12="","",'Start Here'!$C$12)
A28: 30-day check-in with Kyle: what's used, what isn't, what's annoying | B28: Office | C28: Kyle | D28: =IF('Start Here'!$C$12="","",'Start Here'!$C$12+30) | E28: Normal | F28: To do | G28: =IF(OR(A28="",F28="Done",D28=""),"",IF(D28<TODAY(),"OVERDUE",IF(D28=TODAY(),"TODAY",""))) | H28: =IF('Start Here'!$C$12="","",'Start Here'!$C$12)
G29: =IF(OR(A29="",F29="Done",D29=""),"",IF(D29<TODAY(),"OVERDUE",IF(D29=TODAY(),"TODAY","")))
G30: =IF(OR(A30="",F30="Done",D30=""),"",IF(D30<TODAY(),"OVERDUE",IF(D30=TODAY(),"TODAY","")))
G31: =IF(OR(A31="",F31="Done",D31=""),"",IF(D31<TODAY(),"OVERDUE",IF(D31=TODAY(),"TODAY","")))
G32: =IF(OR(A32="",F32="Done",D32=""),"",IF(D32<TODAY(),"OVERDUE",IF(D32=TODAY(),"TODAY","")))
G33: =IF(OR(A33="",F33="Done",D33=""),"",IF(D33<TODAY(),"OVERDUE",IF(D33=TODAY(),"TODAY","")))
G34: =IF(OR(A34="",F34="Done",D34=""),"",IF(D34<TODAY(),"OVERDUE",IF(D34=TODAY(),"TODAY","")))
G35: =IF(OR(A35="",F35="Done",D35=""),"",IF(D35<TODAY(),"OVERDUE",IF(D35=TODAY(),"TODAY","")))
G36: =IF(OR(A36="",F36="Done",D36=""),"",IF(D36<TODAY(),"OVERDUE",IF(D36=TODAY(),"TODAY","")))
G37: =IF(OR(A37="",F37="Done",D37=""),"",IF(D37<TODAY(),"OVERDUE",IF(D37=TODAY(),"TODAY","")))
G38: =IF(OR(A38="",F38="Done",D38=""),"",IF(D38<TODAY(),"OVERDUE",IF(D38=TODAY(),"TODAY","")))
G39: =IF(OR(A39="",F39="Done",D39=""),"",IF(D39<TODAY(),"OVERDUE",IF(D39=TODAY(),"TODAY","")))
G40: =IF(OR(A40="",F40="Done",D40=""),"",IF(D40<TODAY(),"OVERDUE",IF(D40=TODAY(),"TODAY","")))
... G404: =IF(OR(A404="",F404="Done",D404=""),"",IF(D404<TODAY(),"OVERDUE",IF(D404=TODAY(),"TODAY","")))

Sheet Approvals
A1: APPROVAL QUEUE
A2: Anything going out to the public, sponsors, venues or money waits here for a yes. Claude drafts; Cody (or staff, for routine gym replies) approves.
A4: Added | B4: What needs approving | C4: Business | D4: Type | E4: Prepared by | F4: Where it is | G4: Decision | H4: Decided on | I4: Days waiting | J4: Notes
A5: 46315 | B5: (Example) First 5 sponsor pitch drafts: gym-wall sponsors | C5: CCCL | D5: Sponsor pitch | E5: Claude | F5: Gmail drafts folder | G5: Waiting | I5: =IF(OR(B5="",A5="",G5<>"Waiting"),"",MAX(0,TODAY()-A5)) -> 7 | J5: Example row showing the format. Replace or delete it.
I6: =IF(OR(B6="",A6="",G6<>"Waiting"),"",MAX(0,TODAY()-A6))
I7: =IF(OR(B7="",A7="",G7<>"Waiting"),"",MAX(0,TODAY()-A7))
I8: =IF(OR(B8="",A8="",G8<>"Waiting"),"",MAX(0,TODAY()-A8))
I9: =IF(OR(B9="",A9="",G9<>"Waiting"),"",MAX(0,TODAY()-A9))
I10: =IF(OR(B10="",A10="",G10<>"Waiting"),"",MAX(0,TODAY()-A10))
I11: =IF(OR(B11="",A11="",G11<>"Waiting"),"",MAX(0,TODAY()-A11))
I12: =IF(OR(B12="",A12="",G12<>"Waiting"),"",MAX(0,TODAY()-A12))
I13: =IF(OR(B13="",A13="",G13<>"Waiting"),"",MAX(0,TODAY()-A13))
I14: =IF(OR(B14="",A14="",G14<>"Waiting"),"",MAX(0,TODAY()-A14))
I15: =IF(OR(B15="",A15="",G15<>"Waiting"),"",MAX(0,TODAY()-A15))
I16: =IF(OR(B16="",A16="",G16<>"Waiting"),"",MAX(0,TODAY()-A16))
I17: =IF(OR(B17="",A17="",G17<>"Waiting"),"",MAX(0,TODAY()-A17))
... I304: =IF(OR(B304="",A304="",G304<>"Waiting"),"",MAX(0,TODAY()-A304))

Sheet Content Calendar
A1: CONTENT CALENDAR
A2: Planned posts for BBG and CCCL. Claude's social skill drafts them; someone approves; then post and mark Posted. No photos of kids without a parent's OK. First names only.
A4: Date | B4: Business | C4: Platform | D4: Post type | E4: Draft | F4: Photo / video needed | G4: Status | H4: Approved by | I4: Notes
A5: =IF('Start Here'!$C$12="","",'Start Here'!$C$12-WEEKDAY('Start Here'!$C$12,2)+8+0) | B5: BBG | C5: Facebook + Instagram | D5: Class of the week | E5: Never boxed before? Our Monday boxing class (4-5pm) starts with the basics: stance, jab, footwork. Your first class is free. Sign up at bancroft-boxing-grappling.gymdesk.com/signup or message us. 🥊 | F5: Clip of the 4pm class warming up (adults only, or kids with parent OK) | G5: Drafted | I5: Starter draft from Kyle. Check times against Gymdesk before posting.
A6: =IF('Start Here'!$C$12="","",'Start Here'!$C$12-WEEKDAY('Start Here'!$C$12,2)+8+0) | B6: Cody | C6: Facebook + Instagram | D6: Constrictor Tip | E6: "My first pro win came by rear naked choke in Edmonton, 2016. Here's the grip detail that made it work." Then: "Want to learn it properly? First class at BBG is free." | F6: 45-sec RNC grip demo on an adult partner, slow, from the side | G6: Drafted | I6: Starter draft from Kyle. Check times against Gymdesk before posting.
A7: =IF('Start Here'!$C$12="","",'Start Here'!$C$12-WEEKDAY('Start Here'!$C$12,2)+8+2) | B7: BBG | C7: Facebook + Instagram | D7: Free trial | E7: Your first class at Bancroft Boxing & Grappling is FREE. Boxing, wrestling, jiu-jitsu, kickboxing and MMA, with boxing for kids from about 4. After that it's $20 a drop-in or $25 for the week. Sign up: bancroft-boxing-grappling.gymdesk.com/signup | F7: Wide shot of the gym | G7: Drafted | I7: Starter draft from Kyle. Check times against Gymdesk before posting.
A8: =IF('Start Here'!$C$12="","",'Start Here'!$C$12-WEEKDAY('Start Here'!$C$12,2)+8+2) | B8: Cody | C8: Facebook + Instagram | D8: Behind the scenes | E8: "Wednesdays: boxing at 4, kids at 5:15, women's boxing at 7. In between, I'm answering messages about the next show." | F8: Clips from the day with no kids' faces unless a parent's said yes | G8: Drafted | I8: Starter draft from Kyle. Check times against Gymdesk before posting.
A9: =IF('Start Here'!$C$12="","",'Start Here'!$C$12-WEEKDAY('Start Here'!$C$12,2)+8+4) | B9: BBG | C9: Facebook + Instagram | D9: Coach spotlight | E9: Meet [coach first name, e.g. Sean or Jordan, who help coach wrestling]. [One line on what they coach and their background]. Catch them on [day] at [time]. | F9: Photo of the coach (ask them first) | G9: Drafted | I9: Starter draft from Kyle. Check times against Gymdesk before posting.
A10: =IF('Start Here'!$C$12="","",'Start Here'!$C$12-WEEKDAY('Start Here'!$C$12,2)+8+4) | B10: Cody | C10: Facebook + Instagram | D10: Get back up | E10: "In 2016 I left Bancroft to fight pro in Alberta. Here's what those fights taught me: [Cody: one lesson in your words]." | F10: A photo from the Alberta fights | G10: Drafted | I10: Starter draft from Kyle. Check times against Gymdesk before posting.
A11: =IF('Start Here'!$C$12="","",'Start Here'!$C$12-WEEKDAY('Start Here'!$C$12,2)+8+7) | B11: BBG | C11: Facebook + Instagram | D11: Class of the week | E11: Kids Boxing, Wednesdays 5:15-6:15pm. Fitness, focus and confidence, coached by people who care. First class free for new kids. Parents: sign up and do the waiver at bancroft-boxing-grappling.gymdesk.com/signup | F11: Kids class photo ONLY with parents' OK, or the empty mats and bags | G11: Drafted | I11: Starter draft from Kyle. Check times against Gymdesk before posting.
A12: =IF('Start Here'!$C$12="","",'Start Here'!$C$12-WEEKDAY('Start Here'!$C$12,2)+8+7) | B12: Cody | C12: Facebook + Instagram | D12: Constrictor Tip | E12: "The sprawl: the first move I learned on the North Hastings wrestling mats. It still saves me every week." | F12: Sprawl from a shot, three angles | G12: Drafted | I12: Starter draft from Kyle. Check times against Gymdesk before posting.
A13: =IF('Start Here'!$C$12="","",'Start Here'!$C$12-WEEKDAY('Start Here'!$C$12,2)+8+9) | B13: CCCL | C13: Facebook + Instagram | D13: Announcement | E13: 400 tickets and 15 local sponsors at our first show. The Cottage Country Combat League is coming back in 2027, and sponsor spots are open now. Message Cody to put your name cage-side. | F13: Best photo from CCCL 1 in Haliburton | G13: Drafted | I13: Starter draft from Kyle. Check times against Gymdesk before posting.
A14: =IF('Start Here'!$C$12="","",'Start Here'!$C$12-WEEKDAY('Start Here'!$C$12,2)+8+9) | B14: Cody | C14: Facebook + Instagram | D14: Behind the scenes | E14: "We're calling 8 to 10 venues to book CCCL's 2027 shows. Where should we fight next? Tell me your town." | F14: Short clip at the desk on a call, or the venue list | G14: Drafted | I14: Starter draft from Kyle. Check times against Gymdesk before posting.
A15: =IF('Start Here'!$C$12="","",'Start Here'!$C$12-WEEKDAY('Start Here'!$C$12,2)+8+11) | B15: BBG | C15: Facebook + Instagram | D15: Training clip | E15: Friday pad work. [One line about the drill]. Come try it: first class free. | F15: 15-30 sec pad-work clip | G15: Drafted | I15: Starter draft from Kyle. Check times against Gymdesk before posting.
A16: =IF('Start Here'!$C$12="","",'Start Here'!$C$12-WEEKDAY('Start Here'!$C$12,2)+8+11) | B16: Cody | C16: Facebook + Instagram | D16: Get back up | E16: "Why I opened a gym in Bancroft: we're not just running a gym, we're building a platform for local talent. [Cody: the moment you decided]." | F16: The gym, empty, before a class | G16: Drafted | I16: Starter draft from Kyle. Check times against Gymdesk before posting.
A17: =IF('Start Here'!$C$12="","",'Start Here'!$C$12-WEEKDAY('Start Here'!$C$12,2)+8+14) | B17: BBG | C17: Facebook + Instagram | D17: Class of the week | E17: Women's Boxing: Wednesdays 7pm and Thursdays 6pm. A women-only class for women and girls 16+, all levels welcome. First class is on us. | F17: Photo from the women's class (ask everyone in it) | G17: Drafted | I17: Starter draft from Kyle. Check times against Gymdesk before posting.
A18: =IF('Start Here'!$C$12="","",'Start Here'!$C$12-WEEKDAY('Start Here'!$C$12,2)+8+14) | B18: Cody | C18: Facebook + Instagram | D18: Constrictor Tip | E18: "Every beginner's first question: how do I throw a jab? Three things to fix today." | F18: Jab from stance, front and side | G18: Drafted | I18: Starter draft from Kyle. Check times against Gymdesk before posting.
A19: =IF('Start Here'!$C$12="","",'Start Here'!$C$12-WEEKDAY('Start Here'!$C$12,2)+8+16) | B19: BBG | C19: Facebook + Instagram | D19: Member win | E19: [First name] [what they achieved: first month, first competition, a goal]. Proud of you! 👊 | F19: Photo with permission | G19: Drafted | I19: Starter draft from Kyle. Check times against Gymdesk before posting.
A20: =IF('Start Here'!$C$12="","",'Start Here'!$C$12-WEEKDAY('Start Here'!$C$12,2)+8+16) | B20: Cody | C20: Facebook + Instagram | D20: Behind the scenes | E20: "Friday competition class: this is what fight prep looks like." | F20: Adults in the competition class, with their OK | G20: Drafted | I20: Starter draft from Kyle. Check times against Gymdesk before posting.
A21: =IF('Start Here'!$C$12="","",'Start Here'!$C$12-WEEKDAY('Start Here'!$C$12,2)+8+18) | B21: CCCL | C21: Facebook + Instagram | D21: Behind the scenes | E21: Planning CCCL 2027. Which town should we hit next: Haliburton, Bancroft, Peterborough, Lindsay or somewhere new? Drop it in the comments. | F21: None needed | G21: Drafted | I21: Starter draft from Kyle. Check times against Gymdesk before posting.
A22: =IF('Start Here'!$C$12="","",'Start Here'!$C$12-WEEKDAY('Start Here'!$C$12,2)+8+18) | B22: Cody | C22: Facebook + Instagram | D22: Announcement | E22: "May 2, 2026: 400 tickets sold for the first Cottage Country Combat League show in Haliburton. Thank you. Next one's being booked now." | F22: Best photos from May 2 (official results only, fighters' OK) | G22: Drafted | I22: Starter draft from Kyle. Check times against Gymdesk before posting.
A23: =IF('Start Here'!$C$12="","",'Start Here'!$C$12-WEEKDAY('Start Here'!$C$12,2)+8+21) | B23: BBG | C23: Facebook + Instagram | D23: Class of the week | E23: No-gi Jiu-Jitsu, Tuesdays 4-6pm. Learn to control, escape and submit. Great for self-defence. First class free. | F23: Grappling clip (adults) | G23: Drafted | I23: Starter draft from Kyle. Check times against Gymdesk before posting.
A24: =IF('Start Here'!$C$12="","",'Start Here'!$C$12-WEEKDAY('Start Here'!$C$12,2)+8+21) | B24: Cody | C24: Facebook + Instagram | D24: Constrictor Tip | E24: "Breakfalls: the first thing everyone learns at BBG, kids and adults. Here's why." | F24: Cody demonstrating alone on the mats | G24: Drafted | I24: Starter draft from Kyle. Check times against Gymdesk before posting.
A25: =IF('Start Here'!$C$12="","",'Start Here'!$C$12-WEEKDAY('Start Here'!$C$12,2)+8+23) | B25: BBG | C25: Facebook + Instagram | D25: Free trial | E25: Thinking about it? Just come try one class, free. Message us or drop by 17 Snow Road. | F25: Gym photo | G25: Drafted | I25: Starter draft from Kyle. Check times against Gymdesk before posting.
A26: =IF('Start Here'!$C$12="","",'Start Here'!$C$12-WEEKDAY('Start Here'!$C$12,2)+8+23) | B26: Cody | C26: Facebook + Instagram | D26: Behind the scenes | E26: "Ask me anything about starting to train. I'll answer in my stories this week." | F26: Instagram question sticker; answer with quick selfie clips | G26: Drafted | I26: Starter draft from Kyle. Check times against Gymdesk before posting.
A27: =IF('Start Here'!$C$12="","",'Start Here'!$C$12-WEEKDAY('Start Here'!$C$12,2)+8+25) | B27: BBG | C27: Facebook + Instagram | D27: Training clip | E27: Wrestling, Mondays 3:20pm. Where it all starts. [one line]. | F27: Wrestling clip (kids only with parents' OK) | G27: Drafted | I27: Starter draft from Kyle. Check times against Gymdesk before posting.
A28: =IF('Start Here'!$C$12="","",'Start Here'!$C$12-WEEKDAY('Start Here'!$C$12,2)+8+25) | B28: Cody | C28: Facebook + Instagram | D28: Get back up | E28: "If this year knocked you down, come get back up. Your first class is free." Link: the Gymdesk signup. | F28: Cody hitting pads, then looking at the camera | G28: Drafted | I28: Starter draft from Kyle. Check times against Gymdesk before posting.

Sheet Links
A1: THE OTHER SHEETS
A2: Once each file is in Google Drive, paste its link here so everyone can find it from one place.
A4: File | B4: Google Drive link (paste it here) | C4: What it's for
A5: CCCL Event Profit Predictor | C5: Compare towns and venues, break-even, stress test, 25-town scout, ticket tracker
A6: CCCL Sponsorship Pipeline | C6: 2026 sponsors, 70 local prospects, national brands, stages, follow-ups, delivery checklist
A7: BBG Leads & Trials | C7: Gym inquiries to free trial to member
A8: CCCL Fight Night Kit | C8: Fighters, bout card, countdown, volunteers, production, run of show, press list, results
A9: CCCL Fight Night Templates | C9: Gym outreach, fighter sign-up form, info sheet, announcer script, press releases, promo copy
A10: CCCL Fighter Package | C10: The 4-page packet each confirmed fighter gets through their coach (fill the yellow fields)
A11: CCCL Marketing Kit | C11: Show campaign, ticket sources and tracking links, ad tests, poster drop, shot list, Canva kit
A12: CCCL 2027 Sponsor Packages (PDF) | C12: Attach to sponsor pitches
A13: CCCL Sponsor Pitch Templates | C13: Email and message templates
A14: Staff Playbook | C14: How the team uses all of this
A15: The Constrictor AI Blueprint | C15: The big plan: all 60 jobs and the build order
A16: CCCL Brand Kit + Canva starter designs | C16: Colours, fonts, logo rules and the 16 designs to import into Canva
... A25: The Constrictor Funding Tracker | C25: Grants and programs, eligibility, deadlines and applications
